Workbook

Sheet CFSPres
D3: Violet St Consolidated | O3: Violet St Consolidated
D4: Pro Forma Cash Flow Statement | O4: Pro Forma Cash Flow Statement
D5: AOP 2024-2026 | O5: AOP 2024-2026
D6: Confidential | O6: Confidential
Q10: 2024 | R10: 2024 | S10: 2024 | T10: 2024
D11: Cash Flow Statement | F11: 2023 | G11: 2024 | H11: 2025 | I11: 2026 | J11: 2027 | K11: 2028 | L11: 2029 | O11: Cash Flow Statement | Q11: Q1-2024 | R11: Q2-2024 | S11: Q3-2024 | T11: Q4-2024 | W11: Ending Cash | X11: Jan | Y11: Feb | Z11: Mar | AA11: Apr | AB11: May | AC11: Jun | AD11: Jul | AE11: Aug | AF11: Sep | AG11: Oct | AH11: Nov | AI11: Dec
W12: 2024 | X12: =CFS!AG39 -> 5140932.8 | Y12: =CFS!AH39 -> 2788558.1 | Z12: =CFS!AI39 -> 1405842.1 | AA12: =CFS!AJ39 -> 615898.73 | AB12: =CFS!AK39 -> 259924.89 | AC12: =CFS!AL39 -> -359624.48 | AD12: =CFS!AM39 -> -589963.8 | AE12: =CFS!AN39 -> -1339462.6 | ... AI12: =CFS!AR39 -> -5193407.8
D13: Net Income | G13: =CFS!G13 -> -8434183.5 | H13: =CFS!H13 -> -6671615.1 | I13: =CFS!I13 -> -1328310.9 | J13: =CFS!J13 -> 1807692.6 | K13: =CFS!K13 -> 2454037.9 | L13: =CFS!L13 -> 15795750 | O13: Net Income | Q13: =CFS!P13 -> -1999280.5 | R13: =CFS!Q13 -> -2349700 | S13: =CFS!R13 -> -1821971.5 | T13: =CFS!S13 -> -2263231.5 | W13: 2025 | X13: =CFS!AS39 -> -5777953.6 | Y13: =CFS!AT39 -> -6862940.8 | Z13: =CFS!AU39 -> -7604997.2 | AA13: =CFS!AV39 -> -7466948.3 | AB13: =CFS!AW39 -> -8435124.8 | AC13: =CFS!AX39 -> -9033018.2 | AD13: =CFS!AY39 -> -9654373.9 | AE13: =CFS!AZ39 -> -10732057 | ... AI13: =CFS!BD39 -> -11471750
D14: Cash Flow from Operations | G14: =CFS!G24 -> -8869468.6 | H14: =CFS!H24 -> -5748342.2 | I14: =CFS!I24 -> -659127.97 | J14: =CFS!J24 -> -89949.102 | K14: =CFS!K24 -> -2568191.2 | L14: =CFS!L24 -> 9292968.3 | O14: Cash Flow from Operations | Q14: =CFS!P24 -> -3402363.8 | R14: =CFS!Q24 -> -1765466.5 | S14: =CFS!R24 -> -1597738.1 | T14: =CFS!S24 -> -2103900.2 | W14: 2026 | X14: =CFS!BE39 -> -14001595 | Y14: =CFS!BF39 -> -14993796 | Z14: =CFS!BG39 -> -14220877 | AA14: =CFS!BH39 -> -13070141 | AB14: =CFS!BI39 -> -13800764 | AC14: =CFS!BJ39 -> -13763692 | AD14: =CFS!BK39 -> -15367165 | AE14: =CFS!BL39 -> -16103198 | ... AI14: =CFS!BP39 -> -13105878
D16: Cash Flow from Investing | G16: =CFS!G29 -> -1547145 | H16: =CFS!H29 -> -530000 | I16: =CFS!I29 -> -975000 | J16: =CFS!J29 -> -350000 | K16: =CFS!K29 -> -700000 | L16: =CFS!L29 -> -350000 | O16: Cash Flow from Investing | Q16: =CFS!P29 -> -415000 | R16: =CFS!Q29 -> 1.4551915e-11 | S16: =CFS!R29 -> 1.2369128e-10 | T16: =CFS!S29 -> -1132145
D18: Cash Flow from Financing | G18: =CFS!G34 -> 0 | H18: =CFS!H34 -> 0 | I18: =CFS!I34 -> 0 | J18: =CFS!J34 -> 0 | K18: =CFS!K34 -> 2000000 | L18: =CFS!L34 -> 0 | O18: Cash Flow from Financing | Q18: =CFS!P34 -> 0 | R18: =CFS!Q34 -> 0 | S18: =CFS!R34 -> 0 | T18: =CFS!S34 -> 0
D20: Change in Cash | G20: =CFS!G37 -> -10416614 | H20: =CFS!H37 -> -6278342.2 | I20: =CFS!I37 -> -1634128 | J20: =CFS!J37 -> -439949.1 | K20: =CFS!K37 -> -1268191.2 | L20: =CFS!L37 -> 8942968.3 | O20: Change in Cash | Q20: =CFS!P37 -> -3817363.8 | R20: =CFS!Q37 -> -1765466.5 | S20: =CFS!R37 -> -1597738.1 | T20: =CFS!S37 -> -3236045.2
D21: Beginning Cash Balance | G21: =CFS!G38 -> 5223205.9 | H21: =CFS!H38 -> -5193407.8 | I21: =CFS!I38 -> -11471750 | J21: =CFS!J38 -> -13105878 | K21: =CFS!K38 -> -13545827 | L21: =CFS!L38 -> -14814018 | O21: Beginning Cash Balance | Q21: =CFS!P38 -> 5223205.9 | R21: =CFS!Q38 -> 0 | S21: =CFS!R38 -> 0 | T21: =CFS!S38 -> 0
D22: Ending Cash Balance | F22: =CFS!F39 -> 5223205.9 | G22: =CFS!G39 -> -5193407.8 | H22: =CFS!H39 -> -11471750 | I22: =CFS!I39 -> -13105878 | J22: =CFS!J39 -> -13545827 | K22: =CFS!K39 -> -14814018 | L22: =CFS!L39 -> -5871050 | O22: Ending Cash Balance | Q22: =CFS!P39 -> 1405842.1 | R22: =CFS!Q39 -> -359624.48 | S22: =CFS!R39 -> -1957362.6 | T22: =CFS!S39 -> -5193407.8
D23: check | F23: =BS!F14-F22 -> 0 | G23: =CFS!G40 -> 0 | H23: =CFS!H40 -> 0 | I23: =CFS!I40 -> 0 | J23: =CFS!J40 -> 0 | K23: =CFS!K40 -> 0 | L23: =CFS!L40 -> 0 | O23: check | Q23: =CFS!P40 -> 0 | R23: =CFS!Q40 -> 6.9849193e-10 | S23: =CFS!R40 -> 0 | T23: =CFS!S40 -> 0
E2168: x
D2220: x | O2220: x

Sheet BSPres
D3: Violet St Consolidated
D4: Pro Forma Balance Sheet
D5: AOP 2024-2026
D6: Confidential
D11: Balance Sheet (in $Ms) | F11: 2023 | G11: 2024 | H11: 2025 | I11: 2026 | J11: 2027 | K11: 2028 | L11: 2029
D13: Assets
D14: Cash | F14: =+BS!F14 -> 5223205.9 | G14: =+BS!G14 -> -5193407.8 | H14: =+BS!H14 -> -11471750 | I14: =+BS!I14 -> -13105878 | J14: =+BS!J14 -> -13545827 | K14: =+BS!K14 -> -14814018 | L14: =+BS!L14 -> -5871050
D15: Total Current Assets | F15: =+BS!F21 -> 5908802.8 | G15: =+BS!G21 -> -3345538.2 | H15: =+BS!H21 -> -5787340.4 | I15: =+BS!I21 -> -608962.69 | J15: =+BS!J21 -> 13607300 | K15: =+BS!K21 -> 36037079 | L15: =+BS!L21 -> 44015779
D17: Total Other Assets | F17: =+BS!F28 -> 5671367.5 | G17: =+BS!G28 -> 6766464.1 | H17: =+BS!H28 -> 6206791.2 | I17: =+BS!I28 -> 5745416.7 | J17: =+BS!J28 -> 5087083.3 | K17: =+BS!K28 -> 2977500 | L17: =+BS!L28 -> 2445000
D18: Total Assets | F18: =+BS!F30 -> 11580170 | G18: =+BS!G30 -> 3420926 | H18: =+BS!H30 -> 419450.86 | I18: =+BS!I30 -> 5136454 | J18: =+BS!J30 -> 18694383 | K18: =+BS!K30 -> 39014579 | L18: =+BS!L30 -> 46460779
D21: Liabilities and Equity
D22: Accounts Payable | F22: =+BS!F34 -> 644400.83 | G22: =+BS!G34 -> 919340 | H22: =+BS!H34 -> 4589480 | I22: =+BS!I34 -> 10634794 | J22: =+BS!J34 -> 22385030 | K22: =+BS!K34 -> 40251188 | L22: =+BS!L34 -> 31901639
D23: Total Liabilities | F23: =+BS!F39 -> 742401.33 | G23: =+BS!G39 -> 1017340.5 | H23: =+BS!H39 -> 4687480.5 | I23: =+BS!I39 -> 10732794 | J23: =+BS!J39 -> 22483031 | K23: =+BS!K39 -> 40349189 | L23: =+BS!L39 -> 31999640
D25: Total Equity | F25: =+BS!F44 -> 10837769 | G25: =+BS!G44 -> 2403585.5 | H25: =+BS!H44 -> -4268029.6 | I25: =+BS!I44 -> -5596340.5 | J25: =+BS!J44 -> -3788648 | K25: =+BS!K44 -> -1334610 | L25: =+BS!L44 -> 14461140
D27: Total Liabilities & Equity | F27: =+BS!F46 -> 11580170 | G27: =+BS!G46 -> 3420926 | H27: =+BS!H46 -> 419450.86 | I27: =+BS!I46 -> 5136454 | J27: =+BS!J46 -> 18694383 | K27: =+BS!K46 -> 39014579 | L27: =+BS!L46 -> 46460779
D29: Variance Assets - Liab/Equity | F29: =F18-F27 -> 0 | G29: =G18-G27 -> 0 | H29: =H18-H27 -> 9.3132257e-10 | I29: =I18-I27 -> 0 | J29: =J18-J27 -> 0 | K29: =K18-K27 -> 0 | L29: =L18-L27 -> 0

Sheet BS
D3: Violet St Consolidated
D4: Pro Forma Balance Sheet
D5: AOP 2024-2026
D6: Confidential
Q10: ="Q"&ROUNDUP(MONTH(Q11)/3,0)&"-"&YEAR(Q11) -> Q1-2023 | R10: ="Q"&ROUNDUP(MONTH(R11)/3,0)&"-"&YEAR(R11) -> Q1-2023 | S10: ="Q"&ROUNDUP(MONTH(S11)/3,0)&"-"&YEAR(S11) -> Q1-2023 | T10: ="Q"&ROUNDUP(MONTH(T11)/3,0)&"-"&YEAR(T11) -> Q2-2023 | U10: ="Q"&ROUNDUP(MONTH(U11)/3,0)&"-"&YEAR(U11) -> Q2-2023 | V10: ="Q"&ROUNDUP(MONTH(V11)/3,0)&"-"&YEAR(V11) -> Q2-2023 | W10: ="Q"&ROUNDUP(MONTH(W11)/3,0)&"-"&YEAR(W11) -> Q3-2023 | X10: ="Q"&ROUNDUP(MONTH(X11)/3,0)&"-"&YEAR(X11) -> Q3-2023 | ... CZ10: ="Q"&ROUNDUP(MONTH(CZ11)/3,0)&"-"&YEAR(CZ11) -> Q2-2030
F11: 2023 | G11: 2024 | H11: 2025 | I11: 2026 | J11: 2027 | K11: 2028 | L11: 2029 | Q11: 44957 | R11: =EOMONTH(Q11,1) -> 44985 | S11: =EOMONTH(R11,1) -> 45016 | T11: =EOMONTH(S11,1) -> 45046 | U11: =EOMONTH(T11,1) -> 45077 | V11: =EOMONTH(U11,1) -> 45107 | W11: =EOMONTH(V11,1) -> 45138 | X11: =EOMONTH(W11,1) -> 45169 | Y11: =EOMONTH(X11,1) -> 45199 | ... CZ11: =EOMONTH(CY11,1) -> 47603
D12: Assets
D14: Cash | F14: =AB14 -> 5223205.9 | G14: =AN14 -> -5193407.8 | H14: =AZ14 -> -11471750 | I14: =BL14 -> -13105878 | J14: =BX14 -> -13545827 | K14: =CJ14 -> -14814018 | L14: =CV14 -> -5871050 | Q14: =SUMIFS(ActBS!C$6:C$164,ActBS!$A$6:$A$164,$D14) -> 15260684 | R14: =SUMIFS(ActBS!D$6:D$164,ActBS!$A$6:$A$164,$D14) -> 14914438 | S14: =SUMIFS(ActBS!E$6:E$164,ActBS!$A$6:$A$164,$D14) -> 14372314 | T14: =SUMIFS(ActBS!F$6:F$164,ActBS!$A$6:$A$164,$D14) -> 14077436 | U14: =SUMIFS(ActBS!G$6:G$164,ActBS!$A$6:$A$164,$D14) -> 13545354 | V14: =SUMIFS(ActBS!H$6:H$164,ActBS!$A$6:$A$164,$D14) -> 13025073 | W14: =SUMIFS(ActBS!I$6:I$164,ActBS!$A$6:$A$164,$D14) -> 12647800 | X14: =SUMIFS(ActBS!J$6:J$164,ActBS!$A$6:$A$164,$D14) -> 6839268.1 | ... AB14: =SUMIFS(ActBS!N$6:N$164,ActBS!$A$6:$A$164,$D14) -> 5223205.9 | AC14: =CFS!AG39 -> 5140932.8 | AD14: =CFS!AH39 -> 2788558.1 | AE14: =CFS!AI39 -> 1405842.1 | AF14: =CFS!AJ39 -> 615898.73 | AG14: =CFS!AK39 -> 259924.89 | AH14: =CFS!AL39 -> -359624.48 | AI14: =CFS!AM39 -> -589963.8 | AJ14: =CFS!AN39 -> -1339462.6 | ... CZ14: =CFS!DD39 -> 0
D15: Accounts Receivable | F15: =AB15 -> 146754.86 | G15: =AN15 -> 196600 | H15: =AZ15 -> 863000 | I15: =BL15 -> 1713525 | J15: =BX15 -> 4619500 | K15: =CJ15 -> 10451312 | L15: =CV15 -> 17836594 | Q15: =SUMIFS(ActBS!C$6:C$164,ActBS!$A$6:$A$164,$D15) -> 30690 | R15: =SUMIFS(ActBS!D$6:D$164,ActBS!$A$6:$A$164,$D15) -> 30690 | S15: =SUMIFS(ActBS!E$6:E$164,ActBS!$A$6:$A$164,$D15) -> 203961.29 | T15: =SUMIFS(ActBS!F$6:F$164,ActBS!$A$6:$A$164,$D15) -> 182201.43 | U15: =SUMIFS(ActBS!G$6:G$164,ActBS!$A$6:$A$164,$D15) -> 190946.43 | V15: =SUMIFS(ActBS!H$6:H$164,ActBS!$A$6:$A$164,$D15) -> 198206.43 | W15: =SUMIFS(ActBS!I$6:I$164,ActBS!$A$6:$A$164,$D15) -> 206951.43 | X15: =SUMIFS(ActBS!J$6:J$164,ActBS!$A$6:$A$164,$D15) -> 215696.43 | ... CZ15: =SUMIFS(ActBS!CL$6:CL$164,ActBS!$A$6:$A$164,$D15) -> 0
D16: Inventory | F16: =AB16 -> 1161.84 | G16: =AN16 -> 919340 | H16: =AZ16 -> 4589480 | I16: =BL16 -> 10634794 | J16: =BX16 -> 22385030 | K16: =CJ16 -> 40251188 | L16: =CV16 -> 31901639 | Q16: =SUMIFS(ActBS!C$6:C$164,ActBS!$A$6:$A$164,$D16) -> 0 | R16: =SUMIFS(ActBS!D$6:D$164,ActBS!$A$6:$A$164,$D16) -> 0 | S16: =SUMIFS(ActBS!E$6:E$164,ActBS!$A$6:$A$164,$D16) -> 0 | T16: =SUMIFS(ActBS!F$6:F$164,ActBS!$A$6:$A$164,$D16) -> 0 | U16: =SUMIFS(ActBS!G$6:G$164,ActBS!$A$6:$A$164,$D16) -> 0 | V16: =SUMIFS(ActBS!H$6:H$164,ActBS!$A$6:$A$164,$D16) -> 0 | W16: =SUMIFS(ActBS!I$6:I$164,ActBS!$A$6:$A$164,$D16) -> 0 | X16: =SUMIFS(ActBS!J$6:J$164,ActBS!$A$6:$A$164,$D16) -> 0 | ... CZ16: =SUMIFS(ActBS!CL$6:CL$164,ActBS!$A$6:$A$164,$D16) -> 0
D17: Prepaid Expenses | F17: =AB17 -> 101582.23 | G17: =AN17 -> 684915.56 | H17: =AZ17 -> 184915.56 | I17: =BL17 -> 101582.23 | J17: =BX17 -> 101582.23 | K17: =CJ17 -> 101582.23 | L17: =CV17 -> 101582.23 | Q17: =SUMIFS(ActBS!C$6:C$164,ActBS!$A$6:$A$164,$D17) -> 103446.18 | R17: =SUMIFS(ActBS!D$6:D$164,ActBS!$A$6:$A$164,$D17) -> 88779.32 | S17: =SUMIFS(ActBS!E$6:E$164,ActBS!$A$6:$A$164,$D17) -> 96112.46 | T17: =SUMIFS(ActBS!F$6:F$164,ActBS!$A$6:$A$164,$D17) -> 88859.33 | U17: =SUMIFS(ActBS!G$6:G$164,ActBS!$A$6:$A$164,$D17) -> 198797.41 | V17: =SUMIFS(ActBS!H$6:H$164,ActBS!$A$6:$A$164,$D17) -> 187655.66 | W17: =SUMIFS(ActBS!I$6:I$164,ActBS!$A$6:$A$164,$D17) -> 169055.8 | X17: =SUMIFS(ActBS!J$6:J$164,ActBS!$A$6:$A$164,$D17) -> 200802.96 | ... CZ17: =SUMIFS(ActBS!CL$6:CL$164,ActBS!$A$6:$A$164,$D17) -> 0
D18: Intercompany Receivable | F18: =AB18 -> 0 | G18: =AN18 -> 0 | H18: =AZ18 -> 0 | I18: =BL18 -> 0 | J18: =BX18 -> 0 | K18: =CJ18 -> 0 | L18: =CV18 -> 0 | Q18: =SUMIFS(ActBS!C$6:C$164,ActBS!$A$6:$A$164,$D18) -> 0 | R18: =SUMIFS(ActBS!D$6:D$164,ActBS!$A$6:$A$164,$D18) -> 0 | S18: =SUMIFS(ActBS!E$6:E$164,ActBS!$A$6:$A$164,$D18) -> 0 | T18: =SUMIFS(ActBS!F$6:F$164,ActBS!$A$6:$A$164,$D18) -> 0 | U18: =SUMIFS(ActBS!G$6:G$164,ActBS!$A$6:$A$164,$D18) -> 0 | V18: =SUMIFS(ActBS!H$6:H$164,ActBS!$A$6:$A$164,$D18) -> 0 | W18: =SUMIFS(ActBS!I$6:I$164,ActBS!$A$6:$A$164,$D18) -> 0 | X18: =SUMIFS(ActBS!J$6:J$164,ActBS!$A$6:$A$164,$D18) -> 0 | ... CZ18: =SUMIFS(ActBS!CL$6:CL$164,ActBS!$A$6:$A$164,$D18) -> 0
D19: Other Current Assets | F19: =AB19 -> 436098 | G19: =AN19 -> 47014 | H19: =AZ19 -> 47014 | I19: =BL19 -> 47014 | J19: =BX19 -> 47014 | K19: =CJ19 -> 47014 | L19: =CV19 -> 47014 | Q19: =SUMIFS(ActBS!C$6:C$164,ActBS!$A$6:$A$164,$D19) -> 0 | R19: =SUMIFS(ActBS!D$6:D$164,ActBS!$A$6:$A$164,$D19) -> 0 | S19: =SUMIFS(ActBS!E$6:E$164,ActBS!$A$6:$A$164,$D19) -> 0 | T19: =SUMIFS(ActBS!F$6:F$164,ActBS!$A$6:$A$164,$D19) -> 0 | U19: =SUMIFS(ActBS!G$6:G$164,ActBS!$A$6:$A$164,$D19) -> 0 | V19: =SUMIFS(ActBS!H$6:H$164,ActBS!$A$6:$A$164,$D19) -> 0 | W19: =SUMIFS(ActBS!I$6:I$164,ActBS!$A$6:$A$164,$D19) -> 0 | X19: =SUMIFS(ActBS!J$6:J$164,ActBS!$A$6:$A$164,$D19) -> 0 | ... CZ19: =SUMIFS(ActBS!CL$6:CL$164,ActBS!$A$6:$A$164,$D19) -> 0
F20: =AB20 -> 0 | G20: =AN20 -> 0 | H20: =AZ20 -> 0 | I20: =BL20 -> 0 | J20: =BX20 -> 0 | K20: =CJ20 -> 0 | L20: =CV20 -> 0 | Q20: =SUMIFS(ActBS!C$6:C$164,ActBS!$A$6:$A$164,$D20) -> 0 | R20: =SUMIFS(ActBS!D$6:D$164,ActBS!$A$6:$A$164,$D20) -> 0 | S20: =SUMIFS(ActBS!E$6:E$164,ActBS!$A$6:$A$164,$D20) -> 0 | T20: =SUMIFS(ActBS!F$6:F$164,ActBS!$A$6:$A$164,$D20) -> 0 | U20: =SUMIFS(ActBS!G$6:G$164,ActBS!$A$6:$A$164,$D20) -> 0 | V20: =SUMIFS(ActBS!H$6:H$164,ActBS!$A$6:$A$164,$D20) -> 0 | W20: =SUMIFS(ActBS!I$6:I$164,ActBS!$A$6:$A$164,$D20) -> 0 | X20: =SUMIFS(ActBS!J$6:J$164,ActBS!$A$6:$A$164,$D20) -> 0 | ... CZ20: =SUMIFS(ActBS!CL$6:CL$164,ActBS!$A$6:$A$164,$D20) -> 0
D21: Total Current Assets | F21: =SUM(F14:F20) -> 5908802.8 | G21: =SUM(G14:G20) -> -3345538.2 | H21: =SUM(H14:H20) -> -5787340.4 | I21: =SUM(I14:I20) -> -608962.69 | J21: =SUM(J14:J20) -> 13607300 | K21: =SUM(K14:K20) -> 36037079 | L21: =SUM(L14:L20) -> 44015779 | Q21: =SUM(Q14:Q20) -> 15394820 | R21: =SUM(R14:R20) -> 15033907 | S21: =SUM(S14:S20) -> 14672387 | T21: =SUM(T14:T20) -> 14348497 | U21: =SUM(U14:U20) -> 13935098 | V21: =SUM(V14:V20) -> 13410935 | W21: =SUM(W14:W20) -> 13023807 | X21: =SUM(X14:X20) -> 7255767.5 | ... CZ21: =SUM(CZ14:CZ20) -> 0
D23: Fixed Assets, net | F23: =AB23 -> 378867.45 | G23: =AN23 -> 1473964.1 | H23: =AZ23 -> 914291.25 | I23: =BL23 -> 452916.67 | J23: =BX23 -> -205416.67 | K23: =CJ23 -> -315000 | L23: =CV23 -> -847500 | Q23: =SUMIFS(ActBS!C$6:C$164,ActBS!$A$6:$A$164,$D23) -> 95909.39 | R23: =SUMIFS(ActBS!D$6:D$164,ActBS!$A$6:$A$164,$D23) -> 184771.19 | S23: =SUMIFS(ActBS!E$6:E$164,ActBS!$A$6:$A$164,$D23) -> 225580.07 | T23: =SUMIFS(ActBS!F$6:F$164,ActBS!$A$6:$A$164,$D23) -> 225828.18 | U23: =SUMIFS(ActBS!G$6:G$164,ActBS!$A$6:$A$164,$D23) -> 246363.78 | V23: =SUMIFS(ActBS!H$6:H$164,ActBS!$A$6:$A$164,$D23) -> 295176.12 | W23: =SUMIFS(ActBS!I$6:I$164,ActBS!$A$6:$A$164,$D23) -> 304450.65 | X23: =SUMIFS(ActBS!J$6:J$164,ActBS!$A$6:$A$164,$D23) -> 306864.77 | ... CZ23: =SUMIFS(ActBS!CL$6:CL$164,ActBS!$A$6:$A$164,$D23) -> 0
D24: Intangibles | F24: =AB24 -> 0 | G24: =AN24 -> 0 | H24: =AZ24 -> 0 | I24: =BL24 -> 0 | J24: =BX24 -> 0 | K24: =CJ24 -> 0 | L24: =CV24 -> 0 | Q24: =SUMIFS(ActBS!C$6:C$164,ActBS!$A$6:$A$164,$D24) -> 175593.65 | R24: =SUMIFS(ActBS!D$6:D$164,ActBS!$A$6:$A$164,$D24) -> 180931.23 | S24: =SUMIFS(ActBS!E$6:E$164,ActBS!$A$6:$A$164,$D24) -> 113368.52 | T24: =SUMIFS(ActBS!F$6:F$164,ActBS!$A$6:$A$164,$D24) -> 112737.6 | U24: =SUMIFS(ActBS!G$6:G$164,ActBS!$A$6:$A$164,$D24) -> 103654.78 | V24: =SUMIFS(ActBS!H$6:H$164,ActBS!$A$6:$A$164,$D24) -> 88846.96 | W24: =SUMIFS(ActBS!I$6:I$164,ActBS!$A$6:$A$164,$D24) -> 74039.14 | X24: =SUMIFS(ActBS!J$6:J$164,ActBS!$A$6:$A$164,$D24) -> 59231.32 | ... CZ24: =SUMIFS(ActBS!CL$6:CL$164,ActBS!$A$6:$A$164,$D24) -> 0
D25: Notes Receivable | F25: =AB25 -> 2000000 | G25: =AN25 -> 2000000 | H25: =AZ25 -> 2000000 | I25: =BL25 -> 2000000 | J25: =BX25 -> 2000000 | K25: =CJ25 -> 0 | L25: =CV25 -> 0 | Q25: =SUMIFS(ActBS!C$6:C$164,ActBS!$A$6:$A$164,$D25) -> 0 | R25: =SUMIFS(ActBS!D$6:D$164,ActBS!$A$6:$A$164,$D25) -> 0 | S25: =SUMIFS(ActBS!E$6:E$164,ActBS!$A$6:$A$164,$D25) -> 0 | T25: =SUMIFS(ActBS!F$6:F$164,ActBS!$A$6:$A$164,$D25) -> 0 | U25: =SUMIFS(ActBS!G$6:G$164,ActBS!$A$6:$A$164,$D25) -> 0 | V25: =SUMIFS(ActBS!H$6:H$164,ActBS!$A$6:$A$164,$D25) -> 0 | W25: =SUMIFS(ActBS!I$6:I$164,ActBS!$A$6:$A$164,$D25) -> 0 | X25: =SUMIFS(ActBS!J$6:J$164,ActBS!$A$6:$A$164,$D25) -> 2000000 | ... CZ25: =SUMIFS(ActBS!CL$6:CL$164,ActBS!$A$6:$A$164,$D25) -> 0
D26: Investments | F26: =AB26 -> 3250000 | G26: =AN26 -> 3250000 | H26: =AZ26 -> 3250000 | I26: =BL26 -> 3250000 | J26: =BX26 -> 3250000 | K26: =CJ26 -> 3250000 | L26: =CV26 -> 3250000 | Q26: =SUMIFS(ActBS!C$6:C$164,ActBS!$A$6:$A$164,$D26) -> 0 | R26: =SUMIFS(ActBS!D$6:D$164,ActBS!$A$6:$A$164,$D26) -> 0 | S26: =SUMIFS(ActBS!E$6:E$164,ActBS!$A$6:$A$164,$D26) -> 0 | T26: =SUMIFS(ActBS!F$6:F$164,ActBS!$A$6:$A$164,$D26) -> 0 | U26: =SUMIFS(ActBS!G$6:G$164,ActBS!$A$6:$A$164,$D26) -> 0 | V26: =SUMIFS(ActBS!H$6:H$164,ActBS!$A$6:$A$164,$D26) -> 0 | W26: =SUMIFS(ActBS!I$6:I$164,ActBS!$A$6:$A$164,$D26) -> 0 | X26: =SUMIFS(ActBS!J$6:J$164,ActBS!$A$6:$A$164,$D26) -> 3250000 | ... CZ26: =SUMIFS(ActBS!CL$6:CL$164,ActBS!$A$6:$A$164,$D26) -> 0
D27: Other Assets | F27: =AB27 -> 42500 | G27: =AN27 -> 42500 | H27: =AZ27 -> 42500 | I27: =BL27 -> 42500 | J27: =BX27 -> 42500 | K27: =CJ27 -> 42500 | L27: =CV27 -> 42500 | Q27: =SUMIFS(ActBS!C$6:C$164,ActBS!$A$6:$A$164,$D27) -> 35000 | R27: =SUMIFS(ActBS!D$6:D$164,ActBS!$A$6:$A$164,$D27) -> 35000 | S27: =SUMIFS(ActBS!E$6:E$164,ActBS!$A$6:$A$164,$D27) -> 35000 | T27: =SUMIFS(ActBS!F$6:F$164,ActBS!$A$6:$A$164,$D27) -> 35000 | U27: =SUMIFS(ActBS!G$6:G$164,ActBS!$A$6:$A$164,$D27) -> 42500 | V27: =SUMIFS(ActBS!H$6:H$164,ActBS!$A$6:$A$164,$D27) -> 42500 | W27: =SUMIFS(ActBS!I$6:I$164,ActBS!$A$6:$A$164,$D27) -> 42500 | X27: =SUMIFS(ActBS!J$6:J$164,ActBS!$A$6:$A$164,$D27) -> 42500 | ... CZ27: =SUMIFS(ActBS!CL$6:CL$164,ActBS!$A$6:$A$164,$D27) -> 0
D28: Total Other Assets | F28: =SUM(F23:F27) -> 5671367.5 | G28: =SUM(G23:G27) -> 6766464.1 | H28: =SUM(H23:H27) -> 6206791.2 | I28: =SUM(I23:I27) -> 5745416.7 | J28: =SUM(J23:J27) -> 5087083.3 | K28: =SUM(K23:K27) -> 2977500 | L28: =SUM(L23:L27) -> 2445000 | Q28: =SUM(Q23:Q27) -> 306503.04 | R28: =SUM(R23:R27) -> 400702.42 | S28: =SUM(S23:S27) -> 373948.59 | T28: =SUM(T23:T27) -> 373565.78 | U28: =SUM(U23:U27) -> 392518.56 | V28: =SUM(V23:V27) -> 426523.08 | W28: =SUM(W23:W27) -> 420989.79 | X28: =SUM(X23:X27) -> 5658596.1 | ... CZ28: =SUM(CZ23:CZ27) -> 0
D30: Total Assets | F30: =F21+F28 -> 11580170 | G30: =G21+G28 -> 3420926 | H30: =H21+H28 -> 419450.86 | I30: =I21+I28 -> 5136454 | J30: =J21+J28 -> 18694383 | K30: =K21+K28 -> 39014579 | L30: =L21+L28 -> 46460779 | Q30: =Q21+Q28 -> 15701323 | R30: =R21+R28 -> 15434610 | S30: =S21+S28 -> 15046336 | T30: =T21+T28 -> 14722063 | U30: =U21+U28 -> 14327617 | V30: =V21+V28 -> 13837458 | W30: =W21+W28 -> 13444797 | X30: =X21+X28 -> 12914364 | ... CZ30: =CZ21+CZ28 -> 0
D33: Liabilities and Equity
D34: Accounts Payable | F34: =AB34 -> 644400.83 | G34: =AN34 -> 919340 | H34: =AZ34 -> 4589480 | I34: =BL34 -> 10634794 | J34: =BX34 -> 22385030 | K34: =CJ34 -> 40251188 | L34: =CV34 -> 31901639 | Q34: =SUMIFS(ActBS!C$6:C$164,ActBS!$A$6:$A$164,$D34) -> 35637.52 | R34: =SUMIFS(ActBS!D$6:D$164,ActBS!$A$6:$A$164,$D34) -> 83190.7 | S34: =SUMIFS(ActBS!E$6:E$164,ActBS!$A$6:$A$164,$D34) -> 89838.76 | T34: =SUMIFS(ActBS!F$6:F$164,ActBS!$A$6:$A$164,$D34) -> 194874.99 | U34: =SUMIFS(ActBS!G$6:G$164,ActBS!$A$6:$A$164,$D34) -> 245549.25 | V34: =SUMIFS(ActBS!H$6:H$164,ActBS!$A$6:$A$164,$D34) -> 192120.98 | W34: =SUMIFS(ActBS!I$6:I$164,ActBS!$A$6:$A$164,$D34) -> 301156.33 | X34: =SUMIFS(ActBS!J$6:J$164,ActBS!$A$6:$A$164,$D34) -> 346388.61 | ... CZ34: =SUMIFS(ActBS!CL$6:CL$164,ActBS!$A$6:$A$164,$D34) -> 0
D35: Accrued Liabilities | F35: =AB35 -> 98000.5 | G35: =AN35 -> 98000.5 | H35: =AZ35 -> 98000.5 | I35: =BL35 -> 98000.5 | J35: =BX35 -> 98000.5 | K35: =CJ35 -> 98000.5 | L35: =CV35 -> 98000.5 | Q35: =SUMIFS(ActBS!C$6:C$164,ActBS!$A$6:$A$164,$D35) -> -28880.7 | R35: =SUMIFS(ActBS!D$6:D$164,ActBS!$A$6:$A$164,$D35) -> -30913.1 | S35: =SUMIFS(ActBS!E$6:E$164,ActBS!$A$6:$A$164,$D35) -> -30913.1 | T35: =SUMIFS(ActBS!F$6:F$164,ActBS!$A$6:$A$164,$D35) -> 0 | U35: =SUMIFS(ActBS!G$6:G$164,ActBS!$A$6:$A$164,$D35) -> 11602 | V35: =SUMIFS(ActBS!H$6:H$164,ActBS!$A$6:$A$164,$D35) -> 32582.08 | W35: =SUMIFS(ActBS!I$6:I$164,ActBS!$A$6:$A$164,$D35) -> 140107.25 | X35: =SUMIFS(ActBS!J$6:J$164,ActBS!$A$6:$A$164,$D35) -> 94625.87 | ... CZ35: =SUMIFS(ActBS!CL$6:CL$164,ActBS!$A$6:$A$164,$D35) -> 0
D36: Notes Payable | F36: =AB36 -> 0 | G36: =AN36 -> 0 | H36: =AZ36 -> 0 | I36: =BL36 -> 0 | J36: =BX36 -> 0 | K36: =CJ36 -> 0 | L36: =CV36 -> 0 | Q36: =SUMIFS(ActBS!C$6:C$164,ActBS!$A$6:$A$164,$D36) -> 5000 | R36: =SUMIFS(ActBS!D$6:D$164,ActBS!$A$6:$A$164,$D36) -> 5000 | S36: =SUMIFS(ActBS!E$6:E$164,ActBS!$A$6:$A$164,$D36) -> 5000 | T36: =SUMIFS(ActBS!F$6:F$164,ActBS!$A$6:$A$164,$D36) -> 0 | U36: =SUMIFS(ActBS!G$6:G$164,ActBS!$A$6:$A$164,$D36) -> 0 | V36: =SUMIFS(ActBS!H$6:H$164,ActBS!$A$6:$A$164,$D36) -> 0 | W36: =SUMIFS(ActBS!I$6:I$164,ActBS!$A$6:$A$164,$D36) -> 0 | X36: =SUMIFS(ActBS!J$6:J$164,ActBS!$A$6:$A$164,$D36) -> 0 | ... CZ36: =SUMIFS(ActBS!CL$6:CL$164,ActBS!$A$6:$A$164,$D36) -> 0
D37: Other Liabilities | F37: =AB37 -> 0 | G37: =AN37 -> 0 | H37: =AZ37 -> 0 | I37: =BL37 -> 0 | J37: =BX37 -> 0 | K37: =CJ37 -> 0 | L37: =CV37 -> 0 | Q37: =SUMIFS(ActBS!C$6:C$164,ActBS!$A$6:$A$164,$D37) -> 0 | R37: =SUMIFS(ActBS!D$6:D$164,ActBS!$A$6:$A$164,$D37) -> 0 | S37: =SUMIFS(ActBS!E$6:E$164,ActBS!$A$6:$A$164,$D37) -> 0 | T37: =SUMIFS(ActBS!F$6:F$164,ActBS!$A$6:$A$164,$D37) -> 0 | U37: =SUMIFS(ActBS!G$6:G$164,ActBS!$A$6:$A$164,$D37) -> 0 | V37: =SUMIFS(ActBS!H$6:H$164,ActBS!$A$6:$A$164,$D37) -> 0 | W37: =SUMIFS(ActBS!I$6:I$164,ActBS!$A$6:$A$164,$D37) -> 0 | X37: =SUMIFS(ActBS!J$6:J$164,ActBS!$A$6:$A$164,$D37) -> 0 | ... CZ37: =SUMIFS(ActBS!CL$6:CL$164,ActBS!$A$6:$A$164,$D37) -> 0
D39: Total Liabilities | F39: =SUM(F34:F38) -> 742401.33 | G39: =SUM(G34:G38) -> 1017340.5 | H39: =SUM(H34:H38) -> 4687480.5 | I39: =SUM(I34:I38) -> 10732794 | J39: =SUM(J34:J38) -> 22483031 | K39: =SUM(K34:K38) -> 40349189 | L39: =SUM(L34:L38) -> 31999640 | Q39: =SUM(Q34:Q38) -> 11756.82 | R39: =SUM(R34:R38) -> 57277.6 | S39: =SUM(S34:S38) -> 63925.66 | T39: =SUM(T34:T38) -> 194874.99 | U39: =SUM(U34:U38) -> 257151.25 | V39: =SUM(V34:V38) -> 224703.06 | W39: =SUM(W34:W38) -> 441263.58 | X39: =SUM(X34:X38) -> 441014.48 | ... CZ39: =SUM(CZ34:CZ38) -> 0
D41: Units | F41: =AB41 -> 17500000 | G41: =AN41 -> 17500000 | H41: =AZ41 -> 17500000 | I41: =BL41 -> 17500000 | J41: =BX41 -> 17500000 | K41: =CJ41 -> 17500000 | L41: =CV41 -> 17500000 | Q41: =SUMIFS(ActBS!C$6:C$164,ActBS!$A$6:$A$164,$D41) -> 16337500 | R41: =SUMIFS(ActBS!D$6:D$164,ActBS!$A$6:$A$164,$D41) -> 16283333 | S41: =SUMIFS(ActBS!E$6:E$164,ActBS!$A$6:$A$164,$D41) -> 16229167 | T41: =SUMIFS(ActBS!F$6:F$164,ActBS!$A$6:$A$164,$D41) -> 16175000 | U41: =SUMIFS(ActBS!G$6:G$164,ActBS!$A$6:$A$164,$D41) -> 16120833 | V41: =SUMIFS(ActBS!H$6:H$164,ActBS!$A$6:$A$164,$D41) -> 16066667 | W41: =SUMIFS(ActBS!I$6:I$164,ActBS!$A$6:$A$164,$D41) -> 16012500 | X41: =SUMIFS(ActBS!J$6:J$164,ActBS!$A$6:$A$164,$D41) -> 15958333 | ... CZ41: =SUMIFS(ActBS!CL$6:CL$164,ActBS!$A$6:$A$164,$D41) -> 0
D42: Retained Earnings | F42: =AB42 -> -6662231.1 | G42: =AN42 -> -15096415 | H42: =AZ42 -> -21768030 | I42: =BL42 -> -23096341 | J42: =BX42 -> -21288648 | K42: =CJ42 -> -18834610 | L42: =CV42 -> -3038860.5 | Q42: =SUMIFS(ActBS!C$6:C$164,ActBS!$A$6:$A$164,$D42) -> -647933.72 | R42: =SUMIFS(ActBS!D$6:D$164,ActBS!$A$6:$A$164,$D42) -> -906001.18 | S42: =SUMIFS(ActBS!E$6:E$164,ActBS!$A$6:$A$164,$D42) -> -1246756.3 | T42: =SUMIFS(ActBS!F$6:F$164,ActBS!$A$6:$A$164,$D42) -> -1647812.4 | U42: =SUMIFS(ActBS!G$6:G$164,ActBS!$A$6:$A$164,$D42) -> -2050367.9 | V42: =SUMIFS(ActBS!H$6:H$164,ActBS!$A$6:$A$164,$D42) -> -2453912.1 | W42: =SUMIFS(ActBS!I$6:I$164,ActBS!$A$6:$A$164,$D42) -> -3008966.8 | X42: =SUMIFS(ActBS!J$6:J$164,ActBS!$A$6:$A$164,$D42) -> -3484984.3 | ... CZ42: =SUMIFS(ActBS!CL$6:CL$164,ActBS!$A$6:$A$164,$D42) -> 0
D44: Total Equity | F44: =SUM(F41:F43) -> 10837769 | G44: =SUM(G41:G43) -> 2403585.5 | H44: =SUM(H41:H43) -> -4268029.6 | I44: =SUM(I41:I43) -> -5596340.5 | J44: =SUM(J41:J43) -> -3788648 | K44: =SUM(K41:K43) -> -1334610 | L44: =SUM(L41:L43) -> 14461140 | Q44: =SUM(Q41:Q43) -> 15689566 | R44: =SUM(R41:R43) -> 15377332 | S44: =SUM(S41:S43) -> 14982410 | T44: =SUM(T41:T43) -> 14527188 | U44: =SUM(U41:U43) -> 14070466 | V44: =SUM(V41:V43) -> 13612755 | W44: =SUM(W41:W43) -> 13003533 | X44: =SUM(X41:X43) -> 12473349 | ... CZ44: =SUM(CZ41:CZ43) -> 0
D46: Total Liabilities & Equity | F46: =+F39+F44 -> 11580170 | G46: =+G39+G44 -> 3420926 | H46: =+H39+H44 -> 419450.86 | I46: =+I39+I44 -> 5136454 | J46: =+J39+J44 -> 18694383 | K46: =+K39+K44 -> 39014579 | L46: =+L39+L44 -> 46460779 | Q46: =+Q39+Q44 -> 15701323 | R46: =+R39+R44 -> 15434610 | S46: =+S39+S44 -> 15046336 | T46: =+T39+T44 -> 14722063 | U46: =+U39+U44 -> 14327617 | V46: =+V39+V44 -> 13837458 | W46: =+W39+W44 -> 13444797 | X46: =+X39+X44 -> 12914364 | ... CZ46: =+CZ39+CZ44 -> 0
D48: Variance Assets - Liab/Equity | F48: =F30-F46 -> 0 | G48: =G30-G46 -> 0 | H48: =H30-H46 -> 9.3132257e-10 | I48: =I30-I46 -> 0 | J48: =J30-J46 -> 0 | K48: =K30-K46 -> 0 | L48: =L30-L46 -> 0 | Q48: =Q30-Q46 -> 0 | R48: =R30-R46 -> 0 | S48: =S30-S46 -> 0 | T48: =T30-T46 -> 0 | U48: =U30-U46 -> 0 | V48: =V30-V46 -> 0 | W48: =W30-W46 -> 0 | X48: =X30-X46 -> 0 | ... CZ48: =CZ30-CZ46 -> 0
D53: Inventory
D54: Months on hand, average of 3 month demand | AC54: =AC16/AVERAGE([1]ConsolIS!BE$32:BG$32) -> 3 | AD54: =AD16/AVERAGE([1]ConsolIS!BF$32:BH$32) -> 3 | AE54: =AE16/AVERAGE([1]ConsolIS!BG$32:BI$32) -> 0.28301887 | AF54: =AF16/AVERAGE([1]ConsolIS!BH$32:BJ$32) -> 1.5 | AG54: =AG16/AVERAGE([1]ConsolIS!BI$32:BK$32) -> 3 | AH54: =AH16/AVERAGE([1]ConsolIS!BJ$32:BL$32) -> 2.88 | AI54: =AI16/AVERAGE([1]ConsolIS!BK$32:BM$32) -> 0.23076923 | AJ54: =AJ16/AVERAGE([1]ConsolIS!BL$32:BN$32) -> 3 | ... CV54: =CV16/AVERAGE([1]ConsolIS!DX$32:DZ$32) -> 6.0702187

Sheet CFS
D3: Violet St Consolidated
D4: Pro Forma Cash Flow Statement
D5: AOP 2024-2026
D6: Confidential
P10: 2024 | Q10: 2024 | R10: 2024 | S10: 2024 | U10: ="Q"&ROUNDUP(MONTH(U11)/3,0)&"-"&YEAR(U11) -> Q1-2023 | V10: ="Q"&ROUNDUP(MONTH(V11)/3,0)&"-"&YEAR(V11) -> Q1-2023 | W10: ="Q"&ROUNDUP(MONTH(W11)/3,0)&"-"&YEAR(W11) -> Q1-2023 | X10: ="Q"&ROUNDUP(MONTH(X11)/3,0)&"-"&YEAR(X11) -> Q2-2023 | Y10: ="Q"&ROUNDUP(MONTH(Y11)/3,0)&"-"&YEAR(Y11) -> Q2-2023 | Z10: ="Q"&ROUNDUP(MONTH(Z11)/3,0)&"-"&YEAR(Z11) -> Q2-2023 | AA10: ="Q"&ROUNDUP(MONTH(AA11)/3,0)&"-"&YEAR(AA11) -> Q3-2023 | AB10: ="Q"&ROUNDUP(MONTH(AB11)/3,0)&"-"&YEAR(AB11) -> Q3-2023 | ... CZ10: ="Q"&ROUNDUP(MONTH(CZ11)/3,0)&"-"&YEAR(CZ11) -> Q4-2029
D11: Cash Flow Statement | F11: 2023 | G11: 2024 | H11: 2025 | I11: 2026 | J11: 2027 | K11: 2028 | L11: 2029 | P11: Q1-2024 | Q11: Q2-2024 | R11: Q3-2024 | S11: Q4-2024 | U11: 44957 | V11: =EOMONTH(U11,1) -> 44985 | W11: =EOMONTH(V11,1) -> 45016 | X11: =EOMONTH(W11,1) -> 45046 | Y11: =EOMONTH(X11,1) -> 45077 | Z11: =EOMONTH(Y11,1) -> 45107 | AA11: =EOMONTH(Z11,1) -> 45138 | AB11: =EOMONTH(AA11,1) -> 45169 | AC11: =EOMONTH(AB11,1) -> 45199 | ... CZ11: =EOMONTH(CY11,1) -> 47483
D12: Operating Cash Flow
D13: Net Income | G13: =SUM(AG13:AR13) -> -8434183.5 | H13: =SUM(AS13:BD13) -> -6671615.1 | I13: =SUM(BE13:BP13) -> -1328310.9 | J13: =SUM(BQ13:CB13) -> 1807692.6 | K13: =SUM(CC13:CN13) -> 2454037.9 | L13: =SUM(CO13:CZ13) -> 15795750 | P13: =SUMIFS($AG13:$CB13,$AG$10:$CB$10,P$11) -> -1999280.5 | Q13: =SUMIFS($AG13:$CB13,$AG$10:$CB$10,Q$11) -> -2349700 | R13: =SUMIFS($AG13:$CB13,$AG$10:$CB$10,R$11) -> -1821971.5 | S13: =SUMIFS($AG13:$CB13,$AG$10:$CB$10,S$11) -> -2263231.5 | AG13: =[1]ConsolIS!BE$102 -> -593059.98 | AH13: =[1]ConsolIS!BF$102 -> -723759.98 | AI13: =[1]ConsolIS!BG$102 -> -682460.51 | AJ13: =[1]ConsolIS!BH$102 -> -827187.81 | AK13: =[1]ConsolIS!BI$102 -> -790718.31 | AL13: =[1]ConsolIS!BJ$102 -> -731793.85 | AM13: =[1]ConsolIS!BK$102 -> -305083.8 | AN13: =[1]ConsolIS!BL$102 -> -824243.31 | ... CZ13: =[1]ConsolIS!DX$102 -> 2041934.6
D14: Depreciation & Amortization | G14: =SUM(AG14:AR14) -> 452048.31 | H14: =SUM(AS14:BD14) -> 1089672.9 | I14: =SUM(BE14:BP14) -> 1436374.6 | J14: =SUM(BQ14:CB14) -> 1008333.3 | K14: =SUM(CC14:CN14) -> 809583.33 | L14: =SUM(CO14:CZ14) -> 882500 | P14: =SUMIFS($AG14:$CB14,$AG$10:$CB$10,P$11) -> 64650.098 | Q14: =SUMIFS($AG14:$CB14,$AG$10:$CB$10,Q$11) -> 99233.431 | R14: =SUMIFS($AG14:$CB14,$AG$10:$CB$10,R$11) -> 99233.431 | S14: =SUMIFS($AG14:$CB14,$AG$10:$CB$10,S$11) -> 188931.35 | AG14: =[1]ConsolIS!BE85 -> 15786.144 | AH14: =[1]ConsolIS!BF85 -> 15786.144 | AI14: =[1]ConsolIS!BG85 -> 33077.81 | AJ14: =[1]ConsolIS!BH85 -> 33077.81 | AK14: =[1]ConsolIS!BI85 -> 33077.81 | AL14: =[1]ConsolIS!BJ85 -> 33077.81 | AM14: =[1]ConsolIS!BK85 -> 33077.81 | AN14: =[1]ConsolIS!BL85 -> 33077.81 | ... CZ14: =[1]ConsolIS!DX85 -> 73541.667
D16: Change in Operating Assets / Liabilites
D17: Change in Accounts Receivable | G17: =SUM(AG17:AR17) -> -49845.14 | H17: =SUM(AS17:BD17) -> -666400 | I17: =SUM(BE17:BP17) -> -850525 | J17: =SUM(BQ17:CB17) -> -2905975 | K17: =SUM(CC17:CN17) -> -5831812.5 | L17: =SUM(CO17:CZ17) -> -7385281.2 | P17: =SUMIFS($AG17:$CB17,$AG$10:$CB$10,P$11) -> -255245.14 | Q17: =SUMIFS($AG17:$CB17,$AG$10:$CB$10,Q$11) -> 360000 | R17: =SUMIFS($AG17:$CB17,$AG$10:$CB$10,R$11) -> 0 | S17: =SUMIFS($AG17:$CB17,$AG$10:$CB$10,S$11) -> -154600 | AG17: =-BS!AC15+BS!AB15 -> 104754.86 | AH17: =-BS!AD15+BS!AC15 -> 0 | AI17: =-BS!AE15+BS!AD15 -> -360000 | AJ17: =-BS!AF15+BS!AE15 -> -37500 | AK17: =-BS!AG15+BS!AF15 -> 360000 | AL17: =-BS!AH15+BS!AG15 -> 37500 | AM17: =-BS!AI15+BS!AH15 -> 0 | AN17: =-BS!AJ15+BS!AI15 -> 0 | ... CZ17: =-BS!CV15+BS!CU15 -> -1813476.6
D18: Change in Inventory | G18: =SUM(AG18:AR18) -> -918178.16 | H18: =SUM(AS18:BD18) -> -3670140 | I18: =SUM(BE18:BP18) -> -6045314 | J18: =SUM(BQ18:CB18) -> -11750236 | K18: =SUM(CC18:CN18) -> -17866158 | L18: =SUM(CO18:CZ18) -> 8349549.3 | P18: =SUMIFS($AG18:$CB18,$AG$10:$CB$10,P$11) -> -13288.16 | Q18: =SUMIFS($AG18:$CB18,$AG$10:$CB$10,Q$11) -> -332350 | R18: =SUMIFS($AG18:$CB18,$AG$10:$CB$10,R$11) -> 185640 | S18: =SUMIFS($AG18:$CB18,$AG$10:$CB$10,S$11) -> -758180 | AG18: =-BS!AC16+BS!AB16 -> -137558.16 | AH18: =-BS!AD16+BS!AC16 -> -14450 | AI18: =-BS!AE16+BS!AD16 -> 138720 | AJ18: =-BS!AF16+BS!AE16 -> 0 | AK18: =-BS!AG16+BS!AF16 -> -346800 | AL18: =-BS!AH16+BS!AG16 -> 14450 | AM18: =-BS!AI16+BS!AH16 -> 317900 | AN18: =-BS!AJ16+BS!AI16 -> -24300 | ... CZ18: =-BS!CV16+BS!CU16 -> -5439949.7
D19: Change in Prepaid Expenses | G19: =SUM(AG19:AR19) -> -583333.33 | H19: =SUM(AS19:BD19) -> 500000 | I19: =SUM(BE19:BP19) -> 83333.333 | J19: =SUM(BQ19:CB19) -> 0 | K19: =SUM(CC19:CN19) -> 0 | L19: =SUM(CO19:CZ19) -> 0 | P19: =SUMIFS($AG19:$CB19,$AG$10:$CB$10,P$11) -> -958333.33 | Q19: =SUMIFS($AG19:$CB19,$AG$10:$CB$10,Q$11) -> 125000 | R19: =SUMIFS($AG19:$CB19,$AG$10:$CB$10,R$11) -> 125000 | S19: =SUMIFS($AG19:$CB19,$AG$10:$CB$10,S$11) -> 125000 | AG19: =-BS!AC17+BS!AB17 -> 0 | AH19: =-BS!AD17+BS!AC17 -> -1000000 | AI19: =-BS!AE17+BS!AD17 -> 41666.667 | AJ19: =-BS!AF17+BS!AE17 -> 41666.667 | AK19: =-BS!AG17+BS!AF17 -> 41666.667 | AL19: =-BS!AH17+BS!AG17 -> 41666.667 | AM19: =-BS!AI17+BS!AH17 -> 41666.667 | AN19: =-BS!AJ17+BS!AI17 -> 41666.667 | ... CZ19: =-BS!CV17+BS!CU17 -> 0
D20: Change in Other Current Assets | G20: =SUM(AG20:AR20) -> 389084 | H20: =SUM(AS20:BD20) -> 0 | I20: =SUM(BE20:BP20) -> 0 | J20: =SUM(BQ20:CB20) -> 0 | K20: =SUM(CC20:CN20) -> 0 | L20: =SUM(CO20:CZ20) -> 0 | P20: =SUMIFS($AG20:$CB20,$AG$10:$CB$10,P$11) -> 389084 | Q20: =SUMIFS($AG20:$CB20,$AG$10:$CB$10,Q$11) -> 0 | R20: =SUMIFS($AG20:$CB20,$AG$10:$CB$10,R$11) -> 0 | S20: =SUMIFS($AG20:$CB20,$AG$10:$CB$10,S$11) -> 0 | AG20: =-BS!AC19+BS!AB19 -> 389084 | AH20: =-BS!AD19+BS!AC19 -> 0 | AI20: =-BS!AE19+BS!AD19 -> 0 | AJ20: =-BS!AF19+BS!AE19 -> 0 | AK20: =-BS!AG19+BS!AF19 -> 0 | AL20: =-BS!AH19+BS!AG19 -> 0 | AM20: =-BS!AI19+BS!AH19 -> 0 | AN20: =-BS!AJ19+BS!AI19 -> 0 | ... CZ20: =-BS!CV19+BS!CU19 -> 0
D21: Change in Accounts Payable | G21: =SUM(AG21:AR21) -> 274939.17 | H21: =SUM(AS21:BD21) -> 3670140 | I21: =SUM(BE21:BP21) -> 6045314 | J21: =SUM(BQ21:CB21) -> 11750236 | K21: =SUM(CC21:CN21) -> 17866158 | L21: =SUM(CO21:CZ21) -> -8349549.3 | P21: =SUMIFS($AG21:$CB21,$AG$10:$CB$10,P$11) -> -629950.83 | Q21: =SUMIFS($AG21:$CB21,$AG$10:$CB$10,Q$11) -> 332350 | R21: =SUMIFS($AG21:$CB21,$AG$10:$CB$10,R$11) -> -185640 | S21: =SUMIFS($AG21:$CB21,$AG$10:$CB$10,S$11) -> 758180 | AG21: =BS!AC34-BS!AB34 -> 138720 | AH21: =BS!AD34-BS!AC34 -> -629950.83 | AI21: =BS!AE34-BS!AD34 -> -138720 | AJ21: =BS!AF34-BS!AE34 -> 0 | AK21: =BS!AG34-BS!AF34 -> 346800 | AL21: =BS!AH34-BS!AG34 -> -14450 | AM21: =BS!AI34-BS!AH34 -> -317900 | AN21: =BS!AJ34-BS!AI34 -> 24300 | ... CZ21: =BS!CV34-BS!CU34 -> 5439949.7
D22: Change in Accrued Expenses | G22: =SUM(AG22:AR22) -> 0 | H22: =SUM(AS22:BD22) -> 0 | I22: =SUM(BE22:BP22) -> 0 | J22: =SUM(BQ22:CB22) -> 0 | K22: =SUM(CC22:CN22) -> 0 | L22: =SUM(CO22:CZ22) -> 0 | P22: =SUMIFS($AG22:$CB22,$AG$10:$CB$10,P$11) -> 0 | Q22: =SUMIFS($AG22:$CB22,$AG$10:$CB$10,Q$11) -> 0 | R22: =SUMIFS($AG22:$CB22,$AG$10:$CB$10,R$11) -> 0 | S22: =SUMIFS($AG22:$CB22,$AG$10:$CB$10,S$11) -> 0 | AG22: =BS!AC35-BS!AB35 -> 0 | AH22: =BS!AD35-BS!AC35 -> 0 | AI22: =BS!AE35-BS!AD35 -> 0 | AJ22: =BS!AF35-BS!AE35 -> 0 | AK22: =BS!AG35-BS!AF35 -> 0 | AL22: =BS!AH35-BS!AG35 -> 0 | AM22: =BS!AI35-BS!AH35 -> 0 | AN22: =BS!AJ35-BS!AI35 -> 0 | ... CZ22: =BS!CV35-BS!CU35 -> 0
D23: Change in Other Liabilities | G23: =SUM(AG23:AR23) -> 0 | H23: =SUM(AS23:BD23) -> 0 | I23: =SUM(BE23:BP23) -> 0 | J23: =SUM(BQ23:CB23) -> 0 | K23: =SUM(CC23:CN23) -> 0 | L23: =SUM(CO23:CZ23) -> 0 | P23: =SUMIFS($AG23:$CB23,$AG$10:$CB$10,P$11) -> 0 | Q23: =SUMIFS($AG23:$CB23,$AG$10:$CB$10,Q$11) -> 0 | R23: =SUMIFS($AG23:$CB23,$AG$10:$CB$10,R$11) -> 0 | S23: =SUMIFS($AG23:$CB23,$AG$10:$CB$10,S$11) -> 0 | AG23: =BS!AC37-BS!AB37 -> 0 | AH23: =BS!AD37-BS!AC37 -> 0 | AI23: =BS!AE37-BS!AD37 -> 0 | AJ23: =BS!AF37-BS!AE37 -> 0 | AK23: =BS!AG37-BS!AF37 -> 0 | AL23: =BS!AH37-BS!AG37 -> 0 | AM23: =BS!AI37-BS!AH37 -> 0 | AN23: =BS!AJ37-BS!AI37 -> 0 | ... CZ23: =BS!CV37-BS!CU37 -> 0
D24: Cash Flow from Operations | G24: =SUM(G13:G23) -> -8869468.6 | H24: =SUM(H13:H23) -> -5748342.2 | I24: =SUM(I13:I23) -> -659127.97 | J24: =SUM(J13:J23) -> -89949.102 | K24: =SUM(K13:K23) -> -2568191.2 | L24: =SUM(L13:L23) -> 9292968.3 | P24: =SUM(P13:P23) -> -3402363.8 | Q24: =SUM(Q13:Q23) -> -1765466.5 | R24: =SUM(R13:R23) -> -1597738.1 | S24: =SUM(S13:S23) -> -2103900.2 | AG24: =SUM(AG13:AG23) -> -82273.133 | AH24: =SUM(AH13:AH23) -> -2352374.7 | AI24: =SUM(AI13:AI23) -> -967716.03 | AJ24: =SUM(AJ13:AJ23) -> -789943.33 | AK24: =SUM(AK13:AK23) -> -355973.83 | AL24: =SUM(AL13:AL23) -> -619549.37 | AM24: =SUM(AM13:AM23) -> -230339.32 | AN24: =SUM(AN13:AN23) -> -749498.83 | ... CZ24: =SUM(CZ13:CZ23) -> 301999.75
D26: Investing Cash Flow
D27: Capital Expenditures | G27: =SUM(AG27:AR27) -> -1547145 | H27: =SUM(AS27:BD27) -> -530000 | I27: =SUM(BE27:BP27) -> -975000 | J27: =SUM(BQ27:CB27) -> -350000 | K27: =SUM(CC27:CN27) -> -700000 | L27: =SUM(CO27:CZ27) -> -350000 | P27: =SUMIFS($AG27:$CB27,$AG$10:$CB$10,P$11) -> -415000 | Q27: =SUMIFS($AG27:$CB27,$AG$10:$CB$10,Q$11) -> 1.4551915e-11 | R27: =SUMIFS($AG27:$CB27,$AG$10:$CB$10,R$11) -> 1.2369128e-10 | S27: =SUMIFS($AG27:$CB27,$AG$10:$CB$10,S$11) -> -1132145 | AG27: =-BS!AC23+BS!AB23-AG14 -> 4.7293724e-11 | AH27: =-BS!AD23+BS!AC23-AH14 -> 0 | AI27: =-BS!AE23+BS!AD23-AI14 -> -415000 | AJ27: =-BS!AF23+BS!AE23-AJ14 -> 1.2369128e-10 | AK27: =-BS!AG23+BS!AF23-AK14 -> 0 | AL27: =-BS!AH23+BS!AG23-AL14 -> -1.0913936e-10 | AM27: =-BS!AI23+BS!AH23-AM14 -> 1.2369128e-10 | AN27: =-BS!AJ23+BS!AI23-AN14 -> 0 | ... CZ27: =-BS!CV23+BS!CU23-CZ14 -> 3.0559022e-10
D28: Other Investing Activities | G28: =SUM(AG28:AR28) -> 0 | H28: =SUM(AS28:BD28) -> 0 | I28: =SUM(BE28:BP28) -> 0 | J28: =SUM(BQ28:CB28) -> 0 | K28: =SUM(CC28:CN28) -> 0 | L28: =SUM(CO28:CZ28) -> 0 | P28: =SUMIFS($AG28:$CB28,$AG$10:$CB$10,P$11) -> 0 | Q28: =SUMIFS($AG28:$CB28,$AG$10:$CB$10,Q$11) -> 0 | R28: =SUMIFS($AG28:$CB28,$AG$10:$CB$10,R$11) -> 0 | S28: =SUMIFS($AG28:$CB28,$AG$10:$CB$10,S$11) -> 0 | AG28: =-BS!AC26+BS!AB26 -> 0 | AH28: =-BS!AD26+BS!AC26 -> 0 | AI28: =-BS!AE26+BS!AD26 -> 0 | AJ28: =-BS!AF26+BS!AE26 -> 0 | AK28: =-BS!AG26+BS!AF26 -> 0 | AL28: =-BS!AH26+BS!AG26 -> 0 | AM28: =-BS!AI26+BS!AH26 -> 0 | AN28: =-BS!AJ26+BS!AI26 -> 0 | ... CZ28: =-BS!CV26+BS!CU26 -> 0
D29: Cash Flow from Investing | G29: =SUM(G27:G28) -> -1547145 | H29: =SUM(H27:H28) -> -530000 | I29: =SUM(I27:I28) -> -975000 | J29: =SUM(J27:J28) -> -350000 | K29: =SUM(K27:K28) -> -700000 | L29: =SUM(L27:L28) -> -350000 | P29: =SUM(P27:P28) -> -415000 | Q29: =SUM(Q27:Q28) -> 1.4551915e-11 | R29: =SUM(R27:R28) -> 1.2369128e-10 | S29: =SUM(S27:S28) -> -1132145 | AG29: =SUM(AG27:AG28) -> 4.7293724e-11 | AH29: =SUM(AH27:AH28) -> 0 | AI29: =SUM(AI27:AI28) -> -415000 | AJ29: =SUM(AJ27:AJ28) -> 1.2369128e-10 | AK29: =SUM(AK27:AK28) -> 0 | AL29: =SUM(AL27:AL28) -> -1.0913936e-10 | AM29: =SUM(AM27:AM28) -> 1.2369128e-10 | AN29: =SUM(AN27:AN28) -> 0 | ... CZ29: =SUM(CZ27:CZ28) -> 3.0559022e-10
D31: Financing Cash Flow
D32: Issuance / (Payments) on Long-Term Debt | G32: =SUM(AG32:AR32) -> 0 | H32: =SUM(AS32:BD32) -> 0 | I32: =SUM(BE32:BP32) -> 0 | J32: =SUM(BQ32:CB32) -> 0 | K32: =SUM(CC32:CN32) -> 2000000 | L32: =SUM(CO32:CZ32) -> 0 | P32: =SUMIFS($AG32:$CB32,$AG$10:$CB$10,P$11) -> 0 | Q32: =SUMIFS($AG32:$CB32,$AG$10:$CB$10,Q$11) -> 0 | R32: =SUMIFS($AG32:$CB32,$AG$10:$CB$10,R$11) -> 0 | S32: =SUMIFS($AG32:$CB32,$AG$10:$CB$10,S$11) -> 0 | AG32: =(BS!AC36-BS!AB36)-(BS!AC25-BS!AB25) -> 0 | AH32: =(BS!AD36-BS!AC36)-(BS!AD25-BS!AC25) -> 0 | AI32: =(BS!AE36-BS!AD36)-(BS!AE25-BS!AD25) -> 0 | AJ32: =(BS!AF36-BS!AE36)-(BS!AF25-BS!AE25) -> 0 | AK32: =(BS!AG36-BS!AF36)-(BS!AG25-BS!AF25) -> 0 | AL32: =(BS!AH36-BS!AG36)-(BS!AH25-BS!AG25) -> 0 | AM32: =(BS!AI36-BS!AH36)-(BS!AI25-BS!AH25) -> 0 | AN32: =(BS!AJ36-BS!AI36)-(BS!AJ25-BS!AI25) -> 0 | ... CZ32: =(BS!CV36-BS!CU36)-(BS!CV25-BS!CU25) -> 0
D33: Issuance / (Payments) in Stock | G33: =SUM(AG33:AR33) -> 0 | H33: =SUM(AS33:BD33) -> 0 | I33: =SUM(BE33:BP33) -> 0 | J33: =SUM(BQ33:CB33) -> 0 | K33: =SUM(CC33:CN33) -> 0 | L33: =SUM(CO33:CZ33) -> 0 | P33: =SUMIFS($AG33:$CB33,$AG$10:$CB$10,P$11) -> 0 | Q33: =SUMIFS($AG33:$CB33,$AG$10:$CB$10,Q$11) -> 0 | R33: =SUMIFS($AG33:$CB33,$AG$10:$CB$10,R$11) -> 0 | S33: =SUMIFS($AG33:$CB33,$AG$10:$CB$10,S$11) -> 0 | AG33: =BS!AC41-BS!AB41 -> 0 | AH33: =BS!AD41-BS!AC41 -> 0 | AI33: =BS!AE41-BS!AD41 -> 0 | AJ33: =BS!AF41-BS!AE41 -> 0 | AK33: =BS!AG41-BS!AF41 -> 0 | AL33: =BS!AH41-BS!AG41 -> 0 | AM33: =BS!AI41-BS!AH41 -> 0 | AN33: =BS!AJ41-BS!AI41 -> 0 | ... CZ33: =BS!CV41-BS!CU41 -> 0
D34: Cash Flow from Financing | G34: =SUM(G32:G33) -> 0 | H34: =SUM(H32:H33) -> 0 | I34: =SUM(I32:I33) -> 0 | J34: =SUM(J32:J33) -> 0 | K34: =SUM(K32:K33) -> 2000000 | L34: =SUM(L32:L33) -> 0 | P34: =SUM(P32:P33) -> 0 | Q34: =SUM(Q32:Q33) -> 0 | R34: =SUM(R32:R33) -> 0 | S34: =SUM(S32:S33) -> 0 | AG34: =SUM(AG32:AG33) -> 0 | AH34: =SUM(AH32:AH33) -> 0 | AI34: =SUM(AI32:AI33) -> 0 | AJ34: =SUM(AJ32:AJ33) -> 0 | AK34: =SUM(AK32:AK33) -> 0 | AL34: =SUM(AL32:AL33) -> 0 | AM34: =SUM(AM32:AM33) -> 0 | AN34: =SUM(AN32:AN33) -> 0 | ... CZ34: =SUM(CZ32:CZ33) -> 0
D37: Change in Cash | G37: =SUM(G24,G29,G34) -> -10416614 | H37: =SUM(H24,H29,H34) -> -6278342.2 | I37: =SUM(I24,I29,I34) -> -1634128 | J37: =SUM(J24,J29,J34) -> -439949.1 | K37: =SUM(K24,K29,K34) -> -1268191.2 | L37: =SUM(L24,L29,L34) -> 8942968.3 | P37: =SUMIFS($AG37:$CB37,$AG$10:$CB$10,P$11) -> -3817363.8 | Q37: =SUMIFS($AG37:$CB37,$AG$10:$CB$10,Q$11) -> -1765466.5 | R37: =SUMIFS($AG37:$CB37,$AG$10:$CB$10,R$11) -> -1597738.1 | S37: =SUMIFS($AG37:$CB37,$AG$10:$CB$10,S$11) -> -3236045.2 | AG37: =SUM(AG24,AG29,AG34) -> -82273.133 | AH37: =SUM(AH24,AH29,AH34) -> -2352374.7 | AI37: =SUM(AI24,AI29,AI34) -> -1382716 | AJ37: =SUM(AJ24,AJ29,AJ34) -> -789943.33 | AK37: =SUM(AK24,AK29,AK34) -> -355973.83 | AL37: =SUM(AL24,AL29,AL34) -> -619549.37 | AM37: =SUM(AM24,AM29,AM34) -> -230339.32 | AN37: =SUM(AN24,AN29,AN34) -> -749498.83 | ... CZ37: =SUM(CZ24,CZ29,CZ34) -> 301999.75
D38: Beginning Cash Balance | G38: =F39 -> 5223205.9 | H38: =G39 -> -5193407.8 | I38: =H39 -> -11471750 | J38: =I39 -> -13105878 | K38: =J39 -> -13545827 | L38: =K39 -> -14814018 | P38: =+AG38 -> 5223205.9 | AG38: =AF39 -> 5223205.9 | AH38: =AG39 -> 5140932.8 | AI38: =AH39 -> 2788558.1 | AJ38: =AI39 -> 1405842.1 | AK38: =AJ39 -> 615898.73 | AL38: =AK39 -> 259924.89 | AM38: =AL39 -> -359624.48 | AN38: =AM39 -> -589963.8 | ... CZ38: =CY39 -> -6173049.7
D39: Ending Cash Balance | F39: =ActBS!N17 -> 5223205.9 | G39: =+G37+G38 -> -5193407.8 | H39: =+H37+H38 -> -11471750 | I39: =+I37+I38 -> -13105878 | J39: =+J37+J38 -> -13545827 | K39: =+K37+K38 -> -14814018 | L39: =+L37+L38 -> -5871050 | P39: =+P37+P38 -> 1405842.1 | Q39: =+Q37+Q38+P39 -> -359624.48 | R39: =+R37+R38+Q39 -> -1957362.6 | S39: =+S37+S38+R39 -> -5193407.8 | AF39: =ActBS!N17 -> 5223205.9 | AG39: =+AG37+AG38 -> 5140932.8 | AH39: =+AH37+AH38 -> 2788558.1 | AI39: =+AI37+AI38 -> 1405842.1 | AJ39: =+AJ37+AJ38 -> 615898.73 | AK39: =+AK37+AK38 -> 259924.89 | AL39: =+AL37+AL38 -> -359624.48 | AM39: =+AM37+AM38 -> -589963.8 | AN39: =+AN37+AN38 -> -1339462.6 | ... CZ39: =+CZ37+CZ38 -> -5871050
D40: check | F40: =BS!F14-F39 -> 0 | G40: =AR39-G39 -> 0 | H40: =BD39-H39 -> 0 | I40: =BP39-I39 -> 0 | J40: =CB39-J39 -> 0 | K40: =CN39-K39 -> 0 | L40: =CZ39-L39 -> 0 | P40: =+AI39-P39 -> 0 | Q40: =+AL39-Q39 -> 6.9849193e-10 | R40: =+AO39-R39 -> 0 | S40: =+AR39-S39 -> 0 | AG40: =BS!AC14-AG39 -> 0 | AH40: =BS!AD14-AH39 -> 0 | AI40: =BS!AE14-AI39 -> 0 | AJ40: =BS!AF14-AJ39 -> 0 | AK40: =BS!AG14-AK39 -> 0 | AL40: =BS!AH14-AL39 -> 0 | AM40: =BS!AI14-AM39 -> 0 | AN40: =BS!AJ14-AN39 -> 0 | ... CZ40: =BS!CV14-CZ39 -> 0
D44: Net Income check:
D45: Net Income | G45: =SUM(AG45:AR45) -> -8434183.5 | H45: =SUM(AS45:BD45) -> -6671615.1 | I45: =SUM(BE45:BP45) -> -1328310.9 | J45: =SUM(BQ45:CB45) -> 1807692.6 | K45: =SUM(CC45:CN45) -> 2454037.9 | L45: =SUM(CO45:CZ45) -> 15795750 | AG45: =+AG13 -> -593059.98 | AH45: =+AH13 -> -723759.98 | AI45: =+AI13 -> -682460.51 | AJ45: =+AJ13 -> -827187.81 | AK45: =+AK13 -> -790718.31 | AL45: =+AL13 -> -731793.85 | AM45: =+AM13 -> -305083.8 | AN45: =+AN13 -> -824243.31 | ... CZ45: =+CZ13 -> 2041934.6
D46: Net Change in RE | G46: =BS!G42-BS!F42 -> -8434183.5 | H46: =BS!H42-BS!G42 -> -6671615.1 | I46: =BS!I42-BS!H42 -> -1328310.9 | J46: =BS!J42-BS!I42 -> 1807692.6 | K46: =BS!K42-BS!J42 -> 2454037.9 | L46: =BS!L42-BS!K42 -> 15795750 | AG46: =BS!AC42-BS!AB42 -> -593059.98 | AH46: =BS!AD42-BS!AC42 -> -723759.98 | AI46: =BS!AE42-BS!AD42 -> -682460.51 | AJ46: =BS!AF42-BS!AE42 -> -827187.81 | AK46: =BS!AG42-BS!AF42 -> -790718.31 | AL46: =BS!AH42-BS!AG42 -> -731793.85 | AM46: =BS!AI42-BS!AH42 -> -305083.8 | AN46: =BS!AJ42-BS!AI42 -> -824243.31 | ... CZ46: =BS!CV42-BS!CU42 -> 2041934.6
D47: Variance | G47: =-G45+G46 -> 0 | H47: =-H45+H46 -> 0 | I47: =-I45+I46 -> 0 | J47: =-J45+J46 -> 1.8626451e-09 | K47: =-K45+K46 -> 0 | L47: =-L45+L46 -> 0 | AG47: =-AG45+AG46 -> 0 | AH47: =-AH45+AH46 -> 0 | AI47: =-AI45+AI46 -> 0 | AJ47: =-AJ45+AJ46 -> 0 | AK47: =-AK45+AK46 -> 1.6298145e-09 | AL47: =-AL45+AL46 -> 0 | AM47: =-AM45+AM46 -> 0 | AN47: =-AN45+AN46 -> 0 | ... CZ47: =-CZ45+CZ46 -> 0
E2141: x
D2193: x

Sheet WC
D3: Violet St Consolidated
D4: Working Capital | G4: Inv | Y4: =ActBS!N26 -> 1161.84 | Z4: =Z86 -> 138720 | AA4: =AA86 -> 153170 | AB4: =AB86 -> 14450 | AC4: =AC86 -> 14450 | AD4: =AD86 -> 361250 | AE4: =AE86 -> 346800 | AF4: =AF86 -> 28900 | AG4: =AG86 -> 53200 | ... CS4: =CS86 -> 31901639
D5: AOP 2024-2026 | G5: A/R | Y5: =ActBS!N19 -> 146754.86 | Z5: =Z269 -> 42000 | AA5: =AA269 -> 42000 | AB5: =AB269 -> 402000 | AC5: =AC269 -> 439500 | AD5: =AD269 -> 79500 | AE5: =AE269 -> 42000 | AF5: =AF269 -> 42000 | AG5: =AG269 -> 42000 | ... CS5: =CS269 -> 17836594
D6: Confidential | G6: A/P | Y6: =ActBS!N69+ActBS!N75 -> 644400.83 | Z6: =Z357 -> 783120.83 | AA6: =AA357 -> 153170 | AB6: =AB357 -> 14450 | AC6: =AC357 -> 14450 | AD6: =AD357 -> 361250 | AE6: =AE357 -> 346800 | AF6: =AF357 -> 28900 | AG6: =AG357 -> 53200 | ... CS6: =CS357 -> 31901639
G7: Contra Balance | Y7: 0 | Z7: =Z299 -> 0 | AA7: =AA299 -> 0 | AB7: =AB299 -> 43200 | AC7: =AC299 -> 47700 | AD7: =AD299 -> 4500 | AE7: =AE299 -> 0 | AF7: =AF299 -> 0 | AG7: =AG299 -> 0 | ... CS7: =CS299 -> 2140391.2
N10: ="Q"&ROUNDUP(MONTH(N11)/3,0)&"-"&YEAR(N11) -> Q1-2023 | O10: ="Q"&ROUNDUP(MONTH(O11)/3,0)&"-"&YEAR(O11) -> Q1-2023 | P10: ="Q"&ROUNDUP(MONTH(P11)/3,0)&"-"&YEAR(P11) -> Q1-2023 | Q10: ="Q"&ROUNDUP(MONTH(Q11)/3,0)&"-"&YEAR(Q11) -> Q2-2023 | R10: ="Q"&ROUNDUP(MONTH(R11)/3,0)&"-"&YEAR(R11) -> Q2-2023 | S10: ="Q"&ROUNDUP(MONTH(S11)/3,0)&"-"&YEAR(S11) -> Q2-2023 | T10: ="Q"&ROUNDUP(MONTH(T11)/3,0)&"-"&YEAR(T11) -> Q3-2023 | U10: ="Q"&ROUNDUP(MONTH(U11)/3,0)&"-"&YEAR(U11) -> Q3-2023 | ... CV10: ="Q"&ROUNDUP(MONTH(CV11)/3,0)&"-"&YEAR(CV11) -> Q1-2030
N11: 44957 | O11: =EOMONTH(N11,1) -> 44985 | P11: =EOMONTH(O11,1) -> 45016 | Q11: =EOMONTH(P11,1) -> 45046 | R11: =EOMONTH(Q11,1) -> 45077 | S11: =EOMONTH(R11,1) -> 45107 | T11: =EOMONTH(S11,1) -> 45138 | U11: =EOMONTH(T11,1) -> 45169 | V11: =EOMONTH(U11,1) -> 45199 | ... CV11: =EOMONTH(CU11,1) -> 47573
B16: x | D16: Inventory
D18: Inventory Beginning Balance
D19: =[1]Key!$W$12 -> BARI | Z19: =Y73 -> 0 | AA19: =Z73 -> 0 | AB19: =AA73 -> 0 | AC19: =AB73 -> 0 | AD19: =AC73 -> 0 | AE19: =AD73 -> 0 | AF19: =AE73 -> 0 | AG19: =AF73 -> 0 | ... CV19: =CU73 -> 293436
D20: =[1]Key!$W$13 -> BRAIN DEAD OAKLEY | Z20: =Y74 -> 0 | AA20: =Z74 -> 0 | AB20: =AA74 -> 0 | AC20: =AB74 -> 0 | AD20: =AC74 -> 0 | AE20: =AD74 -> 0 | AF20: =AE74 -> 0 | AG20: =AF74 -> 0 | ... CV20: =CU74 -> 264092.4
D21: =[1]Key!$W$14 -> GROWTH "HIT" PH | Z21: =Y75 -> 0 | AA21: =Z75 -> 0 | AB21: =AA75 -> 0 | AC21: =AB75 -> 0 | AD21: =AC75 -> 0 | AE21: =AD75 -> 0 | AF21: =AE75 -> 0 | AG21: =AF75 -> 0 | ... CV21: =CU75 -> 1600560
D22: =[1]Key!$W$15 -> ICE STUDIOS | Z22: =Y76 -> 0 | AA22: =Z76 -> 0 | AB22: =AA76 -> 0 | AC22: =AB76 -> 0 | AD22: =AC76 -> 0 | AE22: =AD76 -> 0 | AF22: =AE76 -> 0 | AG22: =AF76 -> 0 | ... CV22: =CU76 -> 2336394.4
D23: =[1]Key!$W$16 -> MURAKAMI / TORITON | Z23: =Y77 -> 0 | AA23: =Z77 -> 138720 | AB23: =AA77 -> 153170 | AC23: =AB77 -> 14450 | AD23: =AC77 -> 14450 | AE23: =AD77 -> 361250 | AF23: =AE77 -> 346800 | AG23: =AF77 -> 28900 | ... CV23: =CU77 -> 1580060.8
D24: =[1]Key!$W$17 -> NEW PARTNER 1 | Z24: =Y78 -> 0 | AA24: =Z78 -> 0 | AB24: =AA78 -> 0 | AC24: =AB78 -> 0 | AD24: =AC78 -> 0 | AE24: =AD78 -> 0 | AF24: =AE78 -> 0 | AG24: =AF78 -> 0 | ... CV24: =CU78 -> 448875
D25: =[1]Key!$W$18 -> NEW PARTNER 2 | Z25: =Y79 -> 0 | AA25: =Z79 -> 0 | AB25: =AA79 -> 0 | AC25: =AB79 -> 0 | AD25: =AC79 -> 0 | AE25: =AD79 -> 0 | AF25: =AE79 -> 0 | AG25: =AF79 -> 0 | ... CV25: =CU79 -> 1292760
D26: =[1]Key!$W$19 -> PIGALLE | Z26: =Y80 -> 0 | AA26: =Z80 -> 0 | AB26: =AA80 -> 0 | AC26: =AB80 -> 0 | AD26: =AC80 -> 0 | AE26: =AD80 -> 0 | AF26: =AE80 -> 0 | AG26: =AF80 -> 0 | ... CV26: =CU80 -> 160056
D27: =[1]Key!$W$20 -> SPORT PLACEHOLDER | Z27: =Y81 -> 0 | AA27: =Z81 -> 0 | AB27: =AA81 -> 0 | AC27: =AB81 -> 0 | AD27: =AC81 -> 0 | AE27: =AD81 -> 0 | AF27: =AE81 -> 0 | AG27: =AF81 -> 0 | ... CV27: =CU81 -> 4617000
D28: =[1]Key!$W$21 -> SPUNGE | Z28: =Y82 -> 0 | AA28: =Z82 -> 0 | AB28: =AA82 -> 0 | AC28: =AB82 -> 0 | AD28: =AC82 -> 0 | AE28: =AD82 -> 0 | AF28: =AE82 -> 0 | AG28: =AF82 -> 0 | ... CV28: =CU82 -> 2890755
D29: =[1]Key!$W$22 -> SUNFLOWER | Z29: =Y83 -> 0 | AA29: =Z83 -> 0 | AB29: =AA83 -> 0 | AC29: =AB83 -> 0 | AD29: =AC83 -> 0 | AE29: =AD83 -> 0 | AF29: =AE83 -> 0 | AG29: =AF83 -> 0 | ... CV29: =CU83 -> 466830
D30: =[1]Key!$W$23 -> Corporate | Z30: =Y84 -> 1161.84 | AA30: =Z84 -> 0 | AB30: =AA84 -> 0 | AC30: =AB84 -> 0 | AD30: =AC84 -> 0 | AE30: =AD84 -> 0 | AF30: =AE84 -> 0 | AG30: =AF84 -> 0 | ... CV30: =CU84 -> 0
D32: Total | Z32: =SUM(Z19:Z31) -> 1161.84 | AA32: =SUM(AA19:AA31) -> 138720 | AB32: =SUM(AB19:AB31) -> 153170 | AC32: =SUM(AC19:AC31) -> 14450 | AD32: =SUM(AD19:AD31) -> 14450 | AE32: =SUM(AE19:AE31) -> 361250 | AF32: =SUM(AF19:AF31) -> 346800 | AG32: =SUM(AG19:AG31) -> 28900 | ... CV32: =SUM(CV19:CV31) -> 15950820
D36: Inventory Sold
D37: =[1]Key!$W$12 -> BARI | Z37: =[1]CostSumm!AS28 -> 0 | AA37: =[1]CostSumm!AT28 -> 0 | AB37: =[1]CostSumm!AU28 -> 0 | AC37: =[1]CostSumm!AV28 -> 0 | AD37: =[1]CostSumm!AW28 -> 0 | AE37: =[1]CostSumm!AX28 -> 0 | AF37: =[1]CostSumm!AY28 -> 0 | AG37: =[1]CostSumm!AZ28 -> 0 | ... CS37: =[1]CostSumm!DL28 -> 512179.2 | CT37: =AVERAGE($CN37:$CS37) -> 293436 | CU37: =AVERAGE($CN37:$CS37) -> 293436 | CV37: =AVERAGE($CN37:$CS37) -> 293436
D38: =[1]Key!$W$13 -> BRAIN DEAD OAKLEY | Z38: =[1]CostSumm!AS29 -> 0 | AA38: =[1]CostSumm!AT29 -> 0 | AB38: =[1]CostSumm!AU29 -> 0 | AC38: =[1]CostSumm!AV29 -> 0 | AD38: =[1]CostSumm!AW29 -> 0 | AE38: =[1]CostSumm!AX29 -> 0 | AF38: =[1]CostSumm!AY29 -> 0 | AG38: =[1]CostSumm!AZ29 -> 0 | ... CS38: =[1]CostSumm!DL29 -> 0 | CT38: =AVERAGE($CN38:$CS38) -> 264092.4 | CU38: =AVERAGE($CN38:$CS38) -> 264092.4 | CV38: =AVERAGE($CN38:$CS38) -> 264092.4
D39: =[1]Key!$W$14 -> GROWTH "HIT" PH | Z39: =[1]CostSumm!AS30 -> 0 | AA39: =[1]CostSumm!AT30 -> 0 | AB39: =[1]CostSumm!AU30 -> 0 | AC39: =[1]CostSumm!AV30 -> 0 | AD39: =[1]CostSumm!AW30 -> 0 | AE39: =[1]CostSumm!AX30 -> 0 | AF39: =[1]CostSumm!AY30 -> 0 | AG39: =[1]CostSumm!AZ30 -> 0 | ... CS39: =[1]CostSumm!DL30 -> 0 | CT39: =AVERAGE($CN39:$CS39) -> 1600560 | CU39: =AVERAGE($CN39:$CS39) -> 1600560 | CV39: =AVERAGE($CN39:$CS39) -> 1600560
D40: =[1]Key!$W$15 -> ICE STUDIOS | Z40: =[1]CostSumm!AS31 -> 0 | AA40: =[1]CostSumm!AT31 -> 0 | AB40: =[1]CostSumm!AU31 -> 0 | AC40: =[1]CostSumm!AV31 -> 0 | AD40: =[1]CostSumm!AW31 -> 0 | AE40: =[1]CostSumm!AX31 -> 0 | AF40: =[1]CostSumm!AY31 -> 0 | AG40: =[1]CostSumm!AZ31 -> 0 | ... CS40: =[1]CostSumm!DL31 -> 6766790.6 | CT40: =AVERAGE($CN40:$CS40) -> 2336394.4 | CU40: =AVERAGE($CN40:$CS40) -> 2336394.4 | CV40: =AVERAGE($CN40:$CS40) -> 2336394.4
D41: =[1]Key!$W$16 -> MURAKAMI / TORITON | Z41: =[1]CostSumm!AS32 -> 0 | AA41: =[1]CostSumm!AT32 -> 0 | AB41: =[1]CostSumm!AU32 -> 138720 | AC41: =[1]CostSumm!AV32 -> 14450 | AD41: =[1]CostSumm!AW32 -> 0 | AE41: =[1]CostSumm!AX32 -> 14450 | AF41: =[1]CostSumm!AY32 -> 346800 | AG41: =[1]CostSumm!AZ32 -> 0 | ... CS41: =[1]CostSumm!DL32 -> 1615950 | CT41: =AVERAGE($CN41:$CS41) -> 1580060.8 | CU41: =AVERAGE($CN41:$CS41) -> 1580060.8 | CV41: =AVERAGE($CN41:$CS41) -> 1580060.8
D42: =[1]Key!$W$17 -> NEW PARTNER 1 | Z42: =[1]CostSumm!AS33 -> 0 | AA42: =[1]CostSumm!AT33 -> 0 | AB42: =[1]CostSumm!AU33 -> 0 | AC42: =[1]CostSumm!AV33 -> 0 | AD42: =[1]CostSumm!AW33 -> 0 | AE42: =[1]CostSumm!AX33 -> 0 | AF42: =[1]CostSumm!AY33 -> 0 | AG42: =[1]CostSumm!AZ33 -> 0 | ... CS42: =[1]CostSumm!DL33 -> 0 | CT42: =AVERAGE($CN42:$CS42) -> 448875 | CU42: =AVERAGE($CN42:$CS42) -> 448875 | CV42: =AVERAGE($CN42:$CS42) -> 448875
D43: =[1]Key!$W$18 -> NEW PARTNER 2 | Z43: =[1]CostSumm!AS34 -> 0 | AA43: =[1]CostSumm!AT34 -> 0 | AB43: =[1]CostSumm!AU34 -> 0 | AC43: =[1]CostSumm!AV34 -> 0 | AD43: =[1]CostSumm!AW34 -> 0 | AE43: =[1]CostSumm!AX34 -> 0 | AF43: =[1]CostSumm!AY34 -> 0 | AG43: =[1]CostSumm!AZ34 -> 0 | ... CS43: =[1]CostSumm!DL34 -> 0 | CT43: =AVERAGE($CN43:$CS43) -> 1292760 | CU43: =AVERAGE($CN43:$CS43) -> 1292760 | CV43: =AVERAGE($CN43:$CS43) -> 1292760
D44: =[1]Key!$W$19 -> PIGALLE | Z44: =[1]CostSumm!AS35 -> 0 | AA44: =[1]CostSumm!AT35 -> 0 | AB44: =[1]CostSumm!AU35 -> 0 | AC44: =[1]CostSumm!AV35 -> 0 | AD44: =[1]CostSumm!AW35 -> 0 | AE44: =[1]CostSumm!AX35 -> 0 | AF44: =[1]CostSumm!AY35 -> 0 | AG44: =[1]CostSumm!AZ35 -> 0 | ... CS44: =[1]CostSumm!DL35 -> 0 | CT44: =AVERAGE($CN44:$CS44) -> 160056 | CU44: =AVERAGE($CN44:$CS44) -> 160056 | CV44: =AVERAGE($CN44:$CS44) -> 160056
D45: =[1]Key!$W$20 -> SPORT PLACEHOLDER | Z45: =[1]CostSumm!AS36 -> 0 | AA45: =[1]CostSumm!AT36 -> 0 | AB45: =[1]CostSumm!AU36 -> 0 | AC45: =[1]CostSumm!AV36 -> 0 | AD45: =[1]CostSumm!AW36 -> 0 | AE45: =[1]CostSumm!AX36 -> 0 | AF45: =[1]CostSumm!AY36 -> 0 | AG45: =[1]CostSumm!AZ36 -> 0 | ... CS45: =[1]CostSumm!DL36 -> 0 | CT45: =AVERAGE($CN45:$CS45) -> 4617000 | CU45: =AVERAGE($CN45:$CS45) -> 4617000 | CV45: =AVERAGE($CN45:$CS45) -> 4617000
D46: =[1]Key!$W$21 -> SPUNGE | Z46: =[1]CostSumm!AS37 -> 0 | AA46: =[1]CostSumm!AT37 -> 0 | AB46: =[1]CostSumm!AU37 -> 0 | AC46: =[1]CostSumm!AV37 -> 0 | AD46: =[1]CostSumm!AW37 -> 0 | AE46: =[1]CostSumm!AX37 -> 0 | AF46: =[1]CostSumm!AY37 -> 0 | AG46: =[1]CostSumm!AZ37 -> 0 | ... CS46: =[1]CostSumm!DL37 -> 1615950 | CT46: =AVERAGE($CN46:$CS46) -> 2890755 | CU46: =AVERAGE($CN46:$CS46) -> 2890755 | CV46: =AVERAGE($CN46:$CS46) -> 2890755
D47: =[1]Key!$W$22 -> SUNFLOWER | Z47: =[1]CostSumm!AS38 -> 0 | AA47: =[1]CostSumm!AT38 -> 0 | AB47: =[1]CostSumm!AU38 -> 0 | AC47: =[1]CostSumm!AV38 -> 0 | AD47: =[1]CostSumm!AW38 -> 0 | AE47: =[1]CostSumm!AX38 -> 0 | AF47: =[1]CostSumm!AY38 -> 0 | AG47: =[1]CostSumm!AZ38 -> 0 | ... CS47: =[1]CostSumm!DL38 -> 0 | CT47: =AVERAGE($CN47:$CS47) -> 466830 | CU47: =AVERAGE($CN47:$CS47) -> 466830 | CV47: =AVERAGE($CN47:$CS47) -> 466830
D48: =[1]Key!$W$23 -> Corporate | Z48: =Y84 -> 1161.84
D50: Total | Z50: =SUM(Z37:Z49) -> 1161.84 | AA50: =SUM(AA37:AA49) -> 0 | AB50: =SUM(AB37:AB49) -> 138720 | AC50: =SUM(AC37:AC49) -> 14450 | AD50: =SUM(AD37:AD49) -> 0 | AE50: =SUM(AE37:AE49) -> 14450 | AF50: =SUM(AF37:AF49) -> 346800 | AG50: =SUM(AG37:AG49) -> 0 | ... CV50: =SUM(CV37:CV49) -> 15950820
D53: Forced Nov/Dec26 to tie to prior forecast
D54: Inventory Purchased | F54: Leadtime Days
D55: =[1]Key!$W12 -> BARI | F55: =[1]Key!$AD12 -> -60 | Z55: =IF($F55<=0,OFFSET(INDEX($Z$37:$CV$49,MATCH($D55,$D$37:$D$49,0),MATCH(Z$11,$Z$11:$CV$11,0)),0,-ROUNDUP($F55/30,0)),OFFSET(INDEX($Z$37:$CV$49,MATCH($D55,$D$37:$D$49,0),MATCH(Z$11,$Z$11:$CV$11,0)),0,-ROUNDUP($F55/30,0))) -> 0 | AA55: =IF($F55<=0,OFFSET(INDEX($Z$37:$CV$49,MATCH($D55,$D$37:$D$49,0),MATCH(AA$11,$Z$11:$CV$11,0)),0,-ROUNDUP($F55/30,0)),OFFSET(INDEX($Z$37:$CV$49,MATCH($D55,$D$37:$D$49,0),MATCH(AA$11,$Z$11:$CV$11,0)),0,-ROUNDUP($F55/30,0))) -> 0 | AB55: =IF($F55<=0,OFFSET(INDEX($Z$37:$CV$49,MATCH($D55,$D$37:$D$49,0),MATCH(AB$11,$Z$11:$CV$11,0)),0,-ROUNDUP($F55/30,0)),OFFSET(INDEX($Z$37:$CV$49,MATCH($D55,$D$37:$D$49,0),MATCH(AB$11,$Z$11:$CV$11,0)),0,-ROUNDUP($F55/30,0))) -> 0 | AC55: =IF($F55<=0,OFFSET(INDEX($Z$37:$CV$49,MATCH($D55,$D$37:$D$49,0),MATCH(AC$11,$Z$11:$CV$11,0)),0,-ROUNDUP($F55/30,0)),OFFSET(INDEX($Z$37:$CV$49,MATCH($D55,$D$37:$D$49,0),MATCH(AC$11,$Z$11:$CV$11,0)),0,-ROUNDUP($F55/30,0))) -> 0 | AD55: =IF($F55<=0,OFFSET(INDEX($Z$37:$CV$49,MATCH($D55,$D$37:$D$49,0),MATCH(AD$11,$Z$11:$CV$11,0)),0,-ROUNDUP($F55/30,0)),OFFSET(INDEX($Z$37:$CV$49,MATCH($D55,$D$37:$D$49,0),MATCH(AD$11,$Z$11:$CV$11,0)),0,-ROUNDUP($F55/30,0))) -> 0 | AE55: =IF($F55<=0,OFFSET(INDEX($Z$37:$CV$49,MATCH($D55,$D$37:$D$49,0),MATCH(AE$11,$Z$11:$CV$11,0)),0,-ROUNDUP($F55/30,0)),OFFSET(INDEX($Z$37:$CV$49,MATCH($D55,$D$37:$D$49,0),MATCH(AE$11,$Z$11:$CV$11,0)),0,-ROUNDUP($F55/30,0))) -> 0 | AF55: =IF($F55<=0,OFFSET(INDEX($Z$37:$CV$49,MATCH($D55,$D$37:$D$49,0),MATCH(AF$11,$Z$11:$CV$11,0)),0,-ROUNDUP($F55/30,0)),OFFSET(INDEX($Z$37:$CV$49,MATCH($D55,$D$37:$D$49,0),MATCH(AF$11,$Z$11:$CV$11,0)),0,-ROUNDUP($F55/30,0))) -> 0 | AG55: =IF($F55<=0,OFFSET(INDEX($Z$37:$CV$49,MATCH($D55,$D$37:$D$49,0),MATCH(AG$11,$Z$11:$CV$11,0)),0,-ROUNDUP($F55/30,0)),OFFSET(INDEX($Z$37:$CV$49,MATCH($D55,$D$37:$D$49,0),MATCH(AG$11,$Z$11:$CV$11,0)),0,-ROUNDUP($F55/30,0))) -> 24300 | ... CV55: =IF($F55<=0,OFFSET(INDEX($Z$37:$CV$49,MATCH($D55,$D$37:$D$49,0),MATCH(CV$11,$Z$11:$CV$11,0)),0,-ROUNDUP($F55/30,0)),OFFSET(INDEX($Z$37:$CV$49,MATCH($D55,$D$37:$D$49,0),MATCH(CV$11,$Z$11:$CV$11,0)),0,-ROUNDUP($F55/30,0))) -> 0
D56: =[1]Key!$W13 -> BRAIN DEAD OAKLEY | F56: =[1]Key!$AD13 -> -60 | Z56: =IF($F56<=0,OFFSET(INDEX($Z$37:$CV$49,MATCH($D56,$D$37:$D$49,0),MATCH(Z$11,$Z$11:$CV$11,0)),0,-ROUNDUP($F56/30,0)),OFFSET(INDEX($Z$37:$CV$49,MATCH($D56,$D$37:$D$49,0),MATCH(Z$11,$Z$11:$CV$11,0)),0,-ROUNDUP($F56/30,0))) -> 0 | AA56: =IF($F56<=0,OFFSET(INDEX($Z$37:$CV$49,MATCH($D56,$D$37:$D$49,0),MATCH(AA$11,$Z$11:$CV$11,0)),0,-ROUNDUP($F56/30,0)),OFFSET(INDEX($Z$37:$CV$49,MATCH($D56,$D$37:$D$49,0),MATCH(AA$11,$Z$11:$CV$11,0)),0,-ROUNDUP($F56/30,0))) -> 0 | AB56: =IF($F56<=0,OFFSET(INDEX($Z$37:$CV$49,MATCH($D56,$D$37:$D$49,0),MATCH(AB$11,$Z$11:$CV$11,0)),0,-ROUNDUP($F56/30,0)),OFFSET(INDEX($Z$37:$CV$49,MATCH($D56,$D$37:$D$49,0),MATCH(AB$11,$Z$11:$CV$11,0)),0,-ROUNDUP($F56/30,0))) -> 0 | AC56: =IF($F56<=0,OFFSET(INDEX($Z$37:$CV$49,MATCH($D56,$D$37:$D$49,0),MATCH(AC$11,$Z$11:$CV$11,0)),0,-ROUNDUP($F56/30,0)),OFFSET(INDEX($Z$37:$CV$49,MATCH($D56,$D$37:$D$49,0),MATCH(AC$11,$Z$11:$CV$11,0)),0,-ROUNDUP($F56/30,0))) -> 0 | AD56: =IF($F56<=0,OFFSET(INDEX($Z$37:$CV$49,MATCH($D56,$D$37:$D$49,0),MATCH(AD$11,$Z$11:$CV$11,0)),0,-ROUNDUP($F56/30,0)),OFFSET(INDEX($Z$37:$CV$49,MATCH($D56,$D$37:$D$49,0),MATCH(AD$11,$Z$11:$CV$11,0)),0,-ROUNDUP($F56/30,0))) -> 0 | AE56: =IF($F56<=0,OFFSET(INDEX($Z$37:$CV$49,MATCH($D56,$D$37:$D$49,0),MATCH(AE$11,$Z$11:$CV$11,0)),0,-ROUNDUP($F56/30,0)),OFFSET(INDEX($Z$37:$CV$49,MATCH($D56,$D$37:$D$49,0),MATCH(AE$11,$Z$11:$CV$11,0)),0,-ROUNDUP($F56/30,0))) -> 0 | AF56: =IF($F56<=0,OFFSET(INDEX($Z$37:$CV$49,MATCH($D56,$D$37:$D$49,0),MATCH(AF$11,$Z$11:$CV$11,0)),0,-ROUNDUP($F56/30,0)),OFFSET(INDEX($Z$37:$CV$49,MATCH($D56,$D$37:$D$49,0),MATCH(AF$11,$Z$11:$CV$11,0)),0,-ROUNDUP($F56/30,0))) -> 0 | AG56: =IF($F56<=0,OFFSET(INDEX($Z$37:$CV$49,MATCH($D56,$D$37:$D$49,0),MATCH(AG$11,$Z$11:$CV$11,0)),0,-ROUNDUP($F56/30,0)),OFFSET(INDEX($Z$37:$CV$49,MATCH($D56,$D$37:$D$49,0),MATCH(AG$11,$Z$11:$CV$11,0)),0,-ROUNDUP($F56/30,0))) -> 0 | ... CV56: =IF($F56<=0,OFFSET(INDEX($Z$37:$CV$49,MATCH($D56,$D$37:$D$49,0),MATCH(CV$11,$Z$11:$CV$11,0)),0,-ROUNDUP($F56/30,0)),OFFSET(INDEX($Z$37:$CV$49,MATCH($D56,$D$37:$D$49,0),MATCH(CV$11,$Z$11:$CV$11,0)),0,-ROUNDUP($F56/30,0))) -> 0
D57: =[1]Key!$W14 -> GROWTH "HIT" PH | F57: =[1]Key!$AD14 -> -60 | Z57: =IF($F57<=0,OFFSET(INDEX($Z$37:$CV$49,MATCH($D57,$D$37:$D$49,0),MATCH(Z$11,$Z$11:$CV$11,0)),0,-ROUNDUP($F57/30,0)),OFFSET(INDEX($Z$37:$CV$49,MATCH($D57,$D$37:$D$49,0),MATCH(Z$11,$Z$11:$CV$11,0)),0,-ROUNDUP($F57/30,0))) -> 0 | AA57: =IF($F57<=0,OFFSET(INDEX($Z$37:$CV$49,MATCH($D57,$D$37:$D$49,0),MATCH(AA$11,$Z$11:$CV$11,0)),0,-ROUNDUP($F57/30,0)),OFFSET(INDEX($Z$37:$CV$49,MATCH($D57,$D$37:$D$49,0),MATCH(AA$11,$Z$11:$CV$11,0)),0,-ROUNDUP($F57/30,0))) -> 0 | AB57: =IF($F57<=0,OFFSET(INDEX($Z$37:$CV$49,MATCH($D57,$D$37:$D$49,0),MATCH(AB$11,$Z$11:$CV$11,0)),0,-ROUNDUP($F57/30,0)),OFFSET(INDEX($Z$37:$CV$49,MATCH($D57,$D$37:$D$49,0),MATCH(AB$11,$Z$11:$CV$11,0)),0,-ROUNDUP($F57/30,0))) -> 0 | AC57: =IF($F57<=0,OFFSET(INDEX($Z$37:$CV$49,MATCH($D57,$D$37:$D$49,0),MATCH(AC$11,$Z$11:$CV$11,0)),0,-ROUNDUP($F57/30,0)),OFFSET(INDEX($Z$37:$CV$49,MATCH($D57,$D$37:$D$49,0),MATCH(AC$11,$Z$11:$CV$11,0)),0,-ROUNDUP($F57/30,0))) -> 0 | AD57: =IF($F57<=0,OFFSET(INDEX($Z$37:$CV$49,MATCH($D57,$D$37:$D$49,0),MATCH(AD$11,$Z$11:$CV$11,0)),0,-ROUNDUP($F57/30,0)),OFFSET(INDEX($Z$37:$CV$49,MATCH($D57,$D$37:$D$49,0),MATCH(AD$11,$Z$11:$CV$11,0)),0,-ROUNDUP($F57/30,0))) -> 0 | AE57: =IF($F57<=0,OFFSET(INDEX($Z$37:$CV$49,MATCH($D57,$D$37:$D$49,0),MATCH(AE$11,$Z$11:$CV$11,0)),0,-ROUNDUP($F57/30,0)),OFFSET(INDEX($Z$37:$CV$49,MATCH($D57,$D$37:$D$49,0),MATCH(AE$11,$Z$11:$CV$11,0)),0,-ROUNDUP($F57/30,0))) -> 0 | AF57: =IF($F57<=0,OFFSET(INDEX($Z$37:$CV$49,MATCH($D57,$D$37:$D$49,0),MATCH(AF$11,$Z$11:$CV$11,0)),0,-ROUNDUP($F57/30,0)),OFFSET(INDEX($Z$37:$CV$49,MATCH($D57,$D$37:$D$49,0),MATCH(AF$11,$Z$11:$CV$11,0)),0,-ROUNDUP($F57/30,0))) -> 0 | AG57: =IF($F57<=0,OFFSET(INDEX($Z$37:$CV$49,MATCH($D57,$D$37:$D$49,0),MATCH(AG$11,$Z$11:$CV$11,0)),0,-ROUNDUP($F57/30,0)),OFFSET(INDEX($Z$37:$CV$49,MATCH($D57,$D$37:$D$49,0),MATCH(AG$11,$Z$11:$CV$11,0)),0,-ROUNDUP($F57/30,0))) -> 0 | ... CV57: =IF($F57<=0,OFFSET(INDEX($Z$37:$CV$49,MATCH($D57,$D$37:$D$49,0),MATCH(CV$11,$Z$11:$CV$11,0)),0,-ROUNDUP($F57/30,0)),OFFSET(INDEX($Z$37:$CV$49,MATCH($D57,$D$37:$D$49,0),MATCH(CV$11,$Z$11:$CV$11,0)),0,-ROUNDUP($F57/30,0))) -> 0
D58: =[1]Key!$W15 -> ICE STUDIOS | F58: =[1]Key!$AD15 -> -60 | Z58: =IF($F58<=0,OFFSET(INDEX($Z$37:$CV$49,MATCH($D58,$D$37:$D$49,0),MATCH(Z$11,$Z$11:$CV$11,0)),0,-ROUNDUP($F58/30,0)),OFFSET(INDEX($Z$37:$CV$49,MATCH($D58,$D$37:$D$49,0),MATCH(Z$11,$Z$11:$CV$11,0)),0,-ROUNDUP($F58/30,0))) -> 0 | AA58: =IF($F58<=0,OFFSET(INDEX($Z$37:$CV$49,MATCH($D58,$D$37:$D$49,0),MATCH(AA$11,$Z$11:$CV$11,0)),0,-ROUNDUP($F58/30,0)),OFFSET(INDEX($Z$37:$CV$49,MATCH($D58,$D$37:$D$49,0),MATCH(AA$11,$Z$11:$CV$11,0)),0,-ROUNDUP($F58/30,0))) -> 0 | AB58: =IF($F58<=0,OFFSET(INDEX($Z$37:$CV$49,MATCH($D58,$D$37:$D$49,0),MATCH(AB$11,$Z$11:$CV$11,0)),0,-ROUNDUP($F58/30,0)),OFFSET(INDEX($Z$37:$CV$49,MATCH($D58,$D$37:$D$49,0),MATCH(AB$11,$Z$11:$CV$11,0)),0,-ROUNDUP($F58/30,0))) -> 0 | AC58: =IF($F58<=0,OFFSET(INDEX($Z$37:$CV$49,MATCH($D58,$D$37:$D$49,0),MATCH(AC$11,$Z$11:$CV$11,0)),0,-ROUNDUP($F58/30,0)),OFFSET(INDEX($Z$37:$CV$49,MATCH($D58,$D$37:$D$49,0),MATCH(AC$11,$Z$11:$CV$11,0)),0,-ROUNDUP($F58/30,0))) -> 0 | AD58: =IF($F58<=0,OFFSET(INDEX($Z$37:$CV$49,MATCH($D58,$D$37:$D$49,0),MATCH(AD$11,$Z$11:$CV$11,0)),0,-ROUNDUP($F58/30,0)),OFFSET(INDEX($Z$37:$CV$49,MATCH($D58,$D$37:$D$49,0),MATCH(AD$11,$Z$11:$CV$11,0)),0,-ROUNDUP($F58/30,0))) -> 0 | AE58: =IF($F58<=0,OFFSET(INDEX($Z$37:$CV$49,MATCH($D58,$D$37:$D$49,0),MATCH(AE$11,$Z$11:$CV$11,0)),0,-ROUNDUP($F58/30,0)),OFFSET(INDEX($Z$37:$CV$49,MATCH($D58,$D$37:$D$49,0),MATCH(AE$11,$Z$11:$CV$11,0)),0,-ROUNDUP($F58/30,0))) -> 0 | AF58: =IF($F58<=0,OFFSET(INDEX($Z$37:$CV$49,MATCH($D58,$D$37:$D$49,0),MATCH(AF$11,$Z$11:$CV$11,0)),0,-ROUNDUP($F58/30,0)),OFFSET(INDEX($Z$37:$CV$49,MATCH($D58,$D$37:$D$49,0),MATCH(AF$11,$Z$11:$CV$11,0)),0,-ROUNDUP($F58/30,0))) -> 0 | AG58: =IF($F58<=0,OFFSET(INDEX($Z$37:$CV$49,MATCH($D58,$D$37:$D$49,0),MATCH(AG$11,$Z$11:$CV$11,0)),0,-ROUNDUP($F58/30,0)),OFFSET(INDEX($Z$37:$CV$49,MATCH($D58,$D$37:$D$49,0),MATCH(AG$11,$Z$11:$CV$11,0)),0,-ROUNDUP($F58/30,0))) -> 0 | ... CV58: =IF($F58<=0,OFFSET(INDEX($Z$37:$CV$49,MATCH($D58,$D$37:$D$49,0),MATCH(CV$11,$Z$11:$CV$11,0)),0,-ROUNDUP($F58/30,0)),OFFSET(INDEX($Z$37:$CV$49,MATCH($D58,$D$37:$D$49,0),MATCH(CV$11,$Z$11:$CV$11,0)),0,-ROUNDUP($F58/30,0))) -> 0
D59: =[1]Key!$W16 -> MURAKAMI / TORITON | F59: =[1]Key!$AD16 -> -60 | Z59: =IF($F59<=0,OFFSET(INDEX($Z$37:$CV$49,MATCH($D59,$D$37:$D$49,0),MATCH(Z$11,$Z$11:$CV$11,0)),0,-ROUNDUP($F59/30,0)),OFFSET(INDEX($Z$37:$CV$49,MATCH($D59,$D$37:$D$49,0),MATCH(Z$11,$Z$11:$CV$11,0)),0,-ROUNDUP($F59/30,0))) -> 138720 | AA59: =IF($F59<=0,OFFSET(INDEX($Z$37:$CV$49,MATCH($D59,$D$37:$D$49,0),MATCH(AA$11,$Z$11:$CV$11,0)),0,-ROUNDUP($F59/30,0)),OFFSET(INDEX($Z$37:$CV$49,MATCH($D59,$D$37:$D$49,0),MATCH(AA$11,$Z$11:$CV$11,0)),0,-ROUNDUP($F59/30,0))) -> 14450 | AB59: =IF($F59<=0,OFFSET(INDEX($Z$37:$CV$49,MATCH($D59,$D$37:$D$49,0),MATCH(AB$11,$Z$11:$CV$11,0)),0,-ROUNDUP($F59/30,0)),OFFSET(INDEX($Z$37:$CV$49,MATCH($D59,$D$37:$D$49,0),MATCH(AB$11,$Z$11:$CV$11,0)),0,-ROUNDUP($F59/30,0))) -> 0 | AC59: =IF($F59<=0,OFFSET(INDEX($Z$37:$CV$49,MATCH($D59,$D$37:$D$49,0),MATCH(AC$11,$Z$11:$CV$11,0)),0,-ROUNDUP($F59/30,0)),OFFSET(INDEX($Z$37:$CV$49,MATCH($D59,$D$37:$D$49,0),MATCH(AC$11,$Z$11:$CV$11,0)),0,-ROUNDUP($F59/30,0))) -> 14450 | AD59: =IF($F59<=0,OFFSET(INDEX($Z$37:$CV$49,MATCH($D59,$D$37:$D$49,0),MATCH(AD$11,$Z$11:$CV$11,0)),0,-ROUNDUP($F59/30,0)),OFFSET(INDEX($Z$37:$CV$49,MATCH($D59,$D$37:$D$49,0),MATCH(AD$11,$Z$11:$CV$11,0)),0,-ROUNDUP($F59/30,0))) -> 346800 | AE59: =IF($F59<=0,OFFSET(INDEX($Z$37:$CV$49,MATCH($D59,$D$37:$D$49,0),MATCH(AE$11,$Z$11:$CV$11,0)),0,-ROUNDUP($F59/30,0)),OFFSET(INDEX($Z$37:$CV$49,MATCH($D59,$D$37:$D$49,0),MATCH(AE$11,$Z$11:$CV$11,0)),0,-ROUNDUP($F59/30,0))) -> 0 | AF59: =IF($F59<=0,OFFSET(INDEX($Z$37:$CV$49,MATCH($D59,$D$37:$D$49,0),MATCH(AF$11,$Z$11:$CV$11,0)),0,-ROUNDUP($F59/30,0)),OFFSET(INDEX($Z$37:$CV$49,MATCH($D59,$D$37:$D$49,0),MATCH(AF$11,$Z$11:$CV$11,0)),0,-ROUNDUP($F59/30,0))) -> 28900 | AG59: =IF($F59<=0,OFFSET(INDEX($Z$37:$CV$49,MATCH($D59,$D$37:$D$49,0),MATCH(AG$11,$Z$11:$CV$11,0)),0,-ROUNDUP($F59/30,0)),OFFSET(INDEX($Z$37:$CV$49,MATCH($D59,$D$37:$D$49,0),MATCH(AG$11,$Z$11:$CV$11,0)),0,-ROUNDUP($F59/30,0))) -> 0 | ... CV59: =IF($F59<=0,OFFSET(INDEX($Z$37:$CV$49,MATCH($D59,$D$37:$D$49,0),MATCH(CV$11,$Z$11:$CV$11,0)),0,-ROUNDUP($F59/30,0)),OFFSET(INDEX($Z$37:$CV$49,MATCH($D59,$D$37:$D$49,0),MATCH(CV$11,$Z$11:$CV$11,0)),0,-ROUNDUP($F59/30,0))) -> 0
D60: =[1]Key!$W17 -> NEW PARTNER 1 | F60: =[1]Key!$AD17 -> -60 | Z60: =IF($F60<=0,OFFSET(INDEX($Z$37:$CV$49,MATCH($D60,$D$37:$D$49,0),MATCH(Z$11,$Z$11:$CV$11,0)),0,-ROUNDUP($F60/30,0)),OFFSET(INDEX($Z$37:$CV$49,MATCH($D60,$D$37:$D$49,0),MATCH(Z$11,$Z$11:$CV$11,0)),0,-ROUNDUP($F60/30,0))) -> 0 | AA60: =IF($F60<=0,OFFSET(INDEX($Z$37:$CV$49,MATCH($D60,$D$37:$D$49,0),MATCH(AA$11,$Z$11:$CV$11,0)),0,-ROUNDUP($F60/30,0)),OFFSET(INDEX($Z$37:$CV$49,MATCH($D60,$D$37:$D$49,0),MATCH(AA$11,$Z$11:$CV$11,0)),0,-ROUNDUP($F60/30,0))) -> 0 | AB60: =IF($F60<=0,OFFSET(INDEX($Z$37:$CV$49,MATCH($D60,$D$37:$D$49,0),MATCH(AB$11,$Z$11:$CV$11,0)),0,-ROUNDUP($F60/30,0)),OFFSET(INDEX($Z$37:$CV$49,MATCH($D60,$D$37:$D$49,0),MATCH(AB$11,$Z$11:$CV$11,0)),0,-ROUNDUP($F60/30,0))) -> 0 | AC60: =IF($F60<=0,OFFSET(INDEX($Z$37:$CV$49,MATCH($D60,$D$37:$D$49,0),MATCH(AC$11,$Z$11:$CV$11,0)),0,-ROUNDUP($F60/30,0)),OFFSET(INDEX($Z$37:$CV$49,MATCH($D60,$D$37:$D$49,0),MATCH(AC$11,$Z$11:$CV$11,0)),0,-ROUNDUP($F60/30,0))) -> 0 | AD60: =IF($F60<=0,OFFSET(INDEX($Z$37:$CV$49,MATCH($D60,$D$37:$D$49,0),MATCH(AD$11,$Z$11:$CV$11,0)),0,-ROUNDUP($F60/30,0)),OFFSET(INDEX($Z$37:$CV$49,MATCH($D60,$D$37:$D$49,0),MATCH(AD$11,$Z$11:$CV$11,0)),0,-ROUNDUP($F60/30,0))) -> 0 | AE60: =IF($F60<=0,OFFSET(INDEX($Z$37:$CV$49,MATCH($D60,$D$37:$D$49,0),MATCH(AE$11,$Z$11:$CV$11,0)),0,-ROUNDUP($F60/30,0)),OFFSET(INDEX($Z$37:$CV$49,MATCH($D60,$D$37:$D$49,0),MATCH(AE$11,$Z$11:$CV$11,0)),0,-ROUNDUP($F60/30,0))) -> 0 | AF60: =IF($F60<=0,OFFSET(INDEX($Z$37:$CV$49,MATCH($D60,$D$37:$D$49,0),MATCH(AF$11,$Z$11:$CV$11,0)),0,-ROUNDUP($F60/30,0)),OFFSET(INDEX($Z$37:$CV$49,MATCH($D60,$D$37:$D$49,0),MATCH(AF$11,$Z$11:$CV$11,0)),0,-ROUNDUP($F60/30,0))) -> 0 | AG60: =IF($F60<=0,OFFSET(INDEX($Z$37:$CV$49,MATCH($D60,$D$37:$D$49,0),MATCH(AG$11,$Z$11:$CV$11,0)),0,-ROUNDUP($F60/30,0)),OFFSET(INDEX($Z$37:$CV$49,MATCH($D60,$D$37:$D$49,0),MATCH(AG$11,$Z$11:$CV$11,0)),0,-ROUNDUP($F60/30,0))) -> 0 | ... CV60: =IF($F60<=0,OFFSET(INDEX($Z$37:$CV$49,MATCH($D60,$D$37:$D$49,0),MATCH(CV$11,$Z$11:$CV$11,0)),0,-ROUNDUP($F60/30,0)),OFFSET(INDEX($Z$37:$CV$49,MATCH($D60,$D$37:$D$49,0),MATCH(CV$11,$Z$11:$CV$11,0)),0,-ROUNDUP($F60/30,0))) -> 0
D61: =[1]Key!$W18 -> NEW PARTNER 2 | F61: =[1]Key!$AD18 -> -60 | Z61: =IF($F61<=0,OFFSET(INDEX($Z$37:$CV$49,MATCH($D61,$D$37:$D$49,0),MATCH(Z$11,$Z$11:$CV$11,0)),0,-ROUNDUP($F61/30,0)),OFFSET(INDEX($Z$37:$CV$49,MATCH($D61,$D$37:$D$49,0),MATCH(Z$11,$Z$11:$CV$11,0)),0,-ROUNDUP($F61/30,0))) -> 0 | AA61: =IF($F61<=0,OFFSET(INDEX($Z$37:$CV$49,MATCH($D61,$D$37:$D$49,0),MATCH(AA$11,$Z$11:$CV$11,0)),0,-ROUNDUP($F61/30,0)),OFFSET(INDEX($Z$37:$CV$49,MATCH($D61,$D$37:$D$49,0),MATCH(AA$11,$Z$11:$CV$11,0)),0,-ROUNDUP($F61/30,0))) -> 0 | AB61: =IF($F61<=0,OFFSET(INDEX($Z$37:$CV$49,MATCH($D61,$D$37:$D$49,0),MATCH(AB$11,$Z$11:$CV$11,0)),0,-ROUNDUP($F61/30,0)),OFFSET(INDEX($Z$37:$CV$49,MATCH($D61,$D$37:$D$49,0),MATCH(AB$11,$Z$11:$CV$11,0)),0,-ROUNDUP($F61/30,0))) -> 0 | AC61: =IF($F61<=0,OFFSET(INDEX($Z$37:$CV$49,MATCH($D61,$D$37:$D$49,0),MATCH(AC$11,$Z$11:$CV$11,0)),0,-ROUNDUP($F61/30,0)),OFFSET(INDEX($Z$37:$CV$49,MATCH($D61,$D$37:$D$49,0),MATCH(AC$11,$Z$11:$CV$11,0)),0,-ROUNDUP($F61/30,0))) -> 0 | AD61: =IF($F61<=0,OFFSET(INDEX($Z$37:$CV$49,MATCH($D61,$D$37:$D$49,0),MATCH(AD$11,$Z$11:$CV$11,0)),0,-ROUNDUP($F61/30,0)),OFFSET(INDEX($Z$37:$CV$49,MATCH($D61,$D$37:$D$49,0),MATCH(AD$11,$Z$11:$CV$11,0)),0,-ROUNDUP($F61/30,0))) -> 0 | AE61: =IF($F61<=0,OFFSET(INDEX($Z$37:$CV$49,MATCH($D61,$D$37:$D$49,0),MATCH(AE$11,$Z$11:$CV$11,0)),0,-ROUNDUP($F61/30,0)),OFFSET(INDEX($Z$37:$CV$49,MATCH($D61,$D$37:$D$49,0),MATCH(AE$11,$Z$11:$CV$11,0)),0,-ROUNDUP($F61/30,0))) -> 0 | AF61: =IF($F61<=0,OFFSET(INDEX($Z$37:$CV$49,MATCH($D61,$D$37:$D$49,0),MATCH(AF$11,$Z$11:$CV$11,0)),0,-ROUNDUP($F61/30,0)),OFFSET(INDEX($Z$37:$CV$49,MATCH($D61,$D$37:$D$49,0),MATCH(AF$11,$Z$11:$CV$11,0)),0,-ROUNDUP($F61/30,0))) -> 0 | AG61: =IF($F61<=0,OFFSET(INDEX($Z$37:$CV$49,MATCH($D61,$D$37:$D$49,0),MATCH(AG$11,$Z$11:$CV$11,0)),0,-ROUNDUP($F61/30,0)),OFFSET(INDEX($Z$37:$CV$49,MATCH($D61,$D$37:$D$49,0),MATCH(AG$11,$Z$11:$CV$11,0)),0,-ROUNDUP($F61/30,0))) -> 0 | ... CV61: =IF($F61<=0,OFFSET(INDEX($Z$37:$CV$49,MATCH($D61,$D$37:$D$49,0),MATCH(CV$11,$Z$11:$CV$11,0)),0,-ROUNDUP($F61/30,0)),OFFSET(INDEX($Z$37:$CV$49,MATCH($D61,$D$37:$D$49,0),MATCH(CV$11,$Z$11:$CV$11,0)),0,-ROUNDUP($F61/30,0))) -> 0
D62: =[1]Key!$W19 -> PIGALLE | F62: =[1]Key!$AD19 -> -60 | Z62: =IF($F62<=0,OFFSET(INDEX($Z$37:$CV$49,MATCH($D62,$D$37:$D$49,0),MATCH(Z$11,$Z$11:$CV$11,0)),0,-ROUNDUP($F62/30,0)),OFFSET(INDEX($Z$37:$CV$49,MATCH($D62,$D$37:$D$49,0),MATCH(Z$11,$Z$11:$CV$11,0)),0,-ROUNDUP($F62/30,0))) -> 0 | AA62: =IF($F62<=0,OFFSET(INDEX($Z$37:$CV$49,MATCH($D62,$D$37:$D$49,0),MATCH(AA$11,$Z$11:$CV$11,0)),0,-ROUNDUP($F62/30,0)),OFFSET(INDEX($Z$37:$CV$49,MATCH($D62,$D$37:$D$49,0),MATCH(AA$11,$Z$11:$CV$11,0)),0,-ROUNDUP($F62/30,0))) -> 0 | AB62: =IF($F62<=0,OFFSET(INDEX($Z$37:$CV$49,MATCH($D62,$D$37:$D$49,0),MATCH(AB$11,$Z$11:$CV$11,0)),0,-ROUNDUP($F62/30,0)),OFFSET(INDEX($Z$37:$CV$49,MATCH($D62,$D$37:$D$49,0),MATCH(AB$11,$Z$11:$CV$11,0)),0,-ROUNDUP($F62/30,0))) -> 0 | AC62: =IF($F62<=0,OFFSET(INDEX($Z$37:$CV$49,MATCH($D62,$D$37:$D$49,0),MATCH(AC$11,$Z$11:$CV$11,0)),0,-ROUNDUP($F62/30,0)),OFFSET(INDEX($Z$37:$CV$49,MATCH($D62,$D$37:$D$49,0),MATCH(AC$11,$Z$11:$CV$11,0)),0,-ROUNDUP($F62/30,0))) -> 0 | AD62: =IF($F62<=0,OFFSET(INDEX($Z$37:$CV$49,MATCH($D62,$D$37:$D$49,0),MATCH(AD$11,$Z$11:$CV$11,0)),0,-ROUNDUP($F62/30,0)),OFFSET(INDEX($Z$37:$CV$49,MATCH($D62,$D$37:$D$49,0),MATCH(AD$11,$Z$11:$CV$11,0)),0,-ROUNDUP($F62/30,0))) -> 0 | AE62: =IF($F62<=0,OFFSET(INDEX($Z$37:$CV$49,MATCH($D62,$D$37:$D$49,0),MATCH(AE$11,$Z$11:$CV$11,0)),0,-ROUNDUP($F62/30,0)),OFFSET(INDEX($Z$37:$CV$49,MATCH($D62,$D$37:$D$49,0),MATCH(AE$11,$Z$11:$CV$11,0)),0,-ROUNDUP($F62/30,0))) -> 0 | AF62: =IF($F62<=0,OFFSET(INDEX($Z$37:$CV$49,MATCH($D62,$D$37:$D$49,0),MATCH(AF$11,$Z$11:$CV$11,0)),0,-ROUNDUP($F62/30,0)),OFFSET(INDEX($Z$37:$CV$49,MATCH($D62,$D$37:$D$49,0),MATCH(AF$11,$Z$11:$CV$11,0)),0,-ROUNDUP($F62/30,0))) -> 0 | AG62: =IF($F62<=0,OFFSET(INDEX($Z$37:$CV$49,MATCH($D62,$D$37:$D$49,0),MATCH(AG$11,$Z$11:$CV$11,0)),0,-ROUNDUP($F62/30,0)),OFFSET(INDEX($Z$37:$CV$49,MATCH($D62,$D$37:$D$49,0),MATCH(AG$11,$Z$11:$CV$11,0)),0,-ROUNDUP($F62/30,0))) -> 0 | ... CV62: =IF($F62<=0,OFFSET(INDEX($Z$37:$CV$49,MATCH($D62,$D$37:$D$49,0),MATCH(CV$11,$Z$11:$CV$11,0)),0,-ROUNDUP($F62/30,0)),OFFSET(INDEX($Z$37:$CV$49,MATCH($D62,$D$37:$D$49,0),MATCH(CV$11,$Z$11:$CV$11,0)),0,-ROUNDUP($F62/30,0))) -> 0
D63: =[1]Key!$W20 -> SPORT PLACEHOLDER | F63: =[1]Key!$AD20 -> -60 | Z63: =IF($F63<=0,OFFSET(INDEX($Z$37:$CV$49,MATCH($D63,$D$37:$D$49,0),MATCH(Z$11,$Z$11:$CV$11,0)),0,-ROUNDUP($F63/30,0)),OFFSET(INDEX($Z$37:$CV$49,MATCH($D63,$D$37:$D$49,0),MATCH(Z$11,$Z$11:$CV$11,0)),0,-ROUNDUP($F63/30,0))) -> 0 | AA63: =IF($F63<=0,OFFSET(INDEX($Z$37:$CV$49,MATCH($D63,$D$37:$D$49,0),MATCH(AA$11,$Z$11:$CV$11,0)),0,-ROUNDUP($F63/30,0)),OFFSET(INDEX($Z$37:$CV$49,MATCH($D63,$D$37:$D$49,0),MATCH(AA$11,$Z$11:$CV$11,0)),0,-ROUNDUP($F63/30,0))) -> 0 | AB63: =IF($F63<=0,OFFSET(INDEX($Z$37:$CV$49,MATCH($D63,$D$37:$D$49,0),MATCH(AB$11,$Z$11:$CV$11,0)),0,-ROUNDUP($F63/30,0)),OFFSET(INDEX($Z$37:$CV$49,MATCH($D63,$D$37:$D$49,0),MATCH(AB$11,$Z$11:$CV$11,0)),0,-ROUNDUP($F63/30,0))) -> 0 | AC63: =IF($F63<=0,OFFSET(INDEX($Z$37:$CV$49,MATCH($D63,$D$37:$D$49,0),MATCH(AC$11,$Z$11:$CV$11,0)),0,-ROUNDUP($F63/30,0)),OFFSET(INDEX($Z$37:$CV$49,MATCH($D63,$D$37:$D$49,0),MATCH(AC$11,$Z$11:$CV$11,0)),0,-ROUNDUP($F63/30,0))) -> 0 | AD63: =IF($F63<=0,OFFSET(INDEX($Z$37:$CV$49,MATCH($D63,$D$37:$D$49,0),MATCH(AD$11,$Z$11:$CV$11,0)),0,-ROUNDUP($F63/30,0)),OFFSET(INDEX($Z$37:$CV$49,MATCH($D63,$D$37:$D$49,0),MATCH(AD$11,$Z$11:$CV$11,0)),0,-ROUNDUP($F63/30,0))) -> 0 | AE63: =IF($F63<=0,OFFSET(INDEX($Z$37:$CV$49,MATCH($D63,$D$37:$D$49,0),MATCH(AE$11,$Z$11:$CV$11,0)),0,-ROUNDUP($F63/30,0)),OFFSET(INDEX($Z$37:$CV$49,MATCH($D63,$D$37:$D$49,0),MATCH(AE$11,$Z$11:$CV$11,0)),0,-ROUNDUP($F63/30,0))) -> 0 | AF63: =IF($F63<=0,OFFSET(INDEX($Z$37:$CV$49,MATCH($D63,$D$37:$D$49,0),MATCH(AF$11,$Z$11:$CV$11,0)),0,-ROUNDUP($F63/30,0)),OFFSET(INDEX($Z$37:$CV$49,MATCH($D63,$D$37:$D$49,0),MATCH(AF$11,$Z$11:$CV$11,0)),0,-ROUNDUP($F63/30,0))) -> 0 | AG63: =IF($F63<=0,OFFSET(INDEX($Z$37:$CV$49,MATCH($D63,$D$37:$D$49,0),MATCH(AG$11,$Z$11:$CV$11,0)),0,-ROUNDUP($F63/30,0)),OFFSET(INDEX($Z$37:$CV$49,MATCH($D63,$D$37:$D$49,0),MATCH(AG$11,$Z$11:$CV$11,0)),0,-ROUNDUP($F63/30,0))) -> 0 | ... CV63: =IF($F63<=0,OFFSET(INDEX($Z$37:$CV$49,MATCH($D63,$D$37:$D$49,0),MATCH(CV$11,$Z$11:$CV$11,0)),0,-ROUNDUP($F63/30,0)),OFFSET(INDEX($Z$37:$CV$49,MATCH($D63,$D$37:$D$49,0),MATCH(CV$11,$Z$11:$CV$11,0)),0,-ROUNDUP($F63/30,0))) -> 0
D64: =[1]Key!$W21 -> SPUNGE | F64: =[1]Key!$AD21 -> -60 | Z64: =IF($F64<=0,OFFSET(INDEX($Z$37:$CV$49,MATCH($D64,$D$37:$D$49,0),MATCH(Z$11,$Z$11:$CV$11,0)),0,-ROUNDUP($F64/30,0)),OFFSET(INDEX($Z$37:$CV$49,MATCH($D64,$D$37:$D$49,0),MATCH(Z$11,$Z$11:$CV$11,0)),0,-ROUNDUP($F64/30,0))) -> 0 | AA64: =IF($F64<=0,OFFSET(INDEX($Z$37:$CV$49,MATCH($D64,$D$37:$D$49,0),MATCH(AA$11,$Z$11:$CV$11,0)),0,-ROUNDUP($F64/30,0)),OFFSET(INDEX($Z$37:$CV$49,MATCH($D64,$D$37:$D$49,0),MATCH(AA$11,$Z$11:$CV$11,0)),0,-ROUNDUP($F64/30,0))) -> 0 | AB64: =IF($F64<=0,OFFSET(INDEX($Z$37:$CV$49,MATCH($D64,$D$37:$D$49,0),MATCH(AB$11,$Z$11:$CV$11,0)),0,-ROUNDUP($F64/30,0)),OFFSET(INDEX($Z$37:$CV$49,MATCH($D64,$D$37:$D$49,0),MATCH(AB$11,$Z$11:$CV$11,0)),0,-ROUNDUP($F64/30,0))) -> 0 | AC64: =IF($F64<=0,OFFSET(INDEX($Z$37:$CV$49,MATCH($D64,$D$37:$D$49,0),MATCH(AC$11,$Z$11:$CV$11,0)),0,-ROUNDUP($F64/30,0)),OFFSET(INDEX($Z$37:$CV$49,MATCH($D64,$D$37:$D$49,0),MATCH(AC$11,$Z$11:$CV$11,0)),0,-ROUNDUP($F64/30,0))) -> 0 | AD64: =IF($F64<=0,OFFSET(INDEX($Z$37:$CV$49,MATCH($D64,$D$37:$D$49,0),MATCH(AD$11,$Z$11:$CV$11,0)),0,-ROUNDUP($F64/30,0)),OFFSET(INDEX($Z$37:$CV$49,MATCH($D64,$D$37:$D$49,0),MATCH(AD$11,$Z$11:$CV$11,0)),0,-ROUNDUP($F64/30,0))) -> 0 | AE64: =IF($F64<=0,OFFSET(INDEX($Z$37:$CV$49,MATCH($D64,$D$37:$D$49,0),MATCH(AE$11,$Z$11:$CV$11,0)),0,-ROUNDUP($F64/30,0)),OFFSET(INDEX($Z$37:$CV$49,MATCH($D64,$D$37:$D$49,0),MATCH(AE$11,$Z$11:$CV$11,0)),0,-ROUNDUP($F64/30,0))) -> 0 | AF64: =IF($F64<=0,OFFSET(INDEX($Z$37:$CV$49,MATCH($D64,$D$37:$D$49,0),MATCH(AF$11,$Z$11:$CV$11,0)),0,-ROUNDUP($F64/30,0)),OFFSET(INDEX($Z$37:$CV$49,MATCH($D64,$D$37:$D$49,0),MATCH(AF$11,$Z$11:$CV$11,0)),0,-ROUNDUP($F64/30,0))) -> 0 | AG64: =IF($F64<=0,OFFSET(INDEX($Z$37:$CV$49,MATCH($D64,$D$37:$D$49,0),MATCH(AG$11,$Z$11:$CV$11,0)),0,-ROUNDUP($F64/30,0)),OFFSET(INDEX($Z$37:$CV$49,MATCH($D64,$D$37:$D$49,0),MATCH(AG$11,$Z$11:$CV$11,0)),0,-ROUNDUP($F64/30,0))) -> 0 | ... CV64: =IF($F64<=0,OFFSET(INDEX($Z$37:$CV$49,MATCH($D64,$D$37:$D$49,0),MATCH(CV$11,$Z$11:$CV$11,0)),0,-ROUNDUP($F64/30,0)),OFFSET(INDEX($Z$37:$CV$49,MATCH($D64,$D$37:$D$49,0),MATCH(CV$11,$Z$11:$CV$11,0)),0,-ROUNDUP($F64/30,0))) -> 0
D65: =[1]Key!$W22 -> SUNFLOWER | F65: =[1]Key!$AD22 -> -60 | Z65: =IF($F65<=0,OFFSET(INDEX($Z$37:$CV$49,MATCH($D65,$D$37:$D$49,0),MATCH(Z$11,$Z$11:$CV$11,0)),0,-ROUNDUP($F65/30,0)),OFFSET(INDEX($Z$37:$CV$49,MATCH($D65,$D$37:$D$49,0),MATCH(Z$11,$Z$11:$CV$11,0)),0,-ROUNDUP($F65/30,0))) -> 0 | AA65: =IF($F65<=0,OFFSET(INDEX($Z$37:$CV$49,MATCH($D65,$D$37:$D$49,0),MATCH(AA$11,$Z$11:$CV$11,0)),0,-ROUNDUP($F65/30,0)),OFFSET(INDEX($Z$37:$CV$49,MATCH($D65,$D$37:$D$49,0),MATCH(AA$11,$Z$11:$CV$11,0)),0,-ROUNDUP($F65/30,0))) -> 0 | AB65: =IF($F65<=0,OFFSET(INDEX($Z$37:$CV$49,MATCH($D65,$D$37:$D$49,0),MATCH(AB$11,$Z$11:$CV$11,0)),0,-ROUNDUP($F65/30,0)),OFFSET(INDEX($Z$37:$CV$49,MATCH($D65,$D$37:$D$49,0),MATCH(AB$11,$Z$11:$CV$11,0)),0,-ROUNDUP($F65/30,0))) -> 0 | AC65: =IF($F65<=0,OFFSET(INDEX($Z$37:$CV$49,MATCH($D65,$D$37:$D$49,0),MATCH(AC$11,$Z$11:$CV$11,0)),0,-ROUNDUP($F65/30,0)),OFFSET(INDEX($Z$37:$CV$49,MATCH($D65,$D$37:$D$49,0),MATCH(AC$11,$Z$11:$CV$11,0)),0,-ROUNDUP($F65/30,0))) -> 0 | AD65: =IF($F65<=0,OFFSET(INDEX($Z$37:$CV$49,MATCH($D65,$D$37:$D$49,0),MATCH(AD$11,$Z$11:$CV$11,0)),0,-ROUNDUP($F65/30,0)),OFFSET(INDEX($Z$37:$CV$49,MATCH($D65,$D$37:$D$49,0),MATCH(AD$11,$Z$11:$CV$11,0)),0,-ROUNDUP($F65/30,0))) -> 0 | AE65: =IF($F65<=0,OFFSET(INDEX($Z$37:$CV$49,MATCH($D65,$D$37:$D$49,0),MATCH(AE$11,$Z$11:$CV$11,0)),0,-ROUNDUP($F65/30,0)),OFFSET(INDEX($Z$37:$CV$49,MATCH($D65,$D$37:$D$49,0),MATCH(AE$11,$Z$11:$CV$11,0)),0,-ROUNDUP($F65/30,0))) -> 0 | AF65: =IF($F65<=0,OFFSET(INDEX($Z$37:$CV$49,MATCH($D65,$D$37:$D$49,0),MATCH(AF$11,$Z$11:$CV$11,0)),0,-ROUNDUP($F65/30,0)),OFFSET(INDEX($Z$37:$CV$49,MATCH($D65,$D$37:$D$49,0),MATCH(AF$11,$Z$11:$CV$11,0)),0,-ROUNDUP($F65/30,0))) -> 0 | AG65: =IF($F65<=0,OFFSET(INDEX($Z$37:$CV$49,MATCH($D65,$D$37:$D$49,0),MATCH(AG$11,$Z$11:$CV$11,0)),0,-ROUNDUP($F65/30,0)),OFFSET(INDEX($Z$37:$CV$49,MATCH($D65,$D$37:$D$49,0),MATCH(AG$11,$Z$11:$CV$11,0)),0,-ROUNDUP($F65/30,0))) -> 0 | ... CV65: =IF($F65<=0,OFFSET(INDEX($Z$37:$CV$49,MATCH($D65,$D$37:$D$49,0),MATCH(CV$11,$Z$11:$CV$11,0)),0,-ROUNDUP($F65/30,0)),OFFSET(INDEX($Z$37:$CV$49,MATCH($D65,$D$37:$D$49,0),MATCH(CV$11,$Z$11:$CV$11,0)),0,-ROUNDUP($F65/30,0))) -> 0
D66: =[1]Key!$W23 -> Corporate | F66: =[1]Key!$AD23 -> 0
D68: Total | Z68: =SUM(Z55:Z67) -> 138720 | AA68: =SUM(AA55:AA67) -> 14450 | AB68: =SUM(AB55:AB67) -> 0 | AC68: =SUM(AC55:AC67) -> 14450 | AD68: =SUM(AD55:AD67) -> 346800 | AE68: =SUM(AE55:AE67) -> 0 | AF68: =SUM(AF55:AF67) -> 28900 | AG68: =SUM(AG55:AG67) -> 24300 | ... CV68: =SUM(CV55:CV67) -> 0
D72: Ending Inventory | AJ72: =ROUNDUP($G73/30,0) -> 0
D73: =[1]Key!$W$12 -> BARI | Z73: =Z19-Z37+Z55 -> 0 | AA73: =AA19-AA37+AA55 -> 0 | AB73: =AB19-AB37+AB55 -> 0 | AC73: =AC19-AC37+AC55 -> 0 | AD73: =AD19-AD37+AD55 -> 0 | AE73: =AE19-AE37+AE55 -> 0 | AF73: =AF19-AF37+AF55 -> 0 | AG73: =AG19-AG37+AG55 -> 24300 | ... CV73: =CV19-CV37+CV55 -> 2.3283064e-10
D74: =[1]Key!$W$13 -> BRAIN DEAD OAKLEY | Z74: =Z20-Z38+Z56 -> 0 | AA74: =AA20-AA38+AA56 -> 0 | AB74: =AB20-AB38+AB56 -> 0 | AC74: =AC20-AC38+AC56 -> 0 | AD74: =AD20-AD38+AD56 -> 0 | AE74: =AE20-AE38+AE56 -> 0 | AF74: =AF20-AF38+AF56 -> 0 | AG74: =AG20-AG38+AG56 -> 0 | ... CV74: =CV20-CV38+CV56 -> 0
D75: =[1]Key!$W$14 -> GROWTH "HIT" PH | Z75: =Z21-Z39+Z57 -> 0 | AA75: =AA21-AA39+AA57 -> 0 | AB75: =AB21-AB39+AB57 -> 0 | AC75: =AC21-AC39+AC57 -> 0 | AD75: =AD21-AD39+AD57 -> 0 | AE75: =AE21-AE39+AE57 -> 0 | AF75: =AF21-AF39+AF57 -> 0 | AG75: =AG21-AG39+AG57 -> 0 | ... CV75: =CV21-CV39+CV57 -> 0
D76: =[1]Key!$W$15 -> ICE STUDIOS | Z76: =Z22-Z40+Z58 -> 0 | AA76: =AA22-AA40+AA58 -> 0 | AB76: =AB22-AB40+AB58 -> 0 | AC76: =AC22-AC40+AC58 -> 0 | AD76: =AD22-AD40+AD58 -> 0 | AE76: =AE22-AE40+AE58 -> 0 | AF76: =AF22-AF40+AF58 -> 0 | AG76: =AG22-AG40+AG58 -> 0 | ... CV76: =CV22-CV40+CV58 -> 0
D77: =[1]Key!$W$16 -> MURAKAMI / TORITON | Z77: =Z23-Z41+Z59 -> 138720 | AA77: =AA23-AA41+AA59 -> 153170 | AB77: =AB23-AB41+AB59 -> 14450 | AC77: =AC23-AC41+AC59 -> 14450 | AD77: =AD23-AD41+AD59 -> 361250 | AE77: =AE23-AE41+AE59 -> 346800 | AF77: =AF23-AF41+AF59 -> 28900 | AG77: =AG23-AG41+AG59 -> 28900 | ... CV77: =CV23-CV41+CV59 -> 0
D78: =[1]Key!$W$17 -> NEW PARTNER 1 | Z78: =Z24-Z42+Z60 -> 0 | AA78: =AA24-AA42+AA60 -> 0 | AB78: =AB24-AB42+AB60 -> 0 | AC78: =AC24-AC42+AC60 -> 0 | AD78: =AD24-AD42+AD60 -> 0 | AE78: =AE24-AE42+AE60 -> 0 | AF78: =AF24-AF42+AF60 -> 0 | AG78: =AG24-AG42+AG60 -> 0 | ... CV78: =CV24-CV42+CV60 -> 0
D79: =[1]Key!$W$18 -> NEW PARTNER 2 | Z79: =Z25-Z43+Z61 -> 0 | AA79: =AA25-AA43+AA61 -> 0 | AB79: =AB25-AB43+AB61 -> 0 | AC79: =AC25-AC43+AC61 -> 0 | AD79: =AD25-AD43+AD61 -> 0 | AE79: =AE25-AE43+AE61 -> 0 | AF79: =AF25-AF43+AF61 -> 0 | AG79: =AG25-AG43+AG61 -> 0 | ... CV79: =CV25-CV43+CV61 -> 0
D80: =[1]Key!$W$19 -> PIGALLE | Z80: =Z26-Z44+Z62 -> 0 | AA80: =AA26-AA44+AA62 -> 0 | AB80: =AB26-AB44+AB62 -> 0 | AC80: =AC26-AC44+AC62 -> 0 | AD80: =AD26-AD44+AD62 -> 0 | AE80: =AE26-AE44+AE62 -> 0 | AF80: =AF26-AF44+AF62 -> 0 | AG80: =AG26-AG44+AG62 -> 0 | ... CV80: =CV26-CV44+CV62 -> 0
D81: =[1]Key!$W$20 -> SPORT PLACEHOLDER | Z81: =Z27-Z45+Z63 -> 0 | AA81: =AA27-AA45+AA63 -> 0 | AB81: =AB27-AB45+AB63 -> 0 | AC81: =AC27-AC45+AC63 -> 0 | AD81: =AD27-AD45+AD63 -> 0 | AE81: =AE27-AE45+AE63 -> 0 | AF81: =AF27-AF45+AF63 -> 0 | AG81: =AG27-AG45+AG63 -> 0 | ... CV81: =CV27-CV45+CV63 -> 0
D82: =[1]Key!$W$21 -> SPUNGE | Z82: =Z28-Z46+Z64 -> 0 | AA82: =AA28-AA46+AA64 -> 0 | AB82: =AB28-AB46+AB64 -> 0 | AC82: =AC28-AC46+AC64 -> 0 | AD82: =AD28-AD46+AD64 -> 0 | AE82: =AE28-AE46+AE64 -> 0 | AF82: =AF28-AF46+AF64 -> 0 | AG82: =AG28-AG46+AG64 -> 0 | ... CV82: =CV28-CV46+CV64 -> 0
D83: =[1]Key!$W$22 -> SUNFLOWER | Z83: =Z29-Z47+Z65 -> 0 | AA83: =AA29-AA47+AA65 -> 0 | AB83: =AB29-AB47+AB65 -> 0 | AC83: =AC29-AC47+AC65 -> 0 | AD83: =AD29-AD47+AD65 -> 0 | AE83: =AE29-AE47+AE65 -> 0 | AF83: =AF29-AF47+AF65 -> 0 | AG83: =AG29-AG47+AG65 -> 0 | ... CV83: =CV29-CV47+CV65 -> 0
D84: =[1]Key!$W$23 -> Corporate | Y84: =$Y$4 -> 1161.84 | Z84: =Z30-Z48+Z66 -> 0 | AA84: =AA30-AA48+AA66 -> 0 | AB84: =AB30-AB48+AB66 -> 0 | AC84: =AC30-AC48+AC66 -> 0 | AD84: =AD30-AD48+AD66 -> 0 | AE84: =AE30-AE48+AE66 -> 0 | AF84: =AF30-AF48+AF66 -> 0 | AG84: =AG30-AG48+AG66 -> 0 | ... CV84: =CV30-CV48+CV66 -> 0
D86: Total | Y86: =SUM(Y73:Y85) -> 1161.84 | Z86: =SUM(Z73:Z85) -> 138720 | AA86: =SUM(AA73:AA85) -> 153170 | AB86: =SUM(AB73:AB85) -> 14450 | AC86: =SUM(AC73:AC85) -> 14450 | AD86: =SUM(AD73:AD85) -> 361250 | AE86: =SUM(AE73:AE85) -> 346800 | AF86: =SUM(AF73:AF85) -> 28900 | ... CV86: =SUM(CV73:CV85) -> 2.3283064e-10
B90: x
C92: Accounts Receivable
D93: Gross Revenue
D94: =[1]Key!C$12 -> BARI | E94: =[1]Key!D$12 -> Wholesale | Z94: =[1]contras!AS12 -> 0 | AA94: =[1]contras!AT12 -> 0 | AB94: =[1]contras!AU12 -> 0 | AC94: =[1]contras!AV12 -> 0 | AD94: =[1]contras!AW12 -> 0 | AE94: =[1]contras!AX12 -> 0 | AF94: =[1]contras!AY12 -> 0 | AG94: =[1]contras!AZ12 -> 0 | ... CS94: =[1]contras!DL12 -> 353437.5
D95: =[1]Key!C$13 -> BRAIN DEAD OAKLEY | E95: =[1]Key!D$13 -> Wholesale | Z95: =[1]contras!AS13 -> 0 | AA95: =[1]contras!AT13 -> 0 | AB95: =[1]contras!AU13 -> 0 | AC95: =[1]contras!AV13 -> 0 | AD95: =[1]contras!AW13 -> 0 | AE95: =[1]contras!AX13 -> 0 | AF95: =[1]contras!AY13 -> 0 | AG95: =[1]contras!AZ13 -> 0 | ... CS95: =[1]contras!DL13 -> 0
D96: =[1]Key!C$14 -> GROWTH "HIT" PH | E96: =[1]Key!D$14 -> Wholesale | Z96: =[1]contras!AS14 -> 0 | AA96: =[1]contras!AT14 -> 0 | AB96: =[1]contras!AU14 -> 0 | AC96: =[1]contras!AV14 -> 0 | AD96: =[1]contras!AW14 -> 0 | AE96: =[1]contras!AX14 -> 0 | AF96: =[1]contras!AY14 -> 0 | AG96: =[1]contras!AZ14 -> 0 | ... CS96: =[1]contras!DL14 -> 0
D97: =[1]Key!C$15 -> ICE STUDIOS | E97: =[1]Key!D$15 -> Wholesale | Z97: =[1]contras!AS15 -> 0 | AA97: =[1]contras!AT15 -> 0 | AB97: =[1]contras!AU15 -> 0 | AC97: =[1]contras!AV15 -> 0 | AD97: =[1]contras!AW15 -> 0 | AE97: =[1]contras!AX15 -> 0 | AF97: =[1]contras!AY15 -> 0 | AG97: =[1]contras!AZ15 -> 0 | ... CS97: =[1]contras!DL15 -> 5118750
D98: =[1]Key!C$16 -> MURAKAMI / TORITON | E98: =[1]Key!D$16 -> Wholesale | Z98: =[1]contras!AS16 -> 0 | AA98: =[1]contras!AT16 -> 0 | AB98: =[1]contras!AU16 -> 360000 | AC98: =[1]contras!AV16 -> 37500 | AD98: =[1]contras!AW16 -> 0 | AE98: =[1]contras!AX16 -> 0 | AF98: =[1]contras!AY16 -> 0 | AG98: =[1]contras!AZ16 -> 0 | ... CS98: =[1]contras!DL16 -> 689062.5
D99: =[1]Key!C$17 -> NEW PARTNER 1 | E99: =[1]Key!D$17 -> Wholesale | Z99: =[1]contras!AS17 -> 0 | AA99: =[1]contras!AT17 -> 0 | AB99: =[1]contras!AU17 -> 0 | AC99: =[1]contras!AV17 -> 0 | AD99: =[1]contras!AW17 -> 0 | AE99: =[1]contras!AX17 -> 0 | AF99: =[1]contras!AY17 -> 0 | AG99: =[1]contras!AZ17 -> 0 | ... CS99: =[1]contras!DL17 -> 0
D100: =[1]Key!C$18 -> NEW PARTNER 2 | E100: =[1]Key!D$18 -> Wholesale | Z100: =[1]contras!AS18 -> 0 | AA100: =[1]contras!AT18 -> 0 | AB100: =[1]contras!AU18 -> 0 | AC100: =[1]contras!AV18 -> 0 | AD100: =[1]contras!AW18 -> 0 | AE100: =[1]contras!AX18 -> 0 | AF100: =[1]contras!AY18 -> 0 | AG100: =[1]contras!AZ18 -> 0 | ... CS100: =[1]contras!DL18 -> 0
D101: =[1]Key!C$19 -> PIGALLE | E101: =[1]Key!D$19 -> Wholesale | Z101: =[1]contras!AS19 -> 0 | AA101: =[1]contras!AT19 -> 0 | AB101: =[1]contras!AU19 -> 0 | AC101: =[1]contras!AV19 -> 0 | AD101: =[1]contras!AW19 -> 0 | AE101: =[1]contras!AX19 -> 0 | AF101: =[1]contras!AY19 -> 0 | AG101: =[1]contras!AZ19 -> 0 | ... CS101: =[1]contras!DL19 -> 0
D102: =[1]Key!C$20 -> SPORT PLACEHOLDER | E102: =[1]Key!D$20 -> Wholesale | Z102: =[1]contras!AS20 -> 0 | AA102: =[1]contras!AT20 -> 0 | AB102: =[1]contras!AU20 -> 0 | AC102: =[1]contras!AV20 -> 0 | AD102: =[1]contras!AW20 -> 0 | AE102: =[1]contras!AX20 -> 0 | AF102: =[1]contras!AY20 -> 0 | AG102: =[1]contras!AZ20 -> 0 | ... CS102: =[1]contras!DL20 -> 0
D103: =[1]Key!C$21 -> SPUNGE | E103: =[1]Key!D$21 -> Wholesale | Z103: =[1]contras!AS21 -> 0 | AA103: =[1]contras!AT21 -> 0 | AB103: =[1]contras!AU21 -> 0 | AC103: =[1]contras!AV21 -> 0 | AD103: =[1]contras!AW21 -> 0 | AE103: =[1]contras!AX21 -> 0 | AF103: =[1]contras!AY21 -> 0 | AG103: =[1]contras!AZ21 -> 0 | ... CS103: =[1]contras!DL21 -> 1417500
D104: =[1]Key!C$22 -> SUNFLOWER | E104: =[1]Key!D$22 -> Wholesale | Z104: =[1]contras!AS22 -> 0 | AA104: =[1]contras!AT22 -> 0 | AB104: =[1]contras!AU22 -> 0 | AC104: =[1]contras!AV22 -> 0 | AD104: =[1]contras!AW22 -> 0 | AE104: =[1]contras!AX22 -> 0 | AF104: =[1]contras!AY22 -> 0 | AG104: =[1]contras!AZ22 -> 0 | ... CS104: =[1]contras!DL22 -> 0
D105: =[1]Key!C$23 -> BARI | E105: =[1]Key!D$23 -> DTC | Z105: =[1]contras!AS23 -> 0 | AA105: =[1]contras!AT23 -> 0 | AB105: =[1]contras!AU23 -> 0 | AC105: =[1]contras!AV23 -> 0 | AD105: =[1]contras!AW23 -> 0 | AE105: =[1]contras!AX23 -> 0 | AF105: =[1]contras!AY23 -> 0 | AG105: =[1]contras!AZ23 -> 0 | ... CS105: =[1]contras!DL23 -> 2120625
D106: =[1]Key!C$24 -> BRAIN DEAD OAKLEY | E106: =[1]Key!D$24 -> DTC | Z106: =[1]contras!AS24 -> 0 | AA106: =[1]contras!AT24 -> 0 | AB106: =[1]contras!AU24 -> 0 | AC106: =[1]contras!AV24 -> 0 | AD106: =[1]contras!AW24 -> 0 | AE106: =[1]contras!AX24 -> 0 | AF106: =[1]contras!AY24 -> 0 | AG106: =[1]contras!AZ24 -> 0 | ... CS106: =[1]contras!DL24 -> 0
D107: =[1]Key!C$25 -> GROWTH "HIT" PH | E107: =[1]Key!D$25 -> DTC | Z107: =[1]contras!AS25 -> 0 | AA107: =[1]contras!AT25 -> 0 | AB107: =[1]contras!AU25 -> 0 | AC107: =[1]contras!AV25 -> 0 | AD107: =[1]contras!AW25 -> 0 | AE107: =[1]contras!AX25 -> 0 | AF107: =[1]contras!AY25 -> 0 | AG107: =[1]contras!AZ25 -> 0 | ... CS107: =[1]contras!DL25 -> 0
D108: =[1]Key!C$26 -> ICE STUDIOS | E108: =[1]Key!D$26 -> DTC | Z108: =[1]contras!AS26 -> 0 | AA108: =[1]contras!AT26 -> 0 | AB108: =[1]contras!AU26 -> 0 | AC108: =[1]contras!AV26 -> 0 | AD108: =[1]contras!AW26 -> 0 | AE108: =[1]contras!AX26 -> 0 | AF108: =[1]contras!AY26 -> 0 | AG108: =[1]contras!AZ26 -> 0 | ... CS108: =[1]contras!DL26 -> 15356250
D109: =[1]Key!C$27 -> MURAKAMI / TORITON | E109: =[1]Key!D$27 -> DTC | Z109: =[1]contras!AS27 -> 0 | AA109: =[1]contras!AT27 -> 0 | AB109: =[1]contras!AU27 -> 0 | AC109: =[1]contras!AV27 -> 0 | AD109: =[1]contras!AW27 -> 0 | AE109: =[1]contras!AX27 -> 75000 | AF109: =[1]contras!AY27 -> 1800000 | AG109: =[1]contras!AZ27 -> 0 | ... CS109: =[1]contras!DL27 -> 4134375
D110: =[1]Key!C$28 -> NEW PARTNER 1 | E110: =[1]Key!D$28 -> DTC | Z110: =[1]contras!AS28 -> 0 | AA110: =[1]contras!AT28 -> 0 | AB110: =[1]contras!AU28 -> 0 | AC110: =[1]contras!AV28 -> 0 | AD110: =[1]contras!AW28 -> 0 | AE110: =[1]contras!AX28 -> 0 | AF110: =[1]contras!AY28 -> 0 | AG110: =[1]contras!AZ28 -> 0 | ... CS110: =[1]contras!DL28 -> 0
D111: =[1]Key!C$29 -> NEW PARTNER 2 | E111: =[1]Key!D$29 -> DTC | Z111: =[1]contras!AS29 -> 0 | AA111: =[1]contras!AT29 -> 0 | AB111: =[1]contras!AU29 -> 0 | AC111: =[1]contras!AV29 -> 0 | AD111: =[1]contras!AW29 -> 0 | AE111: =[1]contras!AX29 -> 0 | AF111: =[1]contras!AY29 -> 0 | AG111: =[1]contras!AZ29 -> 0 | ... CS111: =[1]contras!DL29 -> 0
D112: =[1]Key!C$30 -> PIGALLE | E112: =[1]Key!D$30 -> DTC | Z112: =[1]contras!AS30 -> 0 | AA112: =[1]contras!AT30 -> 0 | AB112: =[1]contras!AU30 -> 0 | AC112: =[1]contras!AV30 -> 0 | AD112: =[1]contras!AW30 -> 0 | AE112: =[1]contras!AX30 -> 0 | AF112: =[1]contras!AY30 -> 0 | AG112: =[1]contras!AZ30 -> 0 | ... CS112: =[1]contras!DL30 -> 0
D113: =[1]Key!C$31 -> SPORT PLACEHOLDER | E113: =[1]Key!D$31 -> DTC | Z113: =[1]contras!AS31 -> 0 | AA113: =[1]contras!AT31 -> 0 | AB113: =[1]contras!AU31 -> 0 | AC113: =[1]contras!AV31 -> 0 | AD113: =[1]contras!AW31 -> 0 | AE113: =[1]contras!AX31 -> 0 | AF113: =[1]contras!AY31 -> 0 | AG113: =[1]contras!AZ31 -> 0 | ... CS113: =[1]contras!DL31 -> 0
D114: =[1]Key!C$32 -> SPUNGE | E114: =[1]Key!D$32 -> DTC | Z114: =[1]contras!AS32 -> 0 | AA114: =[1]contras!AT32 -> 0 | AB114: =[1]contras!AU32 -> 0 | AC114: =[1]contras!AV32 -> 0 | AD114: =[1]contras!AW32 -> 0 | AE114: =[1]contras!AX32 -> 0 | AF114: =[1]contras!AY32 -> 0 | AG114: =[1]contras!AZ32 -> 0 | ... CS114: =[1]contras!DL32 -> 4252500
D115: =[1]Key!C$33 -> SUNFLOWER | E115: =[1]Key!D$33 -> DTC | Z115: =[1]contras!AS33 -> 0 | AA115: =[1]contras!AT33 -> 0 | AB115: =[1]contras!AU33 -> 0 | AC115: =[1]contras!AV33 -> 0 | AD115: =[1]contras!AW33 -> 0 | AE115: =[1]contras!AX33 -> 0 | AF115: =[1]contras!AY33 -> 0 | AG115: =[1]contras!AZ33 -> 0 | ... CS115: =[1]contras!DL33 -> 0
D116: =[1]Key!C$34 -> Corporate | E116: =[1]Key!D$34 -> N/A
D117: =[1]Key!C$35 -> Other Revenue | E117: =[1]Key!D$35 -> N/A | Z117: =[1]RevSumm!AS$5 -> 42000 | AA117: =[1]RevSumm!AT$5 -> 42000 | AB117: =[1]RevSumm!AU$5 -> 42000 | AC117: =[1]RevSumm!AV$5 -> 42000 | AD117: =[1]RevSumm!AW$5 -> 42000 | AE117: =[1]RevSumm!AX$5 -> 42000 | AF117: =[1]RevSumm!AY$5 -> 42000 | AG117: =[1]RevSumm!AZ$5 -> 42000 | ... CS117: =[1]RevSumm!DL$5 -> 0
D119: Total | Z119: =SUM(Z94:Z118) -> 42000 | AA119: =SUM(AA94:AA118) -> 42000 | AB119: =SUM(AB94:AB118) -> 402000 | AC119: =SUM(AC94:AC118) -> 79500 | AD119: =SUM(AD94:AD118) -> 42000 | AE119: =SUM(AE94:AE118) -> 117000 | AF119: =SUM(AF94:AF118) -> 1842000 | AG119: =SUM(AG94:AG118) -> 42000 | ... CV119: =SUM(CV94:CV118) -> 0
C123: Lookup | D123: Net Revenue
C124: =CONCATENATE(D124,E124) -> BARIWholesale | D124: =[1]Key!C$12 -> BARI | E124: =[1]Key!D$12 -> Wholesale | Z124: =[1]contras!AS40 -> 0 | AA124: =[1]contras!AT40 -> 0 | AB124: =[1]contras!AU40 -> 0 | AC124: =[1]contras!AV40 -> 0 | AD124: =[1]contras!AW40 -> 0 | AE124: =[1]contras!AX40 -> 0 | AF124: =[1]contras!AY40 -> 0 | AG124: =[1]contras!AZ40 -> 0 | ... CS124: =[1]contras!DL40 -> 311025
C125: =CONCATENATE(D125,E125) -> BRAIN DEAD OAKLEYWholesale | D125: =[1]Key!C$13 -> BRAIN DEAD OAKLEY | E125: =[1]Key!D$13 -> Wholesale | Z125: =[1]contras!AS41 -> 0 | AA125: =[1]contras!AT41 -> 0 | AB125: =[1]contras!AU41 -> 0 | AC125: =[1]contras!AV41 -> 0 | AD125: =[1]contras!AW41 -> 0 | AE125: =[1]contras!AX41 -> 0 | AF125: =[1]contras!AY41 -> 0 | AG125: =[1]contras!AZ41 -> 0 | ... CS125: =[1]contras!DL41 -> 0
C126: =CONCATENATE(D126,E126) -> GROWTH "HIT" PHWholesale | D126: =[1]Key!C$14 -> GROWTH "HIT" PH | E126: =[1]Key!D$14 -> Wholesale | Z126: =[1]contras!AS42 -> 0 | AA126: =[1]contras!AT42 -> 0 | AB126: =[1]contras!AU42 -> 0 | AC126: =[1]contras!AV42 -> 0 | AD126: =[1]contras!AW42 -> 0 | AE126: =[1]contras!AX42 -> 0 | AF126: =[1]contras!AY42 -> 0 | AG126: =[1]contras!AZ42 -> 0 | ... CS126: =[1]contras!DL42 -> 0
C127: =CONCATENATE(D127,E127) -> ICE STUDIOSWholesale | D127: =[1]Key!C$15 -> ICE STUDIOS | E127: =[1]Key!D$15 -> Wholesale | Z127: =[1]contras!AS43 -> 0 | AA127: =[1]contras!AT43 -> 0 | AB127: =[1]contras!AU43 -> 0 | AC127: =[1]contras!AV43 -> 0 | AD127: =[1]contras!AW43 -> 0 | AE127: =[1]contras!AX43 -> 0 | AF127: =[1]contras!AY43 -> 0 | AG127: =[1]contras!AZ43 -> 0 | ... CS127: =[1]contras!DL43 -> 4504500
C128: =CONCATENATE(D128,E128) -> MURAKAMI / TORITONWholesale | D128: =[1]Key!C$16 -> MURAKAMI / TORITON | E128: =[1]Key!D$16 -> Wholesale | Z128: =[1]contras!AS44 -> 0 | AA128: =[1]contras!AT44 -> 0 | AB128: =[1]contras!AU44 -> 316800 | AC128: =[1]contras!AV44 -> 33000 | AD128: =[1]contras!AW44 -> 0 | AE128: =[1]contras!AX44 -> 0 | AF128: =[1]contras!AY44 -> 0 | AG128: =[1]contras!AZ44 -> 0 | ... CS128: =[1]contras!DL44 -> 606375
C129: =CONCATENATE(D129,E129) -> NEW PARTNER 1Wholesale | D129: =[1]Key!C$17 -> NEW PARTNER 1 | E129: =[1]Key!D$17 -> Wholesale | Z129: =[1]contras!AS45 -> 0 | AA129: =[1]contras!AT45 -> 0 | AB129: =[1]contras!AU45 -> 0 | AC129: =[1]contras!AV45 -> 0 | AD129: =[1]contras!AW45 -> 0 | AE129: =[1]contras!AX45 -> 0 | AF129: =[1]contras!AY45 -> 0 | AG129: =[1]contras!AZ45 -> 0 | ... CS129: =[1]contras!DL45 -> 0
...

Sheet ActBS
B1: Wood/Mangan Footwear, LLC
B2: Balance Sheet | N2: *Manual input of Other Receivable in row32, for Fry Guy Revenue
B3: As of December 31, 2023
B4: **Actuals through Dec23, estimates through '26
A5: Mapping | C5: Jan 2023 | D5: Feb 2023 | E5: Mar 2023 | F5: Apr 2023 | G5: May 2023 | H5: Jun 2023 | I5: Jul 2023 | J5: Aug 2023 | K5: Sep 2023 | L5: Oct 2023 | M5: Nov 2023 | N5: Dec 2023 | O5: =BS!AC11 -> 45322 | P5: =BS!AD11 -> 45351 | Q5: =BS!AE11 -> 45382 | R5: =BS!AF11 -> 45412 | S5: =BS!AG11 -> 45443 | T5: =BS!AH11 -> 45473 | U5: =BS!AI11 -> 45504 | V5: =BS!AJ11 -> 45535 | ... CH5: =BS!CV11 -> 47483
B6: ASSETS
B7: Current Assets
B8: Bank Accounts
A9: Cash | B9: 1000 Cash | D9: =C9 -> 0 | E9: =D9 -> 0 | F9: =E9 -> 0 | G9: =F9 -> 0 | H9: =G9 -> 0 | I9: =H9 -> 0 | J9: =I9 -> 0 | K9: =J9 -> 0 | ... N9: =M9 -> 0
A10: Cash | B10: 1090 Shopify Clearing | D10: =C10 -> 0 | E10: =D10 -> 0 | F10: =E10 -> 0 | G10: =F10 -> 0 | H10: =G10 -> 0 | I10: =H10 -> 0 | J10: =I10 -> 0 | K10: =J10 -> 0 | ... N10: =M10 -> 0
A11: Cash | B11: Bank 1 | D11: =C11 -> 0 | E11: =D11 -> 0 | F11: =E11 -> 0 | G11: =F11 -> 0 | H11: =G11 -> 0 | I11: =H11 -> 0 | J11: =I11 -> 0 | K11: =625000 -> 625000 | L11: =K11 -> 625000 | M11: =L11 -> 625000 | N11: =M11 -> 625000
A12: Cash | B12: CNB Operating (8899) | C12: =15260683.88 -> 15260684 | D12: =14914438.02 -> 14914438 | E12: =644444.52 -> 644444.52 | F12: =304810.3 -> 304810.3 | G12: =218152.67 -> 218152.67 | H12: =149996.24 -> 149996.24 | I12: =124370.96 -> 124370.96 | J12: =410079.82 -> 410079.82 | K12: =727952.88 -> 727952.88 | L12: =678955.36 -> 678955.36 | M12: =180231.93 -> 180231.93 | N12: =79531.19 -> 79531.19
A13: Cash | B13: CNB Savings (9725) | C13: =0 -> 0 | D13: =C13 -> 0 | E13: =13727869.18 -> 13727869 | F13: =13772625.81 -> 13772626 | G13: =13327201.69 -> 13327202 | H13: =12875076.28 -> 12875076 | I13: =12523428.81 -> 12523429 | J13: =6407521.62 -> 6407521.6 | K13: =5406124.33 -> 5406124.3 | L13: =5428637.5 -> 5428637.5 | M13: =5449831.5 -> 5449831.5 | N13: =4518674.7 -> 4518674.7
B14: Total 1000 Cash | C14: =((((C9)+(C10))+(C11))+(C12))+(C13) -> 15260684 | D14: =((((D9)+(D10))+(D11))+(D12))+(D13) -> 14914438 | E14: =((((E9)+(E10))+(E11))+(E12))+(E13) -> 14372314 | F14: =((((F9)+(F10))+(F11))+(F12))+(F13) -> 14077436 | G14: =((((G9)+(G10))+(G11))+(G12))+(G13) -> 13545354 | H14: =((((H9)+(H10))+(H11))+(H12))+(H13) -> 13025073 | I14: =((((I9)+(I10))+(I11))+(I12))+(I13) -> 12647800 | J14: =((((J9)+(J10))+(J11))+(J12))+(J13) -> 6817601.4 | ... N14: =((((N9)+(N10))+(N11))+(N12))+(N13) -> 5223205.9
A15: Cash | B15: 1072 Bill.com Money Out Clearing | D15: =C15 -> 0 | E15: =D15 -> 0 | F15: =0 -> 0 | G15: =0 -> 0 | H15: =0 -> 0 | I15: =0 -> 0 | J15: =21666.67 -> 21666.67 | K15: =0 -> 0 | L15: =0 -> 0 | M15: =0 -> 0 | N15: =0 -> 0
A16: Cash | B16: 1073 Bill.com Money In Clearing | D16: =C16 -> 0 | E16: =D16 -> 0 | F16: =E16 -> 0 | G16: =F16 -> 0 | H16: =G16 -> 0 | I16: =H16 -> 0 | J16: =I16 -> 0 | K16: =J16 -> 0 | ... N16: =M16 -> 0
B17: Total Bank Accounts | C17: =((C14)+(C15))+(C16) -> 15260684 | D17: =((D14)+(D15))+(D16) -> 14914438 | E17: =((E14)+(E15))+(E16) -> 14372314 | F17: =((F14)+(F15))+(F16) -> 14077436 | G17: =((G14)+(G15))+(G16) -> 13545354 | H17: =((H14)+(H15))+(H16) -> 13025073 | I17: =((I14)+(I15))+(I16) -> 12647800 | J17: =((J14)+(J15))+(J16) -> 6839268.1 | ... N17: =((N14)+(N15))+(N16) -> 5223205.9
B18: Accounts Receivable
A19: Accounts Receivable | B19: 1200 Accounts Receivable | C19: =30690 -> 30690 | D19: =C19 -> 30690 | E19: =203961.29 -> 203961.29 | F19: =182201.43 -> 182201.43 | G19: =190946.43 -> 190946.43 | H19: =198206.43 -> 198206.43 | I19: =206951.43 -> 206951.43 | J19: =215696.43 -> 215696.43 | K19: =224441.43 -> 224441.43 | L19: =271121.91 -> 271121.91 | M19: =97494.86 -> 97494.86 | N19: =146754.86 -> 146754.86 | O19: =WC!Z5 -> 42000 | P19: =WC!AA5 -> 42000 | Q19: =WC!AB5 -> 402000 | R19: =WC!AC5 -> 439500 | S19: =WC!AD5 -> 79500 | T19: =WC!AE5 -> 42000 | U19: =WC!AF5 -> 42000 | V19: =WC!AG5 -> 42000 | ... CH19: =WC!CS5 -> 17836594
B20: Total Accounts Receivable | C20: =C19 -> 30690 | D20: =D19 -> 30690 | E20: =E19 -> 203961.29 | F20: =F19 -> 182201.43 | G20: =G19 -> 190946.43 | H20: =H19 -> 198206.43 | I20: =I19 -> 206951.43 | J20: =J19 -> 215696.43 | ... N20: =N19 -> 146754.86
B21: Other Current Assets
A22: Inventory | B22: 1300 Inventory | D22: =C22 -> 0 | E22: =D22 -> 0 | F22: =E22 -> 0 | G22: =F22 -> 0 | H22: =G22 -> 0 | I22: =H22 -> 0 | J22: =I22 -> 0 | K22: =J22 -> 0 | ... N22: =M22 -> 0
A23: Inventory | B23: 1305 Finished Goods | D23: =C23 -> 0 | E23: =D23 -> 0 | F23: =E23 -> 0 | G23: =F23 -> 0 | H23: =G23 -> 0 | I23: =H23 -> 0 | J23: =I23 -> 0 | K23: =J23 -> 0 | ... N23: =M23 -> 0
A24: Inventory | B24: 1310 Raw Materials | D24: =C24 -> 0 | E24: =D24 -> 0 | F24: =E24 -> 0 | G24: =F24 -> 0 | H24: =G24 -> 0 | I24: =H24 -> 0 | J24: =I24 -> 0 | K24: =J24 -> 0 | ... N24: =M24 -> 0
A25: Inventory | B25: 1315 Packaging | D25: =C25 -> 0 | E25: =D25 -> 0 | F25: =E25 -> 0 | G25: =F25 -> 0 | H25: =G25 -> 0 | I25: =H25 -> 0 | J25: =I25 -> 0 | K25: =J25 -> 0 | L25: =K25 -> 0 | M25: =1161.84 -> 1161.84 | N25: =M25 -> 1161.84 | O25: =WC!Z4 -> 138720 | P25: =WC!AA4 -> 153170 | Q25: =WC!AB4 -> 14450 | R25: =WC!AC4 -> 14450 | S25: =WC!AD4 -> 361250 | T25: =WC!AE4 -> 346800 | U25: =WC!AF4 -> 28900 | V25: =WC!AG4 -> 53200 | ... CH25: =WC!CS4 -> 31901639
B26: Total 1300 Inventory | C26: =(((C22)+(C23))+(C24))+(C25) -> 0 | D26: =(((D22)+(D23))+(D24))+(D25) -> 0 | E26: =(((E22)+(E23))+(E24))+(E25) -> 0 | F26: =(((F22)+(F23))+(F24))+(F25) -> 0 | G26: =(((G22)+(G23))+(G24))+(G25) -> 0 | H26: =(((H22)+(H23))+(H24))+(H25) -> 0 | I26: =(((I22)+(I23))+(I24))+(I25) -> 0 | J26: =(((J22)+(J23))+(J24))+(J25) -> 0 | ... N26: =(((N22)+(N23))+(N24))+(N25) -> 1161.84
A27: Prepaid Expenses | B27: 1400 Prepaids | D27: =C27 -> 0 | E27: =D27 -> 0 | F27: =E27 -> 0 | G27: =F27 -> 0 | H27: =G27 -> 0 | I27: =H27 -> 0 | J27: =I27 -> 0 | K27: =J27 -> 0 | ... N27: =M27 -> 0
A28: Prepaid Expenses | B28: 1405 Prepaid Inventory | D28: =C28 -> 0 | E28: =D28 -> 0 | F28: =E28 -> 0 | G28: =F28 -> 0 | H28: =G28 -> 0 | I28: =H28 -> 0 | J28: =I28 -> 0 | K28: =J28 -> 0 | ... N28: =M28 -> 0
A29: Prepaid Expenses | B29: 1410 Other Prepaid Expenses | C29: =103446.18 -> 103446.18 | D29: =88779.32 -> 88779.32 | E29: =96112.46 -> 96112.46 | F29: =88859.33 -> 88859.33 | G29: =198797.41 -> 198797.41 | H29: =187655.66 -> 187655.66 | I29: =169055.8 -> 169055.8 | J29: =200802.96 -> 200802.96 | K29: =176435.23 -> 176435.23 | L29: =162213.94 -> 162213.94 | M29: =136301.64 -> 136301.64 | N29: =101582.23 -> 101582.23 | O29: =[1]BSSched!AV51+$N$29 -> 101582.23 | P29: =[1]BSSched!AW51+$N$29 -> 1101582.2 | Q29: =[1]BSSched!AX51+$N$29 -> 1059915.6 | R29: =[1]BSSched!AY51+$N$29 -> 1018248.9 | S29: =[1]BSSched!AZ51+$N$29 -> 976582.23 | T29: =[1]BSSched!BA51+$N$29 -> 934915.56 | U29: =[1]BSSched!BB51+$N$29 -> 893248.9 | V29: =[1]BSSched!BC51+$N$29 -> 851582.23 | ... CH29: =[1]BSSched!DO51+$N$29 -> 101582.23
B30: Total 1400 Prepaids | C30: =((C27)+(C28))+(C29) -> 103446.18 | D30: =((D27)+(D28))+(D29) -> 88779.32 | E30: =((E27)+(E28))+(E29) -> 96112.46 | F30: =((F27)+(F28))+(F29) -> 88859.33 | G30: =((G27)+(G28))+(G29) -> 198797.41 | H30: =((H27)+(H28))+(H29) -> 187655.66 | I30: =((I27)+(I28))+(I29) -> 169055.8 | J30: =((J27)+(J28))+(J29) -> 200802.96 | ... N30: =((N27)+(N28))+(N29) -> 101582.23
A31: Other Current Assets | B31: Inventory Asset | D31: =C31 -> 0 | E31: =D31 -> 0 | F31: =E31 -> 0 | G31: =F31 -> 0 | H31: =G31 -> 0 | I31: =H31 -> 0 | J31: =I31 -> 0 | K31: =J31 -> 0 | ... N31: =M31 -> 0
A32: Other Current Assets | B32: Uncategorized Asset | D32: =C32 -> 0 | E32: =D32 -> 0 | F32: =E32 -> 0 | G32: =F32 -> 0 | H32: =G32 -> 0 | I32: =H32 -> 0 | J32: =I32 -> 0 | K32: =J32 -> 0 | ... M32: =L32 -> 0 | N32: 389084
A33: Other Current Assets | B33: Undeposited Funds | D33: =C33 -> 0 | E33: =D33 -> 0 | F33: =E33 -> 0 | G33: =F33 -> 0 | H33: =G33 -> 0 | I33: =H33 -> 0 | J33: =I33 -> 0 | K33: =J33 -> 0 | ... N33: =M33 -> 0
B34: Total Other Current Assets | C34: =((((C26)+(C30))+(C31))+(C32))+(C33) -> 103446.18 | D34: =((((D26)+(D30))+(D31))+(D32))+(D33) -> 88779.32 | E34: =((((E26)+(E30))+(E31))+(E32))+(E33) -> 96112.46 | F34: =((((F26)+(F30))+(F31))+(F32))+(F33) -> 88859.33 | G34: =((((G26)+(G30))+(G31))+(G32))+(G33) -> 198797.41 | H34: =((((H26)+(H30))+(H31))+(H32))+(H33) -> 187655.66 | I34: =((((I26)+(I30))+(I31))+(I32))+(I33) -> 169055.8 | J34: =((((J26)+(J30))+(J31))+(J32))+(J33) -> 200802.96 | ... N34: =((((N26)+(N30))+(N31))+(N32))+(N33) -> 491828.07
B35: Total Current Assets | C35: =((C17)+(C20))+(C34) -> 15394820 | D35: =((D17)+(D20))+(D34) -> 15033907 | E35: =((E17)+(E20))+(E34) -> 14672387 | F35: =((F17)+(F20))+(F34) -> 14348497 | G35: =((G17)+(G20))+(G34) -> 13935098 | H35: =((H17)+(H20))+(H34) -> 13410935 | I35: =((I17)+(I20))+(I34) -> 13023807 | J35: =((J17)+(J20))+(J34) -> 7255767.5 | ... N35: =((N17)+(N20))+(N34) -> 5861788.8
B36: Fixed Assets
A37: Fixed Assets, net | B37: 1700 Fixed Assets | D37: =C37 -> 0 | E37: =D37 -> 0 | F37: =E37 -> 0 | G37: =F37 -> 0 | H37: =G37 -> 0 | I37: =H37 -> 0 | J37: =I37 -> 0 | K37: =J37 -> 0 | ... CH37: =CG37 -> 0
A38: Fixed Assets, net | B38: 1710 Furniture & Fixtures | C38: =88196.9 -> 88196.9 | D38: =179275.56 -> 179275.56 | E38: =194757.22 -> 194757.22 | F38: =E38 -> 194757.22 | G38: =218498.89 -> 218498.89 | H38: =271228.71 -> 271228.71 | I38: =276706.46 -> 276706.46 | J38: =278393.29 -> 278393.29 | K38: =352689.08 -> 352689.08 | L38: =K38 -> 352689.08 | M38: =364212.73 -> 364212.73 | N38: =M38 -> 364212.73 | O38: =N38 -> 364212.73 | P38: =O38 -> 364212.73 | Q38: =P38 -> 364212.73 | R38: =Q38 -> 364212.73 | S38: =R38 -> 364212.73 | T38: =S38 -> 364212.73 | U38: =T38 -> 364212.73 | ... CH38: =CG38 -> 364212.73
A39: Fixed Assets, net | B39: 1711 Furniture & Fixtures - Accum Depr | C39: =-2099.92 -> -2099.92 | D39: =-4150.47 -> -4150.47 | E39: =-6385.33 -> -6385.33 | F39: =-8620.19 -> -8620.19 | G39: =-11137.69 -> -11137.69 | H39: =-14366.61 -> -14366.61 | I39: =-17660.74 -> -17660.74 | J39: =-20974.95 -> -20974.95 | K39: =-25173.63 -> -25173.63 | L39: =-29372.31 -> -29372.31 | M39: =-33708.18 -> -33708.18 | N39: =-38044.05 -> -38044.05 | O39: =N39+O126 -> -51634.412 | P39: =O39+P126 -> -65224.773 | Q39: =P39+Q126 -> -78815.135 | R39: =Q39+R126 -> -92405.497 | S39: =R39+S126 -> -105995.86 | T39: =S39+T126 -> -119586.22 | U39: =T39+U126 -> -133176.58 | V39: =U39+V126 -> -146766.94 | ... CH39: =CG39+CH126 -> -364212.73
A40: Fixed Assets, net | B40: 1712 Office and Computer Equipment | C40: =9978.72 -> 9978.72 | D40: =C40 -> 9978.72 | E40: =38141.85 -> 38141.85 | F40: =41313.39 -> 41313.39 | G40: =F40 -> 41313.39 | H40: =G40 -> 41313.39 | I40: =49189.39 -> 49189.39 | J40: =54133.12 -> 54133.12 | K40: =55162.38 -> 55162.38 | L40: =58780.52 -> 58780.52 | M40: =61328.82 -> 61328.82 | N40: =M40 -> 61328.82 | O40: =N40 -> 61328.82 | P40: =O40 -> 61328.82 | Q40: =P40 -> 61328.82 | R40: =Q40 -> 61328.82 | S40: =R40 -> 61328.82 | T40: =S40 -> 61328.82 | U40: =T40 -> 61328.82 | ... CH40: =CG40 -> 61328.82
A41: Fixed Assets, net | B41: 1713 Office Equip - Accum Depr | C41: =-166.31 -> -166.31 | D41: =-332.62 -> -332.62 | E41: =-933.67 -> -933.67 | F41: =-1622.24 -> -1622.24 | G41: =-2310.81 -> -2310.81 | H41: =-2999.37 -> -2999.37 | I41: =-3784.46 -> -3784.46 | J41: =-4686.69 -> -4686.69 | K41: =-5606.07 -> -5606.07 | L41: =-6585.75 -> -6585.75 | M41: =-7607.9 -> -7607.9 | N41: =-8630.05 -> -8630.05 | O41: =N41+O130 -> -10825.832 | P41: =O41+P130 -> -13021.614 | Q41: =P41+Q130 -> -15217.396 | R41: =Q41+R130 -> -17413.178 | S41: =R41+S130 -> -19608.96 | T41: =S41+T130 -> -21804.743 | U41: =T41+U130 -> -24000.525 | V41: =U41+V130 -> -26196.307 | ... CH41: =CG41+CH130 -> -61328.82
B42: Total 1700 Fixed Assets | C42: =((((C37)+(C38))+(C39))+(C40))+(C41) -> 95909.39 | D42: =((((D37)+(D38))+(D39))+(D40))+(D41) -> 184771.19 | E42: =((((E37)+(E38))+(E39))+(E40))+(E41) -> 225580.07 | F42: =((((F37)+(F38))+(F39))+(F40))+(F41) -> 225828.18 | G42: =((((G37)+(G38))+(G39))+(G40))+(G41) -> 246363.78 | H42: =((((H37)+(H38))+(H39))+(H40))+(H41) -> 295176.12 | I42: =((((I37)+(I38))+(I39))+(I40))+(I41) -> 304450.65 | J42: =((((J37)+(J38))+(J39))+(J40))+(J41) -> 306864.77 | ... N42: =((((N37)+(N38))+(N39))+(N40))+(N41) -> 378867.45
A43: Fixed Assets, net | B43: Furniture & Fixture - Accum Capex | D43: =C43 -> 0 | E43: =D43 -> 0 | F43: =E43 -> 0 | G43: =F43 -> 0 | H43: =G43 -> 0 | I43: =H43 -> 0 | J43: =I43 -> 0 | K43: =J43 -> 0 | ... N43: =M43 -> 0 | O43: =[1]BSSched!AV43 -> 0 | P43: =[1]BSSched!AW43 -> 0 | Q43: =[1]BSSched!AX43 -> 415000 | R43: =[1]BSSched!AY43 -> 415000 | S43: =[1]BSSched!AZ43 -> 415000 | T43: =[1]BSSched!BA43 -> 415000 | U43: =[1]BSSched!BB43 -> 415000 | V43: =[1]BSSched!BC43 -> 415000 | ... CH43: =[1]BSSched!DO43 -> 4452145
A44: Fixed Assets, net | B44: Furniture & Fixtures (deleted) - Accum Depr related to Capex | D44: =C44 -> 0 | E44: =D44 -> 0 | F44: =E44 -> 0 | G44: =F44 -> 0 | H44: =G44 -> 0 | I44: =H44 -> 0 | J44: =I44 -> 0 | K44: =J44 -> 0 | ... N44: =M44 -> 0 | O44: =-[1]BSSched!AV46 -> 0 | P44: =-[1]BSSched!AW46 -> 0 | Q44: =-[1]BSSched!AX46 -> -17291.667 | R44: =-[1]BSSched!AY46 -> -34583.333 | S44: =-[1]BSSched!AZ46 -> -51875 | T44: =-[1]BSSched!BA46 -> -69166.667 | U44: =-[1]BSSched!BB46 -> -86458.333 | V44: =-[1]BSSched!BC46 -> -103750 | ... CH44: =-[1]BSSched!DO46 -> -5299645
A45: Fixed Assets, net | B45: Leasehold Improvement | D45: =C45 -> 0 | E45: =D45 -> 0 | F45: =E45 -> 0 | G45: =F45 -> 0 | H45: =G45 -> 0 | I45: =H45 -> 0 | J45: =I45 -> 0 | K45: =J45 -> 0 | ... N45: =M45 -> 0
A46: Fixed Assets, net | B46: Leasehold Improvements (deleted) | D46: =C46 -> 0 | E46: =D46 -> 0 | F46: =E46 -> 0 | G46: =F46 -> 0 | H46: =G46 -> 0 | I46: =H46 -> 0 | J46: =I46 -> 0 | K46: =J46 -> 0 | ... N46: =M46 -> 0
A47: Fixed Assets, net | B47: Office and Computer Equipment | D47: =C47 -> 0 | E47: =D47 -> 0 | F47: =E47 -> 0 | G47: =F47 -> 0 | H47: =G47 -> 0 | I47: =H47 -> 0 | J47: =I47 -> 0 | K47: =J47 -> 0 | ... N47: =M47 -> 0
B48: Total Fixed Assets | C48: =(((((C42)+(C43))+(C44))+(C45))+(C46))+(C47) -> 95909.39 | D48: =(((((D42)+(D43))+(D44))+(D45))+(D46))+(D47) -> 184771.19 | E48: =(((((E42)+(E43))+(E44))+(E45))+(E46))+(E47) -> 225580.07 | F48: =(((((F42)+(F43))+(F44))+(F45))+(F46))+(F47) -> 225828.18 | G48: =(((((G42)+(G43))+(G44))+(G45))+(G46))+(G47) -> 246363.78 | H48: =(((((H42)+(H43))+(H44))+(H45))+(H46))+(H47) -> 295176.12 | I48: =(((((I42)+(I43))+(I44))+(I45))+(I46))+(I47) -> 304450.65 | J48: =(((((J42)+(J43))+(J44))+(J45))+(J46))+(J47) -> 306864.77 | ... N48: =(((((N42)+(N43))+(N44))+(N45))+(N46))+(N47) -> 378867.45
B49: Other Assets
A50: Intangibles | B50: 1800 Intangible Assets | D50: =C50 -> 0 | E50: =D50 -> 0 | F50: =E50 -> 0 | G50: =F50 -> 0 | H50: =G50 -> 0 | I50: =H50 -> 0 | J50: =I50 -> 0 | K50: =J50 -> 0 | ... CH50: =CG50 -> 0
A51: Intangibles | B51: 1720 Leasehold Improvements Asset | C51: =175593.65 -> 175593.65 | D51: =180931.23 -> 180931.23 | E51: =125965.02 -> 125965.02 | F51: =139356.44 -> 139356.44 | G51: =145081.44 -> 145081.44 | H51: =G51 -> 145081.44 | I51: =H51 -> 145081.44 | J51: =I51 -> 145081.44 | K51: =J51 -> 145081.44 | L51: =K51 -> 145081.44 | M51: =L51 -> 145081.44 | N51: =M51 -> 145081.44 | O51: =N51 -> 145081.44 | ... CH51: =CG51 -> 145081.44
A52: Intangibles | B52: 1721 Leasehold Improv. - Accum Depr | D52: =C52 -> 0 | E52: =-12596.5 -> -12596.5 | F52: =-26618.84 -> -26618.84 | G52: =-41426.66 -> -41426.66 | H52: =-56234.48 -> -56234.48 | I52: =-71042.3 -> -71042.3 | J52: =-85850.12 -> -85850.12 | K52: =-100657.94 -> -100657.94 | L52: =-115465.76 -> -115465.76 | M52: =-130273.58 -> -130273.58 | N52: =-145081.44 -> -145081.44 | O52: =N52 -> -145081.44 | P52: =O52 -> -145081.44 | Q52: =P52 -> -145081.44 | R52: =Q52 -> -145081.44 | S52: =R52 -> -145081.44 | T52: =S52 -> -145081.44 | U52: =T52 -> -145081.44 | V52: =U52 -> -145081.44 | ... CH52: =CG52 -> -145081.44
A53: Intangibles | B53: 1805 Organizational Costs | C53: =0 -> 0 | D53: =C53 -> 0 | E53: =D53 -> 0 | F53: =E53 -> 0 | G53: =F53 -> 0 | H53: =G53 -> 0 | I53: =H53 -> 0 | J53: =I53 -> 0 | K53: =J53 -> 0 | ... CH53: =CG53 -> 0
A54: Intangibles | B54: 1806 Organizational Costs - Amortization | D54: =C54 -> 0 | E54: =D54 -> 0 | F54: =E54 -> 0 | G54: =F54 -> 0 | H54: =G54 -> 0 | I54: =H54 -> 0 | J54: =I54 -> 0 | K54: =J54 -> 0 | ... CH54: =CG54 -> 0
A55: Intangibles | B55: 1810 Start-Up Costs | C55: =0 -> 0 | D55: =C55 -> 0 | E55: =D55 -> 0 | F55: =E55 -> 0 | G55: =F55 -> 0 | H55: =G55 -> 0 | I55: =H55 -> 0 | J55: =I55 -> 0 | K55: =J55 -> 0 | ... CH55: =CG55 -> 0
A56: Intangibles | B56: 1811 Start-Up Costs - Amortization | D56: =C56 -> 0 | E56: =D56 -> 0 | F56: =E56 -> 0 | G56: =F56 -> 0 | H56: =G56 -> 0 | I56: =H56 -> 0 | J56: =I56 -> 0 | K56: =J56 -> 0 | ... CH56: =CG56 -> 0
B57: Total 1800 Intangible Assets | C57: =((((((C50)+(C51))+(C52))+(C53))+(C54))+(C55))+(C56) -> 175593.65 | D57: =((((((D50)+(D51))+(D52))+(D53))+(D54))+(D55))+(D56) -> 180931.23 | E57: =((((((E50)+(E51))+(E52))+(E53))+(E54))+(E55))+(E56) -> 113368.52 | F57: =((((((F50)+(F51))+(F52))+(F53))+(F54))+(F55))+(F56) -> 112737.6 | G57: =((((((G50)+(G51))+(G52))+(G53))+(G54))+(G55))+(G56) -> 103654.78 | H57: =((((((H50)+(H51))+(H52))+(H53))+(H54))+(H55))+(H56) -> 88846.96 | I57: =((((((I50)+(I51))+(I52))+(I53))+(I54))+(I55))+(I56) -> 74039.14 | J57: =((((((J50)+(J51))+(J52))+(J53))+(J54))+(J55))+(J56) -> 59231.32 | ... N57: =((((((N50)+(N51))+(N52))+(N53))+(N54))+(N55))+(N56) -> 0
A58: Other Assets | B58: 1850 Deposits | C58: =35000 -> 35000 | D58: =C58 -> 35000 | E58: =D58 -> 35000 | F58: =E58 -> 35000 | G58: =42500 -> 42500 | H58: =G58 -> 42500 | I58: =H58 -> 42500 | J58: =I58 -> 42500 | K58: =J58 -> 42500 | L58: =K58 -> 42500 | M58: =L58 -> 42500 | N58: =M58 -> 42500 | O58: =N58 -> 42500 | ... CH58: =CG58 -> 42500
A59: Investments | B59: 1900 Investment in Brain Dead LLC | D59: =C59 -> 0 | E59: =D59 -> 0 | F59: =E59 -> 0 | G59: =F59 -> 0 | H59: =G59 -> 0 | I59: =H59 -> 0 | J59: =3250000 -> 3250000 | K59: =J59 -> 3250000 | L59: =K59 -> 3250000 | M59: =L59 -> 3250000 | N59: =M59 -> 3250000 | O59: =N59 -> 3250000 | P59: =O59 -> 3250000 | Q59: =P59 -> 3250000 | R59: =Q59 -> 3250000 | ... CH59: =CG59 -> 3250000
A60: Notes Receivable | B60: 1910 Promissory Note (Brain Dead Amusement LLC) | D60: =C60 -> 0 | E60: =D60 -> 0 | F60: =E60 -> 0 | G60: =F60 -> 0 | H60: =G60 -> 0 | I60: =H60 -> 0 | J60: =2000000 -> 2000000 | K60: =J60 -> 2000000 | L60: =K60 -> 2000000 | M60: =L60 -> 2000000 | N60: =M60 -> 2000000 | O60: =-[1]Int!AS16+N60 -> 2000000 | P60: =-[1]Int!AT16+O60 -> 2000000 | Q60: =-[1]Int!AU16+P60 -> 2000000 | R60: =-[1]Int!AV16+Q60 -> 2000000 | S60: =-[1]Int!AW16+R60 -> 2000000 | T60: =-[1]Int!AX16+S60 -> 2000000 | U60: =-[1]Int!AY16+T60 -> 2000000 | V60: =-[1]Int!AZ16+U60 -> 2000000 | ... CH60: =-[1]Int!DL16+CG60 -> 0
A61: Other Current Assets | B61: 1911 Accrued Interest | D61: =C61 -> 0 | E61: =D61 -> 0 | F61: =E61 -> 0 | G61: =F61 -> 0 | H61: =G61 -> 0 | I61: =H61 -> 0 | J61: =I61 -> 0 | K61: =J61 -> 0 | ... M61: =L61 -> 0 | N61: =47014 -> 47014 | O61: =N61 -> 47014 | P61: =O61 -> 47014 | Q61: =P61 -> 47014 | R61: =Q61 -> 47014 | S61: =R61 -> 47014 | T61: =S61 -> 47014 | U61: =T61 -> 47014 | V61: =U61 -> 47014 | ... CH61: =CG61 -> 47014
B62: Total 1910 Promissory Note (Brain Dead Amusement LLC) | C62: =(C60)+(C61) -> 0 | D62: =(D60)+(D61) -> 0 | E62: =(E60)+(E61) -> 0 | F62: =(F60)+(F61) -> 0 | G62: =(G60)+(G61) -> 0 | H62: =(H60)+(H61) -> 0 | I62: =(I60)+(I61) -> 0 | J62: =(J60)+(J61) -> 2000000 | ... N62: =(N60)+(N61) -> 2047014
B63: Total Other Assets | C63: =(((C57)+(C58))+(C59))+(C62) -> 210593.65 | D63: =(((D57)+(D58))+(D59))+(D62) -> 215931.23 | E63: =(((E57)+(E58))+(E59))+(E62) -> 148368.52 | F63: =(((F57)+(F58))+(F59))+(F62) -> 147737.6 | G63: =(((G57)+(G58))+(G59))+(G62) -> 146154.78 | H63: =(((H57)+(H58))+(H59))+(H62) -> 131346.96 | I63: =(((I57)+(I58))+(I59))+(I62) -> 116539.14 | J63: =(((J57)+(J58))+(J59))+(J62) -> 5351731.3 | ... N63: =(((N57)+(N58))+(N59))+(N62) -> 5339514
B64: TOTAL ASSETS | C64: =((C35)+(C48))+(C63) -> 15701323 | D64: =((D35)+(D48))+(D63) -> 15434610 | E64: =((E35)+(E48))+(E63) -> 15046336 | F64: =((F35)+(F48))+(F63) -> 14722063 | G64: =((G35)+(G48))+(G63) -> 14327617 | H64: =((H35)+(H48))+(H63) -> 13837458 | I64: =((I35)+(I48))+(I63) -> 13444797 | J64: =((J35)+(J48))+(J63) -> 12914364 | ... N64: =((N35)+(N48))+(N63) -> 11580170
B65: LIABILITIES AND EQUITY
B66: Liabilities
B67: Current Liabilities
B68: Accounts Payable
A69: Accounts Payable | B69: 2000 Accounts Payable | C69: =33385.52 -> 33385.52 | D69: =55385.52 -> 55385.52 | E69: =48721.49 -> 48721.49 | F69: =60285.3 -> 60285.3 | G69: =133427.71 -> 133427.71 | H69: =115356.32 -> 115356.32 | I69: =218481.05 -> 218481.05 | J69: =295353.79 -> 295353.79 | K69: =358950.63 -> 358950.63 | L69: =422593.75 -> 422593.75 | M69: =386309.71 -> 386309.71 | N69: =437226.57 -> 437226.57 | O69: =WC!Z6 -> 783120.83 | P69: =WC!AA6 -> 153170 | Q69: =WC!AB6 -> 14450 | R69: =WC!AC6 -> 14450 | S69: =WC!AD6 -> 361250 | T69: =WC!AE6 -> 346800 | U69: =WC!AF6 -> 28900 | V69: =WC!AG6 -> 53200 | ... CH69: =WC!CS6 -> 31901639
B70: Total Accounts Payable | C70: =C69 -> 33385.52 | D70: =D69 -> 55385.52 | E70: =E69 -> 48721.49 | F70: =F69 -> 60285.3 | G70: =G69 -> 133427.71 | H70: =H69 -> 115356.32 | I70: =I69 -> 218481.05 | J70: =J69 -> 295353.79 | ... N70: =N69 -> 437226.57
B71: Credit Cards
A72: Accounts Payable | B72: 2100 Credit Cards | D72: =C72 -> 0 | E72: =D72 -> 0 | F72: =E72 -> 0 | G72: =F72 -> 0 | H72: =G72 -> 0 | I72: =H72 -> 0 | J72: =I72 -> 0 | K72: =J72 -> 0 | ... N72: =M72 -> 0
A73: Accounts Payable | B73: 2105 AmEx - 01009 | C73: =2252 -> 2252 | D73: =27805.18 -> 27805.18 | E73: =41117.27 -> 41117.27 | F73: =134589.69 -> 134589.69 | G73: =112121.54 -> 112121.54 | H73: =76764.66 -> 76764.66 | I73: =82675.28 -> 82675.28 | J73: =51034.82 -> 51034.82 | K73: =80103.71 -> 80103.71 | L73: =109043.94 -> 109043.94 | M73: =91559.66 -> 91559.66 | N73: =207174.26 -> 207174.26
B74: Total 2100 Credit Cards | C74: =(C72)+(C73) -> 2252 | D74: =(D72)+(D73) -> 27805.18 | E74: =(E72)+(E73) -> 41117.27 | F74: =(F72)+(F73) -> 134589.69 | G74: =(G72)+(G73) -> 112121.54 | H74: =(H72)+(H73) -> 76764.66 | I74: =(I72)+(I73) -> 82675.28 | J74: =(J72)+(J73) -> 51034.82 | ... N74: =(N72)+(N73) -> 207174.26
B75: Total Credit Cards | C75: =C74 -> 2252 | D75: =D74 -> 27805.18 | E75: =E74 -> 41117.27 | F75: =F74 -> 134589.69 | G75: =G74 -> 112121.54 | H75: =H74 -> 76764.66 | I75: =I74 -> 82675.28 | J75: =J74 -> 51034.82 | ... N75: =N74 -> 207174.26
B76: Other Current Liabilities
A77: Accrued Liabilities | B77: 2300 Accrued Expenses | C77: =-28880.7 -> -28880.7 | D77: =-30913.1 -> -30913.1 | E77: =D77 -> -30913.1 | F77: =0 -> 0 | G77: =11602 -> 11602 | H77: =32582.08 -> 32582.08 | I77: =140107.25 -> 140107.25 | J77: =94625.87 -> 94625.87 | K77: =26998.55 -> 26998.55 | L77: =131057.5 -> 131057.5 | M77: =102738 -> 102738 | N77: =98000.5 -> 98000.5 | O77: =N77 -> 98000.5 | P77: =O77 -> 98000.5 | Q77: =P77 -> 98000.5 | R77: =Q77 -> 98000.5 | S77: =R77 -> 98000.5 | T77: =S77 -> 98000.5 | U77: =T77 -> 98000.5 | V77: =U77 -> 98000.5 | ... CH77: =CG77 -> 98000.5
A78: Accrued Liabilities | B78: 2305 Payroll Liabilities | D78: =C78 -> 0 | E78: =D78 -> 0 | F78: =E78 -> 0 | G78: =F78 -> 0 | H78: =G78 -> 0 | I78: =H78 -> 0 | J78: =I78 -> 0 | K78: =J78 -> 0 | ... CH78: =CG78 -> 0
A79: Accrued Liabilities | B79: 2306 401K Liability | D79: =C79 -> 0 | E79: =D79 -> 0 | F79: =E79 -> 0 | G79: =F79 -> 0 | H79: =G79 -> 0 | I79: =H79 -> 0 | J79: =I79 -> 0 | K79: =J79 -> 0 | ... CH79: =CG79 -> 0
B80: Total 2305 Payroll Liabilities | C80: =(C78)+(C79) -> 0 | D80: =(D78)+(D79) -> 0 | E80: =(E78)+(E79) -> 0 | F80: =(F78)+(F79) -> 0 | G80: =(G78)+(G79) -> 0 | H80: =(H78)+(H79) -> 0 | I80: =(I78)+(I79) -> 0 | J80: =(J78)+(J79) -> 0 | ... N80: =(N78)+(N79) -> 0
A81: Accrued Liabilities | B81: 2310 Sales Tax Payable | D81: =C81 -> 0 | E81: =D81 -> 0 | F81: =E81 -> 0 | G81: =F81 -> 0 | H81: =G81 -> 0 | I81: =H81 -> 0 | J81: =I81 -> 0 | K81: =J81 -> 0 | ... CH81: =CG81 -> 0
B82: Total 2300 Accrued Expenses | C82: =((C77)+(C80))+(C81) -> -28880.7 | D82: =((D77)+(D80))+(D81) -> -30913.1 | E82: =((E77)+(E80))+(E81) -> -30913.1 | F82: =((F77)+(F80))+(F81) -> 0 | G82: =((G77)+(G80))+(G81) -> 11602 | H82: =((H77)+(H80))+(H81) -> 32582.08 | I82: =((I77)+(I80))+(I81) -> 140107.25 | J82: =((J77)+(J80))+(J81) -> 94625.87 | ... N82: =((N77)+(N80))+(N81) -> 98000.5
B83: Total Other Current Liabilities | C83: =C82 -> -28880.7 | D83: =D82 -> -30913.1 | E83: =E82 -> -30913.1 | F83: =F82 -> 0 | G83: =G82 -> 11602 | H83: =H82 -> 32582.08 | I83: =I82 -> 140107.25 | J83: =J82 -> 94625.87 | ... N83: =N82 -> 98000.5
B84: Total Current Liabilities | C84: =((C70)+(C75))+(C83) -> 6756.82 | D84: =((D70)+(D75))+(D83) -> 52277.6 | E84: =((E70)+(E75))+(E83) -> 58925.66 | F84: =((F70)+(F75))+(F83) -> 194874.99 | G84: =((G70)+(G75))+(G83) -> 257151.25 | H84: =((H70)+(H75))+(H83) -> 224703.06 | I84: =((I70)+(I75))+(I83) -> 441263.58 | J84: =((J70)+(J75))+(J83) -> 441014.48 | ... N84: =((N70)+(N75))+(N83) -> 742401.33
B85: Long-Term Liabilities
A86: Notes Payable | B86: 2800 Long Term Debt | D86: =C86 -> 0 | E86: =D86 -> 0 | F86: =E86 -> 0 | G86: =F86 -> 0 | H86: =G86 -> 0 | I86: =H86 -> 0 | J86: =I86 -> 0 | K86: =J86 -> 0 | ... CH86: =CG86 -> 0
A87: Notes Payable | B87: 2805 Luke Wood Loan | C87: =5000 -> 5000 | D87: =C87 -> 5000 | E87: =D87 -> 5000 | F87: =0 -> 0 | G87: =F87 -> 0 | H87: =G87 -> 0 | I87: =H87 -> 0 | J87: =I87 -> 0 | K87: =J87 -> 0 | L87: =K87 -> 0 | M87: =L87 -> 0 | N87: =M87 -> 0 | ... CH87: =CG87 -> 0
A88: Notes Payable | B88: 2890 Accrued Interest | D88: =C88 -> 0 | E88: =D88 -> 0 | F88: =E88 -> 0 | G88: =F88 -> 0 | H88: =G88 -> 0 | I88: =H88 -> 0 | J88: =I88 -> 0 | K88: =J88 -> 0 | ... CH88: =CG88 -> 0
B89: Total 2800 Long Term Debt | C89: =((C86)+(C87))+(C88) -> 5000 | D89: =((D86)+(D87))+(D88) -> 5000 | E89: =((E86)+(E87))+(E88) -> 5000 | F89: =((F86)+(F87))+(F88) -> 0 | G89: =((G86)+(G87))+(G88) -> 0 | H89: =((H86)+(H87))+(H88) -> 0 | I89: =((I86)+(I87))+(I88) -> 0 | J89: =((J86)+(J87))+(J88) -> 0 | ... N89: =((N86)+(N87))+(N88) -> 0
B90: Total Long-Term Liabilities | C90: =C89 -> 5000 | D90: =D89 -> 5000 | E90: =E89 -> 5000 | F90: =F89 -> 0 | G90: =G89 -> 0 | H90: =H89 -> 0 | I90: =I89 -> 0 | J90: =J89 -> 0 | ... N90: =N89 -> 0
B91: Total Liabilities | C91: =(C84)+(C90) -> 11756.82 | D91: =(D84)+(D90) -> 57277.6 | E91: =(E84)+(E90) -> 63925.66 | F91: =(F84)+(F90) -> 194874.99 | G91: =(G84)+(G90) -> 257151.25 | H91: =(H84)+(H90) -> 224703.06 | I91: =(I84)+(I90) -> 441263.58 | J91: =(J84)+(J90) -> 441014.48 | ... N91: =(N84)+(N90) -> 742401.33
B92: Equity
B93: 3000 Equity | D93: =C93 -> 0 | E93: =D93 -> 0 | F93: =E93 -> 0 | G93: =F93 -> 0 | H93: =G93 -> 0 | I93: =H93 -> 0 | J93: =I93 -> 0 | K93: =J93 -> 0 | ... N93: =M93 -> 0
A94: Units | B94: 3100 Member Contributions | D94: =C94 -> 0 | E94: =D94 -> 0 | F94: =E94 -> 0 | G94: =F94 -> 0 | H94: =G94 -> 0 | I94: =H94 -> 0 | J94: =I94 -> 0 | K94: =J94 -> 0 | ... CH94: =CG94 -> 0
A95: Units | B95: 3105 Member Contribution - 1868 Univeritas Fund LP | C95: =2500000 -> 2500000 | D95: =C95 -> 2500000 | E95: =D95 -> 2500000 | F95: =E95 -> 2500000 | G95: =F95 -> 2500000 | H95: =G95 -> 2500000 | I95: =H95 -> 2500000 | J95: =I95 -> 2500000 | K95: =J95 -> 2500000 | ... CH95: =CG95 -> 2500000
A96: Units | B96: 3110 Member Contribution - AsiaStar Growth Capital Limited | C96: =3000000 -> 3000000 | D96: =C96 -> 3000000 | E96: =D96 -> 3000000 | F96: =E96 -> 3000000 | G96: =F96 -> 3000000 | H96: =G96 -> 3000000 | I96: =H96 -> 3000000 | J96: =I96 -> 3000000 | K96: =3500000 -> 3500000 | L96: =4000000 -> 4000000 | M96: =L96 -> 4000000 | N96: =M96 -> 4000000 | O96: =N96 -> 4000000 | P96: =O96 -> 4000000 | Q96: =P96 -> 4000000 | R96: =Q96 -> 4000000 | S96: =R96 -> 4000000 | T96: =S96 -> 4000000 | ... CH96: =CG96 -> 4000000
A97: Units | B97: 3115 Member Contribution - C5 Footwear LLC | C97: =350000 -> 350000 | D97: =C97 -> 350000 | E97: =D97 -> 350000 | F97: =E97 -> 350000 | G97: =F97 -> 350000 | H97: =G97 -> 350000 | I97: =H97 -> 350000 | J97: =I97 -> 350000 | K97: =J97 -> 350000 | ... CH97: =CG97 -> 350000
A98: Units | B98: 3120 Member Contribution - Cannon Creatively LLC | C98: =500000 -> 500000 | D98: =C98 -> 500000 | E98: =D98 -> 500000 | F98: =E98 -> 500000 | G98: =F98 -> 500000 | H98: =G98 -> 500000 | I98: =H98 -> 500000 | J98: =I98 -> 500000 | K98: =J98 -> 500000 | ... CH98: =CG98 -> 500000
A99: Units | B99: 3125 Member Contribution - Carl Austin Rosen | C99: =500000 -> 500000 | D99: =C99 -> 500000 | E99: =D99 -> 500000 | F99: =E99 -> 500000 | G99: =F99 -> 500000 | H99: =G99 -> 500000 | I99: =H99 -> 500000 | J99: =I99 -> 500000 | K99: =J99 -> 500000 | ... CH99: =CG99 -> 500000
A100: Units | B100: 3130 Member Contribution - Electric Feel Ventures Fund I LP | C100: =500000 -> 500000 | D100: =C100 -> 500000 | E100: =D100 -> 500000 | F100: =E100 -> 500000 | G100: =F100 -> 500000 | H100: =G100 -> 500000 | I100: =H100 -> 500000 | J100: =I100 -> 500000 | K100: =J100 -> 500000 | ... CH100: =CG100 -> 500000
...
